Workbook
Name _Hlk189750054: #REF!

Sheet ÍNDICE
B2: COMPONENTES CURRICULARES ANOS FINAIS
B3: EDUCAÇÃO FINANCEIRA
B4: PRÁTICAS EXPERIMENTAIS
B5: PROJETO DE VIDA
B6: REDAÇÃO E LEITURA
B7: ROBÓTICA - PEI 9H
B8: TECNOLOGIA E INOVAÇÃO
B9: MATRIZ SOCIOEMOCIONAL PROJETO DE VIDA

Sheet Educação Financeira
A1: AULA COMPLEMENTAR | B1: CICLO | C1: ANO | D1: BIMESTRE | E1: AULA | F1: HABILIDADE - CÓDIGO | G1: HABILIDADE - TEXTO | H1: UNIDADE TEMÁTICA | I1: OBJETO DE CONHECIMENTO | J1: TÍTULO DA AULA | K1: CONTEÚDO | L1: OBJETIVOS
B2: Anos Finais | C2: 7º | D2: 1º | E2: 1 | F2: - EF05CO10 | G2: - Expressar-se crítica e criativamente na compreensão das mudanças tecnológicas no mundo do trabalho e sobre a evolução da sociedade. | H2: - Planejamento e gestão financeira. | I2: - Orçamento e controle financeiro. | J2: Como nos relacionamos com o dinheiro? ‒ Parte 1 | K2: - Dinheiro no cotidiano. - Relação pessoal com o dinheiro. | L2: - Reconhecer a presença do dinheiro no cotidiano. - Refletir sobre sua relação pessoal com o dinheiro. - Discutir sobre a importância da Educação Financeira nas suas escolhas.
B3: Anos Finais | C3: 7º | D3: 1º | E3: 2 | F3: - EF04GE08 | G3: - Descrever o processo de produção, circulação e consumo de diferentes produtos, reconhecendo as etapas da transformação da matéria-prima em produção de bens e alimentos e comparando a produção de resíduos, no seu município, Estado de São Paulo e em outras regiões do Brasil. | H3: - Planejamento e gestão financeira. | I3: - Orçamento e controle financeiro. | J3: Como nos relacionamos com o dinheiro? ‒ Parte 2 | K3: - Necessidades. - Desejos. - Itens de consumo básico. - Gastos do dia a dia. | L3: - Distinguir necessidades e desejos. - Identificar o custo de itens básicos e supérfluos. - Reconhecer a ideia de escolhas financeiras e suas consequências.
B4: Anos Finais | C4: 7º | D4: 1º | E4: 3 | F4: - EF03GE08A - EF06MA34 | G4: - Associar consumo à produção de resíduos, reconhecendo que o consumo excessivo e o descarte inadequado acarretam problemas socioambientais, em diferentes lugares - Interpretar e desenvolver fluxogramas simples, identificando as relações entre os objetos representados (por exemplo, posição de cidades considerando as estradas que as unem, hierarquia dos funcionários de uma empresa etc.). | H4: - Consumo, sustentabilidade e cidadania. | I4: - Consumo consciente e sustentável. | J4: Consumir com consciência: o que é e por que importa? | K4: - consumo consciente. - consumo sustentável. | L4: - Diferenciar consumo consciente de consumo sustentável, reconhecendo a importância de ambos para as decisões financeiras e para o bem-estar coletivo. - Representar esses conceitos por meio de um esquema visual.
B5: Anos Finais | C5: 7º | D5: 1º | E5: 4 | F5: - EF06MA11 | G5: - Resolver e elaborar problemas com números racionais positivos na representação decimal, envolvendo as quatro operações fundamentais e a potenciação, por meio de estratégias diversas, utilizando estimativas e arredondamentos para verificar a razoabilidade de respostas, com e sem uso de calculadora. | H5: - Planejamento e gestão financeira. | I5: - problemas com valores monetários. | J5: Consumo consciente no dia a dia: analisando nossos gastos ‒ Parte 1 | K5: - Tipos de gastos. - Rendas e despesas. - Entradas e saídas em um orçamento. | L5: - Identificar e classificar seus gastos cotidianos. - Reconhecer as noções básicas de renda e despesas. - Analisar casos envolvendo gastos diários.
B6: Anos Finais | C6: 7º | D6: 1º | E6: 5 | F6: - EF06MA11 | G6: - Resolver e elaborar problemas com números racionais positivos na representação decimal, envolvendo as quatro operações fundamentais e a potenciação, por meio de estratégias diversas, utilizando estimativas e arredondamentos para verificar a razoabilidade de respostas, com e sem uso de calculadora. | H6: - Planejamento e gestão financeira. | I6: - problemas com valores monetários. | J6: Consumo consciente no dia a dia: analisando nossos gastos ‒ Parte 2 | K6: - Tipos de gastos. - Rendas e despesas. - Entradas e saídas em um orçamento. | L6: - Resolver problemas envolvendo gastos diários.
B7: Anos Finais | C7: 7º | D7: 1º | E7: 6 | F7: - EF06MA11 | G7: - Resolver e elaborar problemas com números racionais positivos na representação decimal, envolvendo as quatro operações fundamentais e a potenciação, por meio de estratégias diversas, utilizando estimativas e arredondamentos para verificar a razoabilidade de respostas, com e sem uso de calculadora. | H7: - Planejamento e gestão financeira. | I7: - problemas com valores monetários. | J7: Consumo consciente no dia a dia: analisando nossos gastos ‒ Parte 3 | K7: - Tipos de gastos. - Rendas e despesas. - Entradas e saídas em um orçamento. | L7: - Elaborar problemas envolvendo gastos diários.
B8: Anos Finais | C8: 7º | D8: 1º | E8: 7 | F8: - EF06MA33 | G8: - Planejar e coletar dados de pesquisa referente a práticas sociais escolhidas pelos alunos e fazer uso de planilhas eletrônicas para registro, representação e interpretação das informações, em tabelas, vários tipos de gráficos e texto. | H8: - Planejamento e gestão financeira. | I8: - Orçamento e controle financeiro. | J8: O que é poupar? ‒ Parte 1 | K8: - conceito de poupar. | L8: - Definir o conceito de poupar. - Reconhecer a poupança como uma ação para o futuro.
B9: Anos Finais | C9: 7º | D9: 1º | E9: 8 | F9: - EF06MA11 | G9: - Resolver e elaborar problemas com números racionais positivos na representação decimal, envolvendo as quatro operações fundamentais e a potenciação, por meio de estratégias diversas, utilizando estimativas e arredondamentos para verificar a razoabilidade de respostas, com e sem uso de calculadora. | H9: - Planejamento e gestão financeira. | I9: - Orçamento e controle financeiro. | J9: O que é poupar? ‒ Parte 2 | K9: - conceito de poupar. - conceito de economizar. - estratégias de economia. | L9: - Diferenciar os conceitos de poupar e economizar.
B10: Anos Finais | C10: 7º | D10: 1º | E10: 9 | F10: - EF06MA11 | G10: - Resolver e elaborar problemas com números racionais positivos na representação decimal, envolvendo as quatro operações fundamentais e a potenciação, por meio de estratégias diversas, utilizando estimativas e arredondamentos para verificar a razoabilidade de respostas, com e sem uso de calculadora. | H10: - Planejamento e gestão financeira. | I10: - problemas com valores monetários. | J10: Calculando economias e poupanças ‒ Parte 1 | K10: - Cálculos com valores monetários. | L10: - Realizar cálculos simples para quantificar economias e poupanças, utilizando estratégias diversas e estimativas.
B11: Anos Finais | C11: 7º | D11: 1º | E11: 10 | F11: - EF05MA06 | G11: - Associar as representações 10%, 25%, 50%, 75% e 100% respectivamente à décima parte, quarta parte, metade, três quartos e um inteiro, para calcular porcentagens, utilizando estratégias pessoais, cálculo mental e calculadora, em contextos de educação financeira, entre outros. | H11: - Planejamento e gestão financeira. | I11: - problemas com valores monetários. | J11: Calculando economias e poupanças ‒ Parte 2 | K11: - Cálculos com valores monetários. | L11: - Realizar cálculos simples para quantificar economias e poupanças, utilizando estratégias diversas e estimativas.
B12: Anos Finais | C12: 7º | D12: 1º | E12: 11 | F12: - EF07GE06 | G12: - Analisar a apropriação dos recursos naturais pelas diferentes sociedades e discutir como os processos produtivos, a circulação e o consumo de mercadorias provocam impactos socioambientais e influem nas relações de trabalho e na distribuição de riquezas em diferentes lugares. | H12: - Consumo, sustentabilidade e cidadania. | I12: - Consumo consciente e sustentável. | J12: Consumo sustentável: o impacto das nossas escolhas no bolso e no meio ambiente ‒ Parte 1 | K12: - Decisões de consumo. - Custo/benefício. - Sustentabilidade. | L12: - Reconhecer o impacto das suas decisões de consumo no próprio orçamento, no meio ambiente e na sociedade.
B13: Anos Finais | C13: 7º | D13: 1º | E13: 12 | F13: - EF03GE08A - EF05CI04 | G13: - Associar consumo à produção de resíduos, reconhecendo que o consumo excessivo e o descarte inadequado acarretam problemas socioambientais, em diferentes lugares - Identificar os usos da água nas atividades cotidianas, do campo, no transporte, na indústria, no lazer e na geração de energia, para discutir e propor formas sustentáveis de utilização desse recurso. | H13: - Consumo, sustentabilidade e cidadania. | I13: - Consumo consciente e sustentável. | J13: Consumo sustentável: o impacto das nossas escolhas no bolso e no meio ambiente ‒ Parte 2 | K13: - Impacto do consumo. - Política dos 7Rs. - Sustentabilidade. - Economia. | L13: - Relacionar o consumo excessivo e a produção de lixo. - Propor estratégias de redução, reúso e reciclagem de materiais, visando a economia e o menor impacto.
... B105: Anos Finais | C105: 8º | D105: 4º | E105: 12 | F105: - EF69LP41 | G105: Usar adequadamente ferramentas de apoio a apresentações orais, escolhendo e usando tipos e tamanhos de fontes que permitam boa visualização, topicalizando e/ou organizando o conteúdo em itens, inserindo de forma adequada imagens, gráficos, tabelas, formas e elementos gráficos, dimensionando a quantidade de texto (e imagem) por slide, usando progressivamente e de forma harmônica recursos mais sofisticados como efeitos de transição, slides mestres, layouts personalizados etc. | H105: - Reflexão e fechamento. | I105: - Educação Financeira: Lições e Impactos. | J105: Projeto final: apresentando o Guia da Cidadania Financeira - Parte 2 | K105: Revisão dos principais aprendizados do ano - Reflexão coletiva sobre cidadania financeira | L105: Apresentar o guia de cidadania financeira e refletir sobre a importância da educação financeira.

Sheet Práticas Experimentais
A1: CICLO | B1: ANO | C1: BIMESTRE | D1: AULA | E1: HABILIDADE | F1: OBJETO DE CONHECIMENTO | G1: TÍTULO DA AULA | H1: CONTEÚDO | I1: OBJETIVOS
A2: Anos Finais | B2: 6º | C2: 1º | D2: 1 | E2: EF06CI14 | F2: Forma, estrutura e movimento da Terra | G2: A dança da Terra | H2: Esfericidade da Terra.​ | I2: Compreender o conceito de esfericidade da Terra e como isso influencia a incidência de luz solar.​
A3: Anos Finais | B3: 6º | C3: 1º | D3: 2 | E3: EF06CI11 | F3: Forma, estrutura e movimento da Terra | G3: Como o passado da Terra e o nosso cotidiano se conectam?​ | H3: Tempo histórico, geológico e cronológico. | I3: Compreender o tempo para construir uma visão integrada sobre o desenvolvimento da Terra e das civilizações, relacionando ciência, história e o cotidiano.
A4: Anos Finais | B4: 6º | C4: 1º | D4: 3 | E4: EF06CI14​ | F4: Forma, estrutura e movimento da Terra | G4: Um objeto que cai | H4: Gravidade, aceleração e peso.​ | I4: Identificar os principais conceitos relacionados à gravidade.​
A5: Anos Finais | B5: 6º | C5: 2º | D5: 1 | E5: EF06CI11 | F5: Forma, estrutura e movimento da Terra | G5: O ciclo da água e os estados físicos da matéria | H5: Principais estados físicos da matéria. | I5: Classificar os estados físicos da matéria a partir da análise das características de diferentes objetos.
A6: Anos Finais | B6: 6º | C6: 2º | D6: 2 | E6: EF06CI01 | F6: Separação de materiais | G6: Os métodos de separação de misturas | H6: - Misturas homogêneas e heterogêneas. - Separação de misturas. | I6: Compreender os fênomenos envolvidos em diferentes técnicas de separação de misturas.
A7: Anos Finais | B7: 6º | C7: 2º | D7: 3 | E7: EF06CI12 | F7: Forma, estrutura e movimento da Terra | G7: O processo de fossilização | H7: O que são fósseis e como são formados. | I7: Simular o processo de fossilização.
A8: Anos Finais | B8: 7º | C8: 1º | D8: 1 | E8: EF07CI02​ | F8: Formas de propagação de calor | G8: Como o calor pode mover as máquinas? | H8: Calor e temperatura. | I8: Compreender os principais conceitos relacionados à temperatura, ao calor e à sensação térmica.​
A9: Anos Finais | B9: 7º | C9: 1º | D9: 2 | E9: EF07CI01A​ | F9: Máquinas simples | G9: A engenharia do dia a dia | H9: Máquinas simples. | I9: Identificar o papel do uso de máquinas simples no cotidiano.​
A10: Anos Finais | B10: 7º | C10: 1º | D10: 3 | E10: EF07CI16​ | F10: Placas tectônicas e deriva continental​ | G10: O movimento das placas tectônicas | H10: - Placas tectônicas. - Deriva continental. | I10: Simular os movimentos convergentes, divergentes e transformantes realizados pelas placas tectônicas.
A11: Anos Finais | B11: 7º | C11: 2º | D11: 1 | E11: EF07CI13A | F11: Efeito estufa | G11: Simulando o efeito estufa | H11: Efeito estufa. | I11: Simular, em um sistema pequeno, as condições que levam ao agravamento do efeito estufa.
A12: Anos Finais | B12: 7º | C12: 2º | D12: 2 | E12: EF07CI07 | F12: Diversidade de ecossistemas | G12: Olhando as plantas de perto | H12: Plantas. | I12: Analisar as principais características dos grupos de plantas terrestres.
A13: Anos Finais | B13: 7º | C13: 2º | D13: 3 | E13: EF07CI10A | F13: Programas e indicadores de saúde pública | G13: Diversidade da vida: microorganismos | H13: Microorganismos. | I13: Explorar a presença de micorganismos em diferentes amostras de solo e de água.
... A49: Anos Finais | B49: 9º | C49: 4º | D49: 3 | E49: EF09CI14 | F49: Composição, estrutura e localização do Sistema Solar no Universo | G49: Planetas rochosos | H49: Planetas rochosos do Sistema Solar. | I49: Elaborar maquete dos planetas rochosos do Sistema Solar.

Sheet Projeto de Vida
A1: AULA COMPLEMENTAR | B1: CICLO | C1: ANO | D1: BIMESTRE | E1: TEMA | F1: AULA | G1: DIMENSÃO EM FOCO | H1: COMPREENSÃO | I1: CONTEXTO DA AULA | J1: QUESTÃO ESSENCIAL | K1: ATITUDE | L1: PRÁTICA | M1: HABILIDADE
B2: Anos Finais | C2: 6º | D2: 1º | E2: O início dos Anos Finais é mais do que mudar de turma e professores — é atravessar uma ponte entre ser criança e tornar-se adolescente. Neste projeto, os estudantes vão investigar quem são e quem estão se tornando, construindo um retrato vivo de sua identidade, motivações e escolhas. Ao longo das aulas, eles irão conectar autoconhecimento, convivência, tomada de decisão, planejamento e engajamento, culminando em um produto coletivo que representa sua chegada ao 6º ano. Ao final do projeto, os estudantes terão produzido um “Livro da Transição” (individual ou coletivo), reunindo registros de autoconhecimento, perfis acadêmicos, mapas de afinidades, dilemas de decisão, metas de curto prazo e estratégias de motivação. Esse material servirá como marco simbólico da chegada ao 6º ano e referência para sua jornada no Ensino Fundamental - Anos Finais. | F2: 1 | G2: Autoconhecimento | H2: Assumir e valorizar quem somos é o primeiro passo para nos tornar quem desejamos ser. | I2: Somos diferentes e habitamos o mesmo mundo. Qual será o resultado disso? Esta aula abre o projeto convidando os estudantes a olhar para si mesmos e a compartilhar como se veem. Propõe uma conexão entre família e escola, valorizando percepções mútuas como ponto de partida para a transição. ENTREGA: Livro da Transição: registro inicial de identidade e percepções pessoais/familiares. | J2: - Quais são as características sem as quais eu deixaria de ser quem sou? - O que me torna eu mesmo(a)? - O que minha família diria que são minhas principais características? E eu, o que vejo em mim? | K2: Autoconexão | L2: Reconhecer | M2: AC.6.1 Reconhecer as próprias características físicas e psicológicas.
B3: Anos Finais | C3: 6º | D3: 1º | F3: 2 | G3: Autoconhecimento | H3: Assumir e valorizar quem somos é o primeiro passo para nos tornar quem desejamos ser. | I3: Somos diferentes e habitamos o mesmo mundo. Qual será o resultado disso? Nesta aula, os estudantes iniciam a construção de seu Livro da Transição, criando seu perfil acadêmico a partir da observação de interesses e resultados, integrando-se com a narrativa pessoal da aula 1. ENTREGA: Inclusão do perfil acadêmico no Livro da Transição. | J3: - Quais são as características sem as quais eu deixaria de ser quem sou? - Quem eu sou como estudante? - O que eu já sei sobre mim e meu jeito de aprender? | K3: - Autoconexão - Compromisso consigo mesmo | L3: - Reconhecer - Observar-se | M3: AC.6.1 Reconhecer as próprias características físicas e psicológicas. P.6.1 Criar seu perfil acadêmico com base na observação de interesses e resultados.
B4: Anos Finais | C4: 6º | D4: 1º | F4: 3 | G4: Convivência | H4: Aprender a se expressar com respeito, sem abrir mão da autenticidade, construindo relações de confiança com os demais. | I4: Na escola e na vida, convivemos com pessoas diferentes — mas com algumas, criamos conexões mais fortes. Quem são essas pessoas? O que temos em comum? Como podemos estar juntos de forma positiva e criativa? Dando continuidade ao Livro da Transição, os estudantes exploram afinidades com os colegas, reconhecendo como seus interesses se conectam e constroem pertencimento no novo ciclo. ENTREGA: Mapa de afinidades ou caderno coletivo de interesses no Livro da Transição. | J4: - Quem são as pessoas com as quais eu tenho afinidades? - Com quem eu gosto de estar junto na escola? Por quê? | K4: Abertura para o encontro | L4: Acolher | M4: C.6.1 Formar grupos de interesse com colegas.
B5: Anos Finais | C5: 6º | D5: 1º | F5: 4 | G5: Tomada de decisão | H5: Testar possibilidades de decisão em diferentes cenários e com a participação de diferentes atores. | I5: Escolher entre ir ou não, contar ou esconder, ajudar ou ignorar, se posicionar ou ficar quieto… Todos os dias tomamos decisões. Mas nem sempre é fácil. Por quê? O que torna uma escolha difícil? No Livro da Transição, os estudantes registram dilemas e decisões significativas, discutindo como fatores pessoais e sociais influenciam suas escolhas. ENTREGA: Registro de dilemas e escolhas no Livro da Transição. | J5: É fácil tomar decisões? Por que, na escola, tomar decisões às vezes é difícil? | K5: Coragem para decidir | L5: Refletir | M5: TD.6.1 Compreender porque pode ser difícil tomar decisões.
B6: Anos Finais | C6: 6º | D6: 1º | F6: 5 | G6: Planejamento | H6: Estabelecer objetivos de curto prazo para organizar os estudos e conquistar metas pessoais na escola. | I6: Cada estudante tem uma forma de aprender, se concentrar e se organizar. Descobrir o seu próprio jeito pode ser o primeiro passo para conquistar seus objetivos na escola. Mas o que será que já sabemos sobre nós mesmos como aprendizes? Os estudantes transformam seus perfis e dilemas em metas concretas, registradas como compromissos pessoais no Livro da Transição. ENTREGA: Metas de curto prazo no Livro da Transição. | J6: - Quem eu sou como estudante? - Como eu me organizo para aprender coisas novas? | K6: Compromisso consigo mesmo | L6: Observar-se | M6: P.6.1 Criar seu perfil acadêmico com base na observação de interesses e resultados.
B7: Anos Finais | C7: 6º | D7: 1º | F7: 6 | G7: Engajamento | H7: Manter a motivação necessária para realizar e concluir tarefas com autonomia e empenho pessoal. | I7: Às vezes acordamos animados para realizar nossas tarefas; em outras, parece que nada faz sentido. Identificar o que influencia nossa motivação é um passo importante para aprender a lidar com os altos e baixos e manter o foco mesmo nos dias difíceis. Encerrando o Livro da Transição, os estudantes identificam fatores que influenciam sua motivação e elaboram estratégias pessoais de resiliência. ENTREGA: Diário de ânimo e estratégias de motivação no Livro da Transição. | J7: - Como me sinto quando estou motivado? E demotivado? - O que me dá vontade de aprender? O que me desanima? | K7: Consciência emocional | L7: Observar-se | M7: E.6.1 Diferenciar estados de ânimo motivadores e desmotivadores.
B8: Anos Finais | C8: 6º | D8: 1º | F8: 7 | G8: Engajamento | H8: Manter a motivação necessária para realizar e concluir tarefas com autonomia e empenho pessoal. | I8: Às vezes acordamos animados para realizar nossas tarefas; em outras, parece que nada faz sentido. Identificar o que influencia nossa motivação é um passo importante para aprender a lidar com os altos e baixos e manter o foco mesmo nos dias difíceis. Conclusão do Livro da Transição: os estudantes refletem sobre como emoções e decisões se entrelaçam em sua vida escolar, registrando compromissos para o 6º ano. ENTREGA: Síntese final do Livro da Transição, com compromissos para o novo ciclo. | J8: - Como me sinto quando estou motivado? E demotivado? - É fácil tomar decisões? - Como eu me sinto quando preciso tomar decisões importantes na escola? | K8: - Consciência emocional - Coragem para decidir | L8: - Observar-se - Refletir | M8: E.6.1 Diferenciar estados de ânimo motivadores e desmotivadores. TD.6.1 Compreender porque pode ser difícil tomar decisões.
B9: Anos Finais | C9: 7º | D9: 1º | E9: Cada pessoa tem seus próprios interesses, formas de se comunicar, decisões a tomar e planos para o futuro. No 7º ano, os estudantes estão em uma fase de transição: seus gostos mudam, suas opiniões ganham força e suas responsabilidades aumentam. Nesse contexto, este projeto convida os alunos a investigarem como seus interesses evoluíram, como se comunicam, como tomam decisões e como podem definir metas em diferentes áreas da vida. Ao final, os estudantes criarão um painel de transformações do 7º ano (individual ou coletivo), reunindo registros de seus interesses em mudança, reflexões sobre comunicação e empatia, mapas de decisões, metas pessoais e propostas de engajamento. Esse painel culminará em uma apresentação multimodal que responde à pergunta: “Quem estou me tornando?”. | F9: 1 | G9: Autoconhecimento | H9: Escolher o que nos interessa é também escolher quem estamos nos tornando. | I9: Os interesses mudam com o tempo — o que gostávamos na infância pode já não fazer sentido hoje. E alguns gostos nos acompanham desde sempre. O que será que isso revela sobre nossa história e sobre quem estamos nos tornando? Esta aula abre o projeto, convidando os estudantes a mapear suas transformações de interesses ao longo da vida. O contexto conecta infância e presente, preparando terreno para relacionar mudanças pessoais a futuras escolhas. ENTREGA: Linha do Tempo dos Interesses – registro inicial no “painel de transformações do 7º ano”. | J9: O que mudou e o que permaneceu nos meus interesses até agora? | K9: Autenticidade | L9: Refletir | M9: AC.7.1 Analisar as transformações que ocorreram em seus interesses ao longo dos anos.
B10: Anos Finais | C10: 7º | D10: 1º | F10: 2 | G10: Autoconhecimento | H10: Escolher o que nos interessa é também escolher quem estamos nos tornando. | I10: Os interesses mudam com o tempo — o que gostávamos na infância pode já não fazer sentido hoje. E alguns gostos nos acompanham desde sempre. O que será que isso revela sobre nossa história e sobre quem estamos nos tornando? Os registros se transformam em narrativas ou símbolos que evidenciam o que mudou e o que permaneceu. Assim, ampliam o painel de transformações. ENTREGA: Painel Individual ou Coletivo de Interesses. | J10: O que mudou e o que permaneceu nos meus interesses até agora? | K10: Autenticidade | L10: Refletir | M10: AC.7.1 Analisar as transformações que ocorreram em seus interesses ao longo dos anos.
B11: Anos Finais | C11: 7º | D11: 1º | F11: 3 | G11: Convivência | H11: Utilizar os princípios da comunicação não violenta para expressar-se com respeito, empatia e assertividade. | I11: Às vezes, o jeito como a gente fala pode machucar, ajudar ou confundir. Outras vezes, o silêncio fala mais do que as palavras. Será que sabemos como nossas palavras afetam os outros? E como a forma de escutar também faz diferença? Nesta aula, os estudantes registram, no Painel, reflexões sobre como se comunicam e como a CNV pode ajudar a evitar conflitos (incluindo bullying e exclusão). ENTREGA: Registro CNV no Painel: mural de “Palavras que constroem”. | J11: O que acontece quando eu sei me comunicar bem com os outros? | K11: Consciência comunicativa | L11: Escutar | M11: C.7.1 Refletir sobre os efeitos de diferentes formas de se comunicar em contextos escolares, familiares e comunitários.
B12: Anos Finais | C12: 7º | D12: 1º | F12: 4 | G12: Tomada de Decisão | H12: Tomar decisões baseadas na análise das causas e consequências das situações. | I12: Muitas vezes a gente decide porque algo acontece, alguém fala, ou uma situação muda. Mas e quando isso acontece com pessoas que tomam decisões que afetam o mundo? O que provoca essas decisões? E o que provoca as nossas? Os estudantes comparam decisões pessoais e históricas, registrando no Painel o que perceberam como causas mais relevantes, aproximando suas escolhas das de grandes marcos. ENTREGA: Mapa das Causas – seção do Painel dedicada às decisões. | J12: O que causa a necessidade de tomar uma decisão? | K12: Curiosidade investigativa | L12: Observar-se | M12: TD.7.1 Analisar causas de decisões pessoais e históricas.
B13: Anos Finais | C13: 7º | D13: 1º | F13: 5 | G13: Planejamento | H13: Formular objetivos de curto a médio prazo para diferentes áreas da vida e usar ferramentas para conquistá-los. | I13: Todo mundo tem sonhos, planos e desejos. Mas quais deles podem se tornar realidade em pouco tempo? E o que pode levar um pouco mais? Reconhecer essas metas e pensar em como conquistá-las é uma forma de cuidar da própria vida. A partir da Roda da Vida, os estudantes definem metas, ligando interesses e decisões anteriores. Registram compromissos concretos para diferentes áreas da vida. ENTREGA: Cartões de Metas no Painel. | J13: O que eu quero conquistar a curto e médio prazo? | K13: Intencionalidade | L13: Nomear | M13: P.7.1 Criar uma lista de objetivos de curto e médio prazo para diversas áreas da vida.
B14: Anos Finais | C14: 7º | D14: 1º | F14: 6 | G14: Engajamento | H14: Estar atento e comprometido com as necessidades e demandas do seu entorno. | I14: Vivemos em comunidade. Na escola, em casa e em outros espaços, existem necessidades que nem sempre são ditas. Perceber essas demandas é o primeiro passo para colaborar e se engajar em soluções que fazem a diferença. Os estudantes investigam necessidades na escola, família e comunidade. No Painel, registram propostas coletivas para atendê-las. ENTREGA: Mapa das Necessidades no Painel. | J14: O que as pessoas à minha volta necessitam? | K14: Empatia | L14: Escutar | M14: E.7.1 Perceber e analisar as necessidades e demandas de sua escola, família e comunidade, propondo formas coletivas de atendê-las.
B15: Anos Finais | C15: 7º | D15: 1º | F15: 7 | G15: Autoconhecimento | H15: Escolher o que nos interessa é também escolher quem estamos nos tornando. (Síntese do projeto) | I15: Os interesses mudam com o tempo — o que gostávamos na infância pode já não fazer sentido hoje. E alguns gostos nos acompanham desde sempre. O que será que isso revela sobre nossa história e sobre quem estamos nos tornando? Encerram o painel de transformações conectando interesses, decisões, metas e engajamento. A síntese pode ser multimodal (texto, imagens, áudio, vídeo). ENTREGA: Apresentação Multimodal do painel de transformações. | J15: O que mudou e o que permaneceu nos meus interesses até agora? | K15: - Autenticidade - Intencionalidade | L15: - Refletir - Nomear | M15: AC.7.1 Analisar as transformações que ocorreram em seus interesses ao longo dos anos. P.7.1 Criar uma lista de objetivos de curto e médio prazo para diversas áreas da vida.
B16: Anos Finais | C16: 8º | D16: 1º | E16: Nos pequenos e grandes momentos da vida, lidamos com imprevistos, diferenças, decisões difíceis e o desafio de entender o que é certo ou justo. Ao mesmo tempo, desenvolvemos habilidades únicas, cultivadas pela humanidade ao longo de milênios — imaginar, cuidar, criar, escutar. Neste projeto, os estudantes serão convidados a investigar essas habilidades, a praticar a empatia, a analisar dilemas éticos e a planejar formas de enfrentar frustrações. Ao final, irão elaborar uma Proposta de Ação Pessoal para responder: “Como posso me desenvolver e agir de forma consciente no mundo em que vivo?”. Nesta proposta, deverão reunir reflexões sobre habilidades humanas, empatia, ética, frustrações e engajamento social. Essa proposta será apresentada em formato multimodal (texto, vídeo, painel ou apresentação oral) como marco de sua transição para um papel mais ativo e consciente na sociedade. | F16: 1 | G16: Autoconhecimento | H16: Cultivar habilidades que conectem quem somos hoje com quem desejamos ser no futuro. | I16: Desde que existimos, os seres humanos inventam, aprendem, cuidam, narram, dançam, constroem e sentem. O que será que essas habilidades dizem sobre o que é ser humano? E como elas continuam vivas em nós hoje? A aula inaugura o projeto, levando os estudantes a identificar e valorizar habilidades humanas que os conectam ao passado e ao futuro. Os registros alimentam o início da Proposta de Ação Pessoal. ENTREGA: Mapa das Habilidades Humanas como capítulo inicial da Proposta de Ação Pessoal. | J16: Quais habilidades foram desenvolvidas pela humanidade? | K16: Admiração pelo humano | L16: Nomear | M16: AC.8.1 Conhecer habilidades humanas de diversas naturezas.
B17: Anos Finais | C17: 8º | D17: 1º | F17: 2 | G17: Convivência | H17: Agir com empatia, sendo capaz de compreender as perspectivas e os sentimentos dos outros. | I17: Nem sempre as pessoas pensam como a gente. Às vezes, elas reagem de formas que não entendemos. Mas será que conseguimos enxergar as situações pelos olhos dos outros? Entender como os outros pensam pode mudar nossas relações — e até nossas decisões. Os estudantes exploram a empatia como prática diária, registrando no projeto percepções sobre como enxergar pelos olhos dos outros pode mudar relações e decisões. ENTREGA: Cartas de Perspectiva ou Painel de Múltiplas Vozes integrados à Proposta de Ação Pessoal. | J17: O que os outros estão pensando? | K17: Curiosidade empática | L17: Escutar | M17: C.8.1 Conhecer a perspectiva dos outros em diferentes situações.
B18: Anos Finais | C18: 8º | D18: 1º | F18: 3 | G18: Tomada de decisão | H18: Usar valores éticos como critérios para a tomada de decisão. | I18: Às vezes, a gente faz algo que parece certo, mas depois percebe que pode ter ferido alguém. Outras vezes, somos pressionados a fazer o que todo mundo faz, mesmo que pareça errado. Como saber o que é ético em cada situação? Existe um jeito justo de decidir? Com dilemas éticos reais e fictícios, os estudantes testam ferramentas para avaliar escolhas justas e responsáveis, registrando aprendizados em sua proposta. ENTREGA: Roteiro de Decisão Ética incorporado à Proposta de Ação Pessoal. | J18: Como saber se uma decisão é ética ou não? | K18: Compromisso com o que é justo | L18: Refletir | M18: TD.8.1 Avaliar as implicações éticas de diferentes decisões em contextos pessoais, familiares e sociais.
B19: Anos Finais | C19: 8º | D19: 1º | F19: 4 | G19: Planejamento | H19: Elaborar planos alternativos para lidar com imprevistos e frustrações sem perder de vista seus objetivos. | I19: Nem tudo sai como o planejado. Às vezes, a internet cai, um compromisso atrasa ou simplesmente o cansaço aparece. Como você reage nesses momentos? O que você faz quando algo frustrante acontece e atrapalha seus planos? Por meio de simulações e reflexões, os estudantes elaboram estratégias de enfrentamento, fortalecendo a dimensão prática de sua Proposta de Ação Pessoal. ENTREGA: Kit de Enfrentamento ou Diário do Inesperado integrado à proposta. | J19: Como eu lido com imprevistos e frustrações? | K19: Flexibilidade | L19: Reconhecer | M19: P.8.1 Avaliar como costuma lidar com imprevistos e frustrações.
B20: Anos Finais | C20: 8º | D20: 1º | F20: 5 | G20: Engajamento | H20: Compreender seu papel na sociedade e as formas pelas quais pode contribuir para sua melhoria. | I20: A sociedade em que vivemos é feita por pessoas e instituições. Em meio aos seus avanços e problemas, podemos aprender a enxergar o que merece ser valorizado e o que precisa ser transformado. Essa consciência é o primeiro passo para o engajamento social. Os estudantes analisam avanços e desafios da sociedade, produzindo críticas e elogios fundamentados, que ampliam sua visão de engajamento. ENTREGA: Painel O que Funciona e o que Não Funciona como parte da proposta. | J20: O que há de bom e de ruim na sociedade? | K20: Senso crítico | L20: Argumentar | M20: E.8.1 Criticar e elogiar características da sociedade, incluindo percepções familiares e comunitárias.
B21: Anos Finais | C21: 8º | D21: 1º | F21: 6 | G21: Autoconhecimento | H21: Cultivar habilidades que conectem quem somos hoje com quem desejamos ser no futuro. | I21: Desde que existimos, os seres humanos inventam, aprendem, cuidam, narram, dançam, constroem e sentem. O que será que essas habilidades dizem sobre o que é ser humano? E como elas continuam vivas em nós hoje? Os registros de habilidades e dilemas se transformam em narrativas pessoais sobre ética e humanidade, integrando-se à proposta final. ENTREGA: Galeria de Pessoas Sábias + Linha Ética da Vida Real na proposta. | J21: - Quais habilidades foram desenvolvidas pela humanidade? - Como saber se uma decisão é ética ou não? | K21: - Admiração pelo humano - Compromisso com o que é justo | L21: - Nomear - Refletir | M21: AC.8.1 Conhecer habilidades humanas de diversas naturezas. TD.8.1 Avaliar as implicações éticas de diferentes decisões em contextos pessoais, familiares e sociais.
B22: Anos Finais | C22: 8º | D22: 1º | F22: 7 | G22: Engajamento | H22: Compreender seu papel na sociedade e as formas pelas quais pode contribuir para sua melhoria. | I22: A sociedade em que vivemos é feita por pessoas e instituições. Em meio aos seus avanços e problemas, podemos aprender a enxergar o que merece ser valorizado e o que precisa ser transformado. Essa consciência é o primeiro passo para o engajamento social. Os estudantes finalizam sua Proposta de Ação Pessoal, conectando suas reflexões e estratégias para se desenvolver e agir no mundo. ENTREGA: Apresentação multimodal da Proposta de Ação Pessoal. | J22: - O que há de bom e de ruim na sociedade? - Como eu lido com imprevistos e frustrações? | K22: - Senso crítico - Flexibilidade | L22: - Argumentar - Reconhecer | M22: E.8.1 Criticar e elogiar características da sociedade, incluindo percepções familiares e comunitárias. P.8.1 Avaliar como costuma lidar com imprevistos e frustrações.
B23: Anos Finais | C23: 9º | D23: 1º | E23: Iniciar o último ano do Ensino Fundamental é um momento de balanço e de escolhas. Este projeto convida os estudantes a olhar para suas forças e fragilidades, refletir sobre convivência e bem-estar, avaliar decisões e planejar formas de lidar com imprevistos e frustrações. Ao final, irão propor pequenas melhorias para si mesmos, para a escola e para a comunidade, construindo um retrato coletivo de quem são hoje e de como desejam impactar o mundo ao seu redor. Essa proposta se concretizará por meio de um portfólio coletivo e individual, reunindo autorretratos simbólicos, recursos de força, guias de convivência, mapas de conselheiros, diários do inesperado e propostas de ação no entorno. Esse dossiê marca o início do 9º ano e será compartilhado em uma roda de síntese com colegas e familiares. | F23: 1 | G23: Autoconhecimento | H23: Compreender as fragilidades como parte da identidade, buscando formas saudáveis de lidar com elas e caminhos possíveis de superação. | I23: Todos nós temos partes fortes e partes frágeis. Mas nem sempre olhamos com cuidado para aquilo que nos faz sentir inseguros, com medo ou expostos. Reconhecer essas partes pode nos tornar mais humanos, mais verdadeiros — e mais capazes de crescer. A aula abre o projeto convidando os estudantes a criar um autorretrato simbólico, registrando forças e fragilidades que marcam quem são hoje. ENTREGA: Autorretrato simbólico no dossiê. | J23: Quais partes de mim fazem com que eu me sinta frágil ou vulnerável? | K23: Coragem emocional | L23: Revelar-se | M23: AC.9.1 Reconhecer as próprias fragilidades.
B24: Anos Finais | C24: 9º | D24: 1º | F24: 2 | G24: Autoconhecimento | H24: Compreender as fragilidades como parte da identidade, buscando formas saudáveis de lidar com elas e caminhos possíveis de superação. | I24: Todos nós temos partes fortes e partes frágeis. Mas nem sempre olhamos com cuidado para aquilo que nos faz sentir inseguros, com medo ou expostos. Reconhecer essas partes pode nos tornar mais humanos, mais verdadeiros — e mais capazes de crescer. Em dinâmicas de reflexão e partilha, os estudantes registram no dossiê estratégias de autocuidado e superação. ENTREGA: Página “Meus Recursos de Força”. | J24: Quais partes de mim fazem com que eu me sinta frágil ou vulnerável? | K24: Coragem emocional | L24: Revelar-se | M24: AC.9.1 Reconhecer as próprias fragilidades.
B25: Anos Finais | C25: 9º | D25: 1º | F25: 3 | G25: Convivência | H25: Agir com responsabilidade, considerando o impacto das próprias decisões no bem-estar físico e psicológico dos outros. | I25: Às vezes, pequenos gestos mudam o dia de alguém. Outras vezes, atitudes comuns podem machucar — mesmo sem intenção. O que realmente faz alguém se sentir bem? Como podemos aprender a reconhecer essas necessidades nas outras pessoas? Construção coletiva de um Guia do Bem-Estar, reunindo atitudes que fortalecem a convivência e o cuidado mútuo. ENTREGA: Guia do Bem-Estar no dossiê. | J25: O que faz com que as pessoas se sintam bem? | K25: Cuidado com o outro | L25: Acolher | M25: C.9.1 Conhecer o que gera bem-estar físico e psicológico para os outros.
B26: Anos Finais | C26: 9º | D26: 1º | F26: 4 | G26: Tomada de decisão | H26: Compreender o papel que outras pessoas podem ter no processo de tomada de decisão dos estudantes. | I26: Em muitas situações importantes, temos que decidir sozinhos — mas isso não significa que precisamos estar sozinhos. Pedir ajuda pode parecer sinal de fraqueza, mas e se for inteligência emocional? Como saber quando é hora de contar com alguém? E quem são essas pessoas? Criação de um Mapa de Pessoas-Conselheiras, com registros de quando e como pedir apoio em decisões. ENTREGA: Mapa de Conselheiros no dossiê. | J26: É mais fácil tomar decisões sozinho ou com ajuda de outras pessoas? | K26: Disposição para buscar apoio | L26: Escutar | M26: TD.9.1 Investigar e praticar estratégias de colaboração, pedindo ajuda e oferecendo apoio em processos de tomada de decisão coletiva.
B27: Anos Finais | C27: 9º | D27: 1º | F27: 5 | G27: Planejamento | H27: Planejar a transição para o Ensino Médio com base em quem desejam ser e no que desejam conquistar nessa nova etapa. | I27: Ao final do Ensino Fundamental, muitas mudanças se aproximam: novos desafios, mais responsabilidades e outras formas de viver a escola e a vida. Imaginar como será essa próxima etapa e reconhecer os sentimentos que ela desperta pode nos ajudar a criar caminhos mais seguros e saudáveis para o futuro. E, acima de tudo, nos permite desenvolver estratégias para lidar com os imprevistos e cultivar a confiança em nossa capacidade de superação. A partir de estudos de caso, elaboram o Diário do Inesperado, com estratégias para enfrentar contratempos. ENTREGA: Diário do Inesperado no dossiê. | J27: O que posso fazer para me preparar melhor para os desafios inesperados do dia a dia? | K27: Visão de futuro | L27: Revelar-se | M27: P.9.1 Criar um cenário sobre como imagina sua vida, seus pensamentos e sentimentos em uma próxima etapa da vida, planejando estratégias de resiliência para enfrentar desafios e contratempos.
B28: Anos Finais | C28: 9º | D28: 1º | F28: 6 | G28: Planejamento | H28: Planejar a transição para o Ensino Médio com base em quem desejam ser e no que desejam conquistar nessa nova etapa. | I28: Ao final do Ensino Fundamental, muitas mudanças se aproximam: novos desafios, mais responsabilidades e outras formas de viver a escola e a vida. Imaginar como será essa próxima etapa e reconhecer os sentimentos que ela desperta pode nos ajudar a criar caminhos mais seguros e saudáveis para o futuro. E, acima de tudo, nos permite desenvolver estratégias para lidar com os imprevistos e cultivar a confiança em nossa capacidade de superação. Aprofundando o Diário do Inesperado, os estudantes constroem um Kit de Resiliência (com frases, hábitos, técnicas e recursos simbólicos), registrando como pretendem lidar com desafios no 9º ano. ENTREGA: Kit de Resiliência no dossiê. | J28: O que posso fazer para me preparar melhor para os desafios inesperados do dia a dia? | K28: Visão de futuro | L28: Revelar-se | M28: P.9.1 Criar um cenário sobre como imagina sua vida, seus pensamentos e sentimentos em uma próxima etapa da vida, planejando estratégias de resiliência para enfrentar desafios e contratempos.
B29: Anos Finais | C29: 9º | D29: 1º | F29: 7 | G29: Engajamento | H29: Comprometer-se com ações éticas e conscientes no presente, que contribuam para a construção de futuros melhores para si e para os outros. | I29: Melhorar a própria vida é um movimento que exige autoconhecimento, escolhas conscientes e ação contínua. Quando os jovens se colocam em movimento, eles expandem sua agência e sua capacidade de transformar também o entorno. Em grupos, os estudantes propõem pequenas ações de melhoria na escola, família ou comunidade. Finalizam o Dossiê Retrato do Presente, apresentando-o em uma roda de partilha que celebra conquistas e compromissos. ENTREGA: Proposta de Ação Coletiva + Dossiê completo. | J29: Como posso melhorar a minha vida? | K29: Autonomia | L29: Decidir | M29: E.9.1 Realizar melhorias na vida pessoal.
B30: Anos Finais | C30: 6º | D30: 2º | E30: Minha Voz Conta: conversas difíceis, escolhas importantes Depois de inaugurar o 6º ano olhando para dentro, este bimestre coloca em foco como nos expressamos e decidimos em situações reais de convivência. O projeto convida os estudantes a transformarem a voz individual em voz coletiva. Na aula 1, cada estudante investiga a própria autenticidade (AC.6.2) e redige uma frase-guia sobre como deseja se expressar. Na aula 2, essa voz se torna prática ao treinar fala e escuta respeitosas (C.6.2), gerando frases-modelo que alimentarão um anexo da futura Carta de Convivência. Na aula 3, a turma escolhe um dilema real da convivência escolar e escreve a minuta da Carta (C.6.2). A aula 4 converte o dilema em mapas de decisão (TD.6.2), que na aula 5 são validados em Círculo de Convivência, quando a turma decide coletivamente e finaliza a Carta e o Mapa de Decisão Coletivo (TD.6.2). Para sustentar mudanças reais, a aula 6 aciona o planejamento de microajustes (P.6.2) e prepara a Mostra (convites/cartaz). A aula 7 fecha com autoavaliação de motivação (E.6.2) e a celebração pública: a Mostra “Minha Voz Conta”, em que os combinados são apresentados à comunidade escolar. Assim, cada aula retoma, aprofunda e encaminha o que veio antes, de modo que produto e percurso se constroem juntos: o que sou e como falo (A1–A2) fundamenta o que combinamos (A3), que orienta como decidimos (A4–A5), que gera como vamos manter (A6–A7). Produto: O Material Impresso funciona como caderno de trabalho do projeto; o produto final do bimestre é público e coletivo: a Carta de Convivência da Turma e a Mostra ‘Minha Voz Conta’ com o Mapa de Decisão Coletivo. Roadmap das entregas A1 → “Minha voz”: Frase-guia + lista de características (MI) → alimenta A2/A3. (sem entrega formal) A2 → “Prática de voz”: Frases-modelo (MI) → anexo da Carta na A3. (sem entrega formal) A3 → “Minuta da Carta” (C.6.2): ENTREGA formal (bloco 1) — regras + anexo com frases-modelo. → prepara A4. A4 → “Mapas de decisão” (TD.6.2): rascunhos individuais (MI) → insumo para A5. (sem entrega formal) A5 → “Deliberação e consolidação” (TD.6.2): ENTREGA formal (bloco 2) — Carta final + Mapa de Decisão Coletivo. → prepara A6. A6 → “Sustentação” (P.6.2): ENTREGA formal — Plano 7 dias + preparo visual da Mostra (convites/cartaz). → prepara A7. A7 → “Mostra & celebração” (E.6.2): apresentação pública da Carta e do Mapa + autoavaliação e compromissos. (entrega formal) | F30: 1 | G30: Autoconhecimento | H30: Assumir e valorizar quem somos é o primeiro passo para nos tornar quem desejamos ser. | I30: Quem sou quando estou comigo? A aula propõe um percurso de autorobservação breve para diferenciar “eu íntimo” e “eu público” e tornar explícito o sentido de autenticidade (coerência entre valores, pensamentos, sentimentos, palavras e ações, com respeito e limites). Para mobilizar a atividade AC.6.2, os estudantes serão convidados a identificar traços que consideram autênticos, selecionar evidências pessoais e registrar uma lista curta de características, discernindo o que compartilhar e o que preservar. A aula abre o projeto definindo voz pessoal que será praticada na A2 e servirá de frase-guia na Carta (borda/citações). Produto em construção: frase-guia + lista de características (registro no MI). (sem entrega formal) | J30: Como eu sou quando estou só comigo mesmo? | K30: Autenticidade | L30: Observar-se | M30: AC.6.2 Identificar quais características pessoais promovem a autenticidade.
B31: Anos Finais | C31: 6º | D31: 2º | F31: 2 | G31: Convivência | H31: Aprender a se expressar com respeito, sem abrir mão da autenticidade, construindo relações de confiança com os demais. | I31: Opiniões diferentes, respeito igual A aula propõe um percurso de simulação de divergências e treino de fala/escuta respeitosas para praticar “autenticidade com responsabilidade” (não é sincericídio). Para mobilizar a atividade C.6.2, os estudantes serão convidados a usar eu‑mensagem, paráfrase e pedidos claros, nomeando gatilhos e reparos que preservam a coerência pessoal sem ferir o outro. A aula propõe o uso da frase-guia da A1 para compor frases-modelo que embasarão a minuta da Carta (A3). Produto em construção: frases-modelo (Anexo da Carta). (sem entrega formal) | J31: Como eu posso falar o que penso de forma respeitosa? | K31: Respeito às diferenças | L31: Argumentar | M31: C.6.2 Expor seu ponto de vista de modo respeitoso em grupos com opiniões diversas.
B32: Anos Finais | C32: 6º | D32: 2º | F32: 3 | G32: Convivência | H32: Aprender a se expressar com respeito, sem abrir mão da autenticidade, construindo relações de confiança com os demais. | I32: Preparando nosso círculo A aula propõe um percurso de curadoria de dilemas reais e coescrita de regras de fala que protegem a autenticidade (coerência na expressão) e os limites (segurança/privacidade), vinculando os combinados ao cuidado com os espaços da escola. Para mobilizar a atividade C.6.2, os estudantes serão convidados a propor dilemas, votar prioridades, definir tempos e papéis (mediador/secretário) e ensaiar abertura e réplica com linguagem alinhada a valores e respeito. A proposta deste encontro é a escolha de um dilema que será analisado na A4 e deliberado na A5. Produto em construção: Minuta da Carta de Convivência (regras + anexo de frases-modelo). ENTREGA formal (bloco 1) | J32: Como eu posso falar o que penso de forma respeitosa? | K32: Respeito às diferenças | L32: Argumentar | M32: C.6.2 Expor seu ponto de vista de modo respeitoso em grupos com opiniões diversas.
A33: X | B33: Anos Finais | C33: 6º | D33: 2º | F33: 4 - Aula complementar | G33: Tomada de decisão - Aula complementar | H33: Testar possibilidades de decisão em diferentes cenários e com a participação de diferentes atores. | I33: Antes de decidir, olhe em volta A aula propõe um percurso de leitura de contexto, mapeamento de atores/interesses e previsão de consequências. Para mobilizar a atividade TD.6.2, os estudantes serão convidados a preencher um mapa de decisão com opções possíveis, efeitos prováveis e pessoas a consultar antes de escolher. Este encontro deverá ser dedicado à produção dos rascunhos de mapas que serão base para a decisão coletiva na A5. Produto em construção: Mapas de decisão individuais (MI) → síntese coletiva na A5. (sem entrega formal) | J33: O que é preciso fazer para tomar decisões? | K33: Atenção ao contexto | L33: Observar-se | M33: TD.6.2 Analisar a influência dos contextos na tomada de decisões.
B34: Anos Finais | C34: 6º | D34: 2º | F34: 5 | G34: Tomada de decisão | H34: Testar possibilidades de decisão em diferentes cenários e com a participação de diferentes atores. | I34: Círculo de Convivência (decidir juntos) A aula propõe um percurso de diálogo estruturado em Círculo de Convivência para decidir coletivamente, explicitando “decisões autênticas” como aquelas que alinham valores pessoais à análise de contexto e aos efeitos sobre os outros. Para mobilizar a atividade TD.6.2, os estudantes serão convidados a realizar rodadas de fala com paráfrase obrigatória, registrar propostas/justificativas e pactuar combinados finais, revisando quando necessário (mudei/por quê). Nesta aula está prevista a finalização da Carta (versão final) e a consolidação do Mapa de Decisão Coletivo (para a Mostra). Produto em construção: Carta final + Mapa coletivo. ENTREGA formal (bloco 2) | J34: O que é preciso fazer para tomar decisões? | K34: Atenção ao contexto | L34: Observar-se | M34: TD.6.2 Analisar a influência dos contextos na tomada de decisões.
B35: Anos Finais | C35: 6º | D35: 2º | F35: 6 | G35: Planejamento | H35: Estabelecer objetivos de curto prazo para organizar os estudos e conquistar metas pessoais na escola. | I35: Pequenas mudanças fazem diferença A aula propõe um percurso de avaliação do perfil acadêmico com foco em microajustes praticáveis. Para mobilizar a atividade P.6.2, os estudantes serão convidados a escolher 1–2 mudanças (espaço/rotina/estratégia), definir gatilhos de ação e registrar um microcompromisso de 7 dias com indicadores de verificação. Esta aula conecta Carta/Mapa a hábitos que garantam sua aplicação e organiza convites/cartaz da Mostra. Produto em construção: Plano 7 dias (P.6.2) e preparo da Mostra (visual). ENTREGA formal | J35: Como posso me tornar um estudante melhor? | K35: Disponibilidade | L35: Transformar | M35: P.6.2 Avaliar as mudanças que gostaria de fazer para melhorar seu perfil acadêmico
B36: Anos Finais | C36: 6º | D36: 2º | F36: 7 | G36: Engajamento | H36: Manter a motivação necessária para realizar e concluir tarefas com autonomia e empenho pessoal. | I36: Altos e baixos do meu ânimo (pré-férias) — Mostra & celebração A aula propõe um percurso de autoavaliação afetiva do bimestre e preparação para o recesso. Para mobilizar a atividade E.6.2, os estudantes serão convidados a construir uma linha do tempo de ânimo, identificar gatilhos de motivação/desmotivação e desenhar um plano leve de férias para manter rotinas saudáveis. Esta aula apresenta Carta e Mapa coletivo e pactua compromissos para o retorno, conectando motivação e constância. Produto concluído: Mostra “Minha Voz Conta” + leitura pública. (entrega formal – celebração/síntese) | J36: Quais os efeitos da motivação e da desmotivação na minha vida? | K36: Responsabilidade emocional | L36: Refletir | M36: E.6.2 Reconhecer os efeitos da motivação e da desmotivação na vida pessoal
B37: Anos Finais | C37: 7º | D37: 2º | E37: Minha voz protege: Rotas de Apoio Quando a palavra encontra cuidado, a escola respira melhor. Depois de revisitarem quem são e o que desejam manter em sua vida, os estudantes são convidados a transformar interesses éticos e saudáveis em direção e coragem para falar com respeito, escutar com atenção e agir quando for preciso. Este projeto nasce do eu (o que escolho cultivar) e se abre para o nós (como nos tratamos), atravessando a leitura de consequências do bullying, a organização de um plano e a realização de Rotas de Apoio – sinais de incentivo comportamental, visíveis e simples, que tornam fácil fazer o certo. As rotas orientam: “se você viu/soube/sofreu, o que fazer agora?” (no pátio, corredor, sala, redes). Sequência em cinco movimentos encadeados 1) Autoconhecimento (A1): “o que quero manter/desenvolver” sustenta atitudes de respeito (lista pessoal de interesses éticos e saudáveis). 2) Convivência (A2): prática de Comunicação Não Violenta (CNV) conectada aos interesses da A1, aplicada a micro‑situações presenciais e on‑line. 3) Tomada de decisão (A3): análise de consequências do bullying e do “não agir” para vítima, autor, testemunhas e clima escolar. 4) Planejamento (A4) + Engajamento (A5): plano das Rotas de Apoio e articulação com a escola (validação de locais, linguagem, canais). 5) Convivência + Engajamento (A6) e Síntese (A7): produção, teste e lançamento das Rotas de Apoio; autoavaliação do percurso e compromissos de continuidade. Produto do bimestre Rotas de Apoio da escola (sinais de incentivo comportamental): placas/cartazes discretos e objetivos, posicionados em pontos‑chave (corredores, pátio, biblioteca, banheiros, sala), com passos simples (“viu/soube/sofreu? 1) pare e respire; 2) procure X; 3) registre Y; 4) não compartilhe; 5) peça ajuda”) e contatos/canais de escuta protegida definidos com a escola. Onde a infraestrutura permitir, adicionar QR para guia/escuta; onde não, manter apenas rotas visuais. O Material Impresso é utilizado como caderno consumível ao longo das aulas (mapas, roteiros, checklists, registros)." | F37: 1 | G37: Autoconhecimento | H37: Escolher o que nos interessa é também escolher quem estamos nos tornando. | I37: Interesses que sustentam o respeito A aula propõe um percurso de mapeamento e priorização de interesses éticos e saudáveis e sua conexão com atitudes antibullying (incluir, ajudar, não compartilhar humilhações). Para mobilizar AC.7.2, os estudantes serão convidados a listar e selecionar interesses que ‘fazem a vida ser melhor’, registrando exemplos de comportamentos coerentes com esses interesses (na escola e nas redes). Este encontro deverá ser dedicado à seleção do top 3 e ao vínculo com atitudes de respeito que embasarão a comunicação das Rotas de Apoio. | J37: Eu me interesso por coisas que fazem a minha vida ser melhor? | K37: Responsabilidade pessoal | L37: Decidir | M37: AC.7.2 Fazer uma lista pessoal de interesses éticos e saudáveis para manter e/ou desenvolver.
A38: X | B38: Anos Finais | C38: 7º | D38: 2º | F38: 2 - complementar | G38: Convivência - complementar | H38: Utilizar os princípios da comunicação não violenta para expressar-se com respeito, empatia e assertividade. | I38: Falar com respeito, agir com cooperação (CNV em ação) A aula propõe um percurso de treino de CNV, conectado ao Top 3 da A1, aplicado a micro‑situações de bullying (exclusão, apelidos, prints). Para mobilizar C.7.2, as equipes assumem papéis (mediador, porta‑voz, observador CNV) e escrevem roteiros breves (eu‑mensagem, pedidos claros, acordos). Este encontro deverá ser dedicado à produção dos cartões ‘Eu digo / Eu escuto / Eu peço’ e aos ensaios curtos com rubrica de respeito e clareza. | J38: A forma como eu falo com os outros me ajuda ou me atrapalha? | K38: Auto-observação | L38: Refletir | M38: C.7.2 Avaliar e ampliar as formas de comunicação, assumindo papéis ativos em grupos e propondo estratégias de cooperação.
B39: Anos Finais | C39: 7º | D39: 2º | F39: 3 | G39: Tomada de decisão | H39: Tomar decisões baseadas na análise das causas e consequências das situações. | I39: Se a gente não faz nada… (analisando consequências) A aula propõe um percurso de análise das consequências do bullying e do ‘não agir’ para vítima, autor, testemunhas e clima escolar (presencial e nas redes). Para mobilizar TD.7.2, os estudantes comparam alternativas de resposta (intervir, procurar ajuda, registrar evidências) e preveem efeitos de curto/médio prazo. Este encontro deverá ser dedicado à produção dos Mapas de Consequências que orientarão o plano das Rotas. | J39: Que tipo de consequências uma decisão pode ter? | K39: Responsabilidade pelas consequências | L39: Refletir | M39: TD.7.2 Analisar consequências de decisões pessoais e históricas.
B40: Anos Finais | C40: 7º | D40: 2º | F40: 4 | G40: Planejamento | H40: Definir objetivos de curto e médio prazo em diferentes áreas da vida, utilizando estratégias e ferramentas para alcançá-los. | I40: Do papel à parede: Plano das Rotas de Apoio A aula propõe um percurso de planejamento das Rotas de Apoio: meta (clareza e acolhimento), locais estratégicos (pátio, corredor, sala, banheiros), mensagens simples (passos ‘viu/soube/sofreu’), contatos/canais, responsáveis e cronograma. Para mobilizar P.7.2, a turma define evidências de sucesso (alcance, compreensão, acesso a apoio). Este encontro deverá ser dedicado à finalização do Plano das Rotas. | J40: Como posso me organizar para realizar de fato meus objetivos? | K40: Organização e perseverança | L40: Decidir | M40: P.7.2 Utilizar uma estrátegia de planejamento para organizar a realização dos seus objetivos.
B41: Anos Finais | C41: 7º | D41: 2º | F41: 5 | G41: Engajamento | H41: Estar atento e comprometido com as necessidades e demandas da escola, da comunidade e das pessoas com quem convive. | I41: Pontes com a escola: validar, ajustar, viabilizar A aula propõe um percurso de articulação com gestão/coordenação/grêmio/professores para validar o plano, ajustar locais/mensagens/canais e combinar responsabilidades compartilhadas. Para mobilizar E.7.2, a turma oferece ajuda concreta e alinha o serviço das Rotas de Apoio às necessidades da escola. Este encontro deverá ser dedicado à reunião‑ponte e aos ajustes finais do plano. | J41: Como posso ajudar as pessoas da minha escola e família? | K41: Colaboração | L41: Cuidar | M41: E.7.2 Oferecer ajuda para suprir necessidades e demandas de sua escola e família.
B42: Anos Finais | C42: 7º | D42: 2º | F42: 6 | G42: Convivência + Engajamento | H42: - Utilizar os princípios da comunicação não violenta para expressar-se com respeito, empatia e assertividade. - Estar atento e comprometido com as necessidades e demandas da escola, da comunidade e das pessoas com quem convive. | I42: Mão na massa: produzir, testar, melhorar A aula propõe um percurso de produção das peças das Rotas (cartazes/placas discretas com passos e canais) e de teste com usuários (legibilidade em 5 segundos: ‘o que você entende que deve fazer?’). Para mobilizar C.7.2 e E.7.2, as equipes revisam linguagem (clara e respeitosa), ajustam símbolos e confirmam posicionamento. Este encontro deverá ser dedicado à finalização dos protótipos e do roteiro de orientação rápida. | J42: - A forma como eu falo com os outros me ajuda ou me atrapalha? - Como posso ajudar as pessoas da minha escola e família? | K42: - Auto-observação - Colaboração | L42: - Refletir - Cuidar | M42: C.7.2 Avaliar e ampliar as formas de comunicação, assumindo papéis ativos em grupos e propondo estratégias de cooperação. E.7.2 Oferecer ajuda para suprir necessidades e demandas de sua escola e família.
B43: Anos Finais | C43: 7º | D43: 2º | F43: 7 | G43: Convivência Planejamento Engajamento | H43: - Utilizar os princípios da comunicação não violenta para expressar-se com respeito, empatia e assertividade. - Definir objetivos de curto e médio prazo em diferentes áreas da vida, utilizando estratégias e ferramentas para alcançá-los. - Estar atento e comprometido com as necessidades e demandas da escola, da comunidade e das pessoas com quem convive. | I43: Lançamento das Rotas + síntese do percurso A aula propõe um percurso de lançamento público das Rotas (apresentações curtas nas turmas) e de autoavaliação do aprendizado: comunicação, consequências, organização e serviço à comunidade. Para mobilizar C.7.2, P.7.2 e E.7.2, os estudantes conduzem o lançamento, coletam feedbacks e registram próximos passos para manutenção das Rotas (responsáveis, reposição, checagens). | J43: - A forma como eu falo com os outros me ajuda ou me atrapalha? - Como posso me organizar para realizar de fato meus objetivos? - Como posso ajudar as pessoas da minha escola e família? | K43: - Auto-observação - Organização e perseverança - Colaboração | L43: - Refletir - Decidir - Cuidar | M43: C.7.2 Avaliar e ampliar as formas de comunicação, assumindo papéis ativos em grupos e propondo estratégias de cooperação. P.7.2 Utilizar uma estrátegia de planejamento para organizar a realização dos seus objetivos. E.7.2 Oferecer ajuda para suprir necessidades e demandas de sua escola e família.
B44: Anos Finais | C44: 8º | D44: 2º | E44: Mostra de HQs Éticas “Antes de Postar” No mundo em que uma reação pode virar corrente e um print pode virar história, este projeto transforma a turma em autores de narrativas éticas. Começamos pelo eu que já existe no digital, mapeando o que cada estudante sabe fazer e como tem usado essas habilidades. Esse retrato inicial não é um fim, mas uma semente de roteiro: dele saem personagens, contextos e conflitos plausíveis. Em seguida, afinamos o como falar/escutar: treinamos paráfrase, pedidos e reparações, para que cada fala possa ser ponte — não pedra. Com a linguagem mais atenta, mergulhamos em dilemas reais do feed: o que está em jogo, quem é afetado, que consequências se desenham. Desse olhar nasce a régua ética da turma, um conjunto de perguntas-guia que distinguem valores éticos de antiéticos e ajudam a experimentar critérios de decisão na prática. A régua vira motor de enredo: cada HQ incorpora planos de resposta a imprevistos e frustrações (o passo a passo quando “dá ruim”), com apoios e prazos. Para não contar histórias que apagam desigualdades, adicionamos lentes de privilégios e desvantagens: quem fica mais exposto? que proteções e solidariedades podemos representar? . Ao final, organizamos uma mostra pública: as HQs se penduram como espelhos que convidam a ler, conversar, combinar — um pacto vivo de convivência digital. Fio condutor: Trabalhar do pessoal ao público: inventário → banco de falas empáticas → análise ética → régua (v1) → roteirização de respostas a imprevistos → revisão com lente de desigualdades → exposição. O Material Impresso atua como caderno consumível (inventários, matrizes, rascunhos e checklists); o produto final é a mostra — visível e dialogável. Produto: Mostra de HQs Éticas “Antes de Postar” (galeria/varal com HQs de 4 quadros por equipe, mediadas pelos estudantes). Roadmap do bimestre A1 — Retrato digital (AC.8.2): inventário “habilidades → usos → efeitos” e foco de melhoria. A2 — Linguagem empática (C.8.2/C.8.3): banco de falas e reparações para roteiros. A3 — Dilemas do feed (TD.8.1): quem é afetado, por quê, com que consequências. A4 — Régua ética v1 (TD.8.2/TD.8.3): perguntas-critério aplicadas ao enredo. (entrega intermediária) A5 — “Quando dá ruim” (P.8.2): planos de resposta em 3 passos dentro da história. A6 — Desigualdades e proteções (E.8.2): ajustes no roteiro com apoios reais. A7 — Exposição (C.8.4/TD.8.3): Mostra de HQs + pactos de convivência. (entrega final) | F44: 1 | G44: Autoconhecimento | H44: Cultivar habilidades que conectem quem somos hoje com quem desejamos ser no futuro. | I44: Meu retrato digital — habilidades e usos A aula propõe um percurso de mapeamento do que já sei fazer (inclusive no mundo digital) ee seus usos no cotidiano on‑line. Para mobilizar AC.8.2, os estudantes constroem um inventário pessoal (o que sei fazer / como uso / efeitos positivos e negativos) e identificam um ponto de atenção para o bimestre. Este material alimentará a criação das HQs ao longo do bimestre, por isso, será importante que essa aula apresente a proposta do bimestre: a construção de uma série de HQs "Antes de postar". | J44: O que eu já sei fazer e o que tenho feito com isso? | K44: Autovalorização consciente | L44: Reconhecer | M44: AC.8.2 Reconhecer as próprias habilidades e seus usos.
B45: Anos Finais | C45: 8º | D45: 2º | F45: 2 | G45: Convivência | H45: Agir com empatia, sendo capaz de compreender as perspectivas e os sentimentos dos outros. | I45: Antes de postar — empatia nas mensagens (roteiro para HQ) A aula propõe leitura de contexto, tom e intenção em mensagens ambíguas e a reescrita empática de falas. Para mobilizar C.8.2/C.8.3, a turma treina paráfrase empática, pedidos claros e reparação, compondo um ‘banco de falas’ que será usado nos roteiros de HQ. | J45: O que os outros estão sentindo? | K45: Sensibilidade emocional | L45: Observar-se | M45: C.8.2 Diferenciar os próprios sentimentos dos sentimentos dos outros em diferentes situações. C.8.3 Agir com empatia em diferentes situações.
B46: Anos Finais | C46: 8º | D46: 2º | F46: 3 | G46: Tomada de decisão | H46: Usar valores éticos como critérios para a tomada de decisão. | I46: Dilemas do feed — o que é ético aqui? (roteiro de cena) A aula propõe analisar casos de redes (boatos, exposição sem consentimento, desafios perigosos), nomeando implicações éticas. Para mobilizar TD.8.1, os estudantes listam quem é afetado, por quê e com quais consequências — esboçando cenas para as HQs. | J46: Como saber se uma decisão é ética ou não? | K46: Compromisso com o que é justo | L46: Refletir | M46: TD.8.1 Avaliar as implicações éticas de diferentes decisões.
B47: Anos Finais | C47: 8º | D47: 2º | F47: 4 | G47: Tomada de decisão | H47: Usar valores éticos como critérios para a tomada de decisão. | I47: Minha régua ética — critérios que guiam a história (v1) A aula propõe diferenciar valores éticos de antiéticos e construir uma régua pessoal de decisão. Para mobilizar TD.8.2/TD.8.3, os estudantes definem perguntas‑chave e aplicam em 2–3 rascunhos de HQ, ajustando enredo e falas. | J47: Tudo o que eu valorizo é bom para mim e para os outros? | K47: Autocrítica | L47: Reconhecer | M47: TD.8.2 Diferenciar valores éticos de antiéticos. TD.8.3 Experimentar diferentes critérios para tomar decisões.
B48: Anos Finais | C48: 8º | D48: 2º | F48: 5 - aula complementar | G48: Planejamento - aula complementar | H48: Elaborar planos alternativos para lidar com imprevistos e frustrações sem perder de vista seus objetivos. | I48: Quando dá ruim — planos de resposta em 3 passos (roteirização) A aula propõe inserir nos roteiros **planos de resposta** para incidentes (conta invadida, print fora de contexto, perfil falso), definindo passos, apoios e prazos dentro da narrativa. Para mobilizar P.8.2, cada equipe roteiriza uma cena‑imprevisto com solução responsável. | J48: O que posso fazer para lidar melhor com imprevistos e frustrações? | K48: Abertura | L48: Escutar | M48: P.8.2 Conhecer formas de lidar com imprevistos e frustrações.
B49: Anos Finais | C49: 8º | D49: 2º | F49: 6 | G49: Engajamento | H49: Compreender seu papel na sociedade e as formas pelas quais pode contribuir para sua melhoria. | I49: Quem fica mais exposto? — privilégios e proteções na história A aula propõe reconhecer privilégios/desvantagens que atravessam o on‑line e ajustar a HQ para representar cuidados solidários. Para mobilizar E.8.2, as equipes inserem personagens/práticas de proteção e suporte entre pares. | J49: Quais são meus privilégios e minhas desvantagens na sociedade? | K49: Consciência social | L49: Refletir | M49: E.8.2 Reconhecer seus privilégios e suas desvantagens na sociedade.
B50: Anos Finais | C50: 8º | D50: 2º | F50: 7 | G50: Convivência + Tomada de decisão (síntese) | H50: - Agir com empatia, sendo capaz de compreender as perspectivas e os sentimentos dos outros. - Usar valores éticos como critérios para a tomada de decisão. | I50: Mostra de HQs Éticas “Antes de Postar” — montagem e mediação A aula propõe finalizar as HQs (4 quadros por equipe), montar um varal/galeria e preparar uma mediação breve para visitantes. Para mobilizar C.8.4/TD.8.3, a turma promove diálogo com vozes diversas e pactos de convivência digital. | J50: O que aconteceria no mundo se as pessoas fossem mais empáticas? | K50: Compromisso com o bem comum | L50: Transformar | M50: C.8.4 Compreender como a empatia pode ajudar a construir futuros melhores para todos. TD.8.3 Experimentar diferentes critérios para tomar decisões.
B51: Anos Finais | C51: 9º | D51: 2º | E51: Cuidar de si e do outro: limites, respeito e vínculos Há momentos em que a vida pede pausa: respirar, nomear, pedir ajuda, combinar cuidados. Este projeto desenha uma ponte do eu que se cuida ao nós que se respeita, para que as relações sustentem escolhas melhores. O início é íntimo e prático: cada estudante olha para si, identifica gatilhos e recursos e cria formas saudáveis de lidar com as próprias fragilidades (AC.9.2 Criar formas saudáveis de lidar com as próprias fragilidades). Esse plano pessoal inaugura o fio do bimestre e já antecipa o produto. Com esse chão, passamos às bordas que protegem o vínculo: a turma observa situações cotidianas, ajusta linguagem e considera o bem-estar dos outros nas decisões da vida cotidiana (C.9.2), redigindo um “contrato de respeito e fronteiras” (rascunho). Para decidir melhor, abrimos espaço às vozes de experiência: compreender a importância de ouvir pessoas mais experientes antes de tomar decisões (TD.9.2) vira prática com roteiros de pedido de ajuda e mapeamento de conselheiros. Planejar é cuidar do que sustenta: avaliar sua rede de apoio atual e o que fazer para fortalecê-la (P.9.2) transforma nomes e vínculos em um mapa acionável. Também olhamos para o que exige coragem: proteger a si mesmo e aos outros de riscos e perigos para o bem-estar físico e psicológico (C.9.3) se traduz em protocolos simples de prevenção, denúncia e reparação; e quando a pressão dos pares pesa, ensaiamos frases, gestos e saídas para resistir à pressão negativa (TD.9.3). O bimestre culmina num gesto coletivo: uma “Caixa dos Vínculos Respeitosos”, com peças úteis e combinadas — plano pessoal sintetizado, contrato de respeito, cartão “como peço ajuda” (com conselheiros), mapa de rede de apoio, cartões “se acontecer…” e plano antipressão — pactuada com famílias. É uma caixa, mas também um acordo de cuidado para o restante do ano. Fio condutor: Trabalhar do pessoal ao público: plano pessoal (AC.9.2) → contrato de respeito (C.9.2) → pedir ajuda (TD.9.2) → rede que sustenta (P.9.2) → proteger e reparar (C.9.3) → dizer não sob pressão (TD.9.3) → montagem e pacto com famílias (E.9.2). Em cada aula, deixar claro o que nasce (rascunho/peça) e como volta nas seguintes para revisão/integração na caixa. O Material Impresso é caderno consumível de processo; o produto é a Caixa montada e pactuada. Produto: Caixa dos Vínculos Respeitosos (kit físico da sala com plano pessoal sintetizado; contrato de respeito; cartão “como peço ajuda” + rede; cartões “se acontecer…”; plano antipressão). Roadmap 1) Plano pessoal (v1) — AC.9.2 · 2) Contrato de respeito (rascunho) — C.9.2 · 3) Pedido de ajuda — TD.9.2 · 4) Rede que apoia — P.9.2 · 5) Proteger e reparar — C.9.3 · 6) Plano antipressão — TD.9.3 · 7) Montagem + pacto — E.9.2. | F51: 1 | G51: Autoconhecimento | H51: Compreender as fragilidades como parte da identidade, buscando formas saudáveis de lidar com elas e caminhos possíveis de superação. | I51: Cuidar de mim com estratégia — plano pessoal de autocuidado (v1) A aula propõe um percurso de identificação de gatilhos, recursos e passos realistas de cuidado. Para mobilizar AC.9.2, os estudantes constroem um plano pessoal (v1) que será testado e revisado ao longo do bimestre e cujo resumo comporá a "Caixa dos Vínculos Respeitosos". ENTREGA: Plano pessoal de autocuidado (v1). | J51: Como posso lidar com as minhas fragilidades? | K51: Cuidado consigo | L51: Cuidar | M51: AC.9.2 Criar formas saudáveis de lidar com as próprias fragilidades.
A52: X | B52: Anos Finais | C52: 9º | D52: 2º | F52: 2 - Aula complementar | G52: Convivência - Aula complementar | H52: Agir com responsabilidade, considerando o impacto das próprias decisões no bem-estar físico e psicológico dos outros. | I52: Relações que respeitam — fronteiras, linguagem e combinados (rascunho) A aula propõe mapear sinais de respeito/irrespeito, ajustar linguagem e redigir um ‘contrato de respeito e fronteiras’ da turma. Para mobilizar C.9.2, a turma escreve um rascunho de contrato que entrará como peça da "Caixa" (versão final na A7). | J52: O que o bem-estar dos outros tem a ver comigo? | K52: Responsabilidade relacional | L52: Decidir | M52: C.9.2 Considerar o bem-estar dos outros nas decisões da vida cotidiana.
B53: Anos Finais | C53: 9º | D53: 2º | F53: 3 | G53: Tomada de decisão | H53: Compreender o papel que outras pessoas podem ter no processo de tomada de decisão dos estudantes. | I53: Ouvir experiência antes de decidir — aprender a pedir ajuda A aula propõe praticar pedidos de ajuda e escuta ativa com adultos de confiança. Para mobilizar TD.9.2, os estudantes roteirizam falas, identificam conselheiros e planejam como e quando contatá-los. Um cartão ‘Como peço ajuda’ integrará a "Caixa". | J53: Como as pessoas mais experientes podem ajudar a tomar decisões melhores? | K53: Respeito pela experiência do outro | L53: Escutar | M53: TD.9.2 Compreender a importância de ouvir pessoas mais experientes antes de tomar decisões.
B54: Anos Finais | C54: 9º | D54: 2º | F54: 4 | G54: Planejamento | H54: Planejar a transição para o Ensino Médio com base em quem desejam ser e no que desejam conquistar nessa nova etapa. | I54: Rede que apoia — mapear, fortalecer, ativar A aula propõe mapear apoios e definir 2 ações de fortalecimento por vínculo. Para mobilizar P.9.2, os estudantes produzem um ‘Mapa de Rede de Apoio’ e escolhem quais contatos entram no verso do cartão ‘Como peço ajuda’ (A3), compondo a "Caixa". | J54: Quem me apoia? | K54: Gratidão | L54: Acolher | M54: P.9.2 Avaliar sua rede de apoio atual e o que fazer para fortalecê-la.
B55: Anos Finais | C55: 9º | D55: 2º | F55: 5 | G55: Convivência | H55: Agir com responsabilidade, considerando o impacto das próprias decisões no bem-estar físico e psicológico dos outros. | I55: Proteger e reparar — protocolos de cuidado A aula propõe construir protocolos de prevenção/denúncia e práticas de reparação quando há dano. Para mobilizar C.9.3, a turma cria cartões ‘Se acontecer…’ (passos, canais, pessoas) e um roteiro de reparação que integrarão a "Caixa". | J55: O que pode ferir o bem-estar dos outros? | K55: Coragem ética | L55: Reparar | M55: C.9.3 Proteger a si mesmo e aos outros de riscos e perigos para o bem-estar físico e psicológico.
B56: Anos Finais | C56: 9º | D56: 2º | F56: 6 | G56: Tomada de decisão | H56: Compreender o papel que outras pessoas podem ter no processo de tomada de decisão dos estudantes. | I56: Dizer não sob pressão — frases, gestos e saídas A aula propõe simular cenários de pressão entre pares e treinar respostas verbais e não verbais. Para mobilizar TD.9.3, cada estudante prepara um ‘Plano pessoal anti-pressão’ que também entrará na "Caixa". | J56: Como posso resistir à influência negativa de amigos e colegas? | K56: Posicionamento | L56: Decidir | M56: TD.9.3 Resistir à pressão negativa entre pares, evitando que eles influenciem a tomada de decisões irresponsáveis.
B57: Anos Finais | C57: 9º | D57: 2º | F57: 7 | G57: Engajamento (síntese) | H57: Comprometer-se com ações éticas e conscientes no presente, que contribuam para a construção de futuros melhores para si e para os outros. | I57: Montar e pactuar — a Caixa dos Vínculos Respeitosos (final) A aula propõe revisar todas as peças (plano pessoal, contrato de respeito, cartões de ajuda, rede de apoio, protocolos, plano antipressão), montar a "Caixa dos Vínculos Respeitosos" da sala e firmar compromissos com a turma e famílias. Para mobilizar E.9.2, cada estudante pacta uma pequena melhoria em casa vinculada à convivência. | J57: — | K57: Visão de futuro | L57: Refletir | M57: E.9.2 Realizar melhorias na vida familiar.
B58: Anos Finais | C58: 6º | D58: 3º | E58: Vozes em Jogo: debater, influenciar e conquistar metas Este bimestre se organiza em torno da realização de uma Sessão de Debates Justos sobre temas de pertencimento à escola (uso dos espaços, regras de convivência, cuidado com o patrimônio). Para que o debate aconteça com qualidade e respeito, os estudantes caminham por etapas que se encadeiam: E.6.3 — Começamos recuperando a motivação pós-férias e escolhendo hábitos que sustentem o percurso (constância, foco, pausas). P.6.3 — Esta energia vira metas de curto prazo que organizam o preparo para o debate (ex.: pesquisar tema, treinar fala, ler textos). AC.6.3 — Em seguida, investigamos como cada um atua em grupo e quais papéis (comunicação, argumentação, organização) melhor aproveitam suas características. TD.6.3 — Antes de defender ideias, mapeamos influências (pares, família, redes, mídia) que pesam nas decisões e definimos critérios para acolher/recusar argumentos. C.6.3 — Por fim, entramos no bloco de Convivência (laboratório, ensaio e sessão), construindo argumentos sólidos, respeitando regras de fala e debatendo com clareza e respeito. O Material Impresso acompanha o percurso como caderno de trabalho (hábitos, metas, papéis, mapa de influências, fichas de argumento). O produto final é público e coletivo: a Sessão de Debates Justos (evento simples) e um Painel “Metas & Hábitos em Ação” da turma, que mostra como a motivação e o planejamento sustentaram a qualidade do debate. Roadmap das entregas e progressão A1 – Cartão de Hábitos (rascunho, MI): base de constância para o projeto. A2 – Plano de Metas (30 dias): ENTREGA #1; metas alinhadas ao preparo do debate. A3 – Mapa de papéis de grupo (MI): define como cada um contribui para cumprir as metas. A4 – Diagrama de influências (MI): critérios para filtrar argumentos e fontes. A5 – Fichas de argumento + rubrica (MI): laboratório → ensaio cronometrado. A6 – Dossiê do Debate + revisão de metas: ENTREGA #2; consolida aprendizado e planeja próximos passos. Produto: realização da Sessão de Debates Justos e montagem do Painel “Metas & Hábitos em Ação”. | F58: 1 | G58: Engajamento | H58: Manter a motivação necessária para realizar e concluir tarefas com autonomia e empenho pessoal. | I58: O que me move A aula propõe um percurso de reentrada pós-férias para mapear gatilhos de motivação e desmotivação e escolher hábitos que sustentem o projeto do bimestre (Sessão de Debates Justos). Para mobilizar a atividade E.6.3, os estudantes serão convidados a identificar padrões “liga/desliga” e iniciar um Cartão de Hábitos vinculado ao preparo do debate. Esta aula inaugura o projeto e prepara a A2 (metas que dependem desses hábitos). | J58: O que pode me motivar? | K58: Autonomia | L58: Reconhecer | M58: E.6.3 Conhecer hábitos e comportamentos que ajudam a manter a motivação.
B59: Anos Finais | C59: 6º | D59: 3º | F59: 2 | G59: Planejamento | H59: Estabelecer objetivos de curto prazo para organizar os estudos e conquistar metas pessoais na escola. | I59: Metas que saem do papel A aula propõe um percurso de definição de 2–3 metas de curto prazo diretamente ligadas à preparação para a Sessão de Debates. Para mobilizar a atividade P.6.3, os estudantes planejam objetivos com passos, prazos, apoios e evidências, conectando cada meta a 1–2 hábitos da A1. Esta aula retoma os hábitos (A1) e prepara a A3 (papéis em grupo para cumprir as metas). ENTREGA: Plano de Metas (30 dias). | J59: Como eu posso atingir meus objetivos acadêmicos? | K59: Proatividade | L59: Decidir | M59: P.6.3 Planejar objetivos de curto prazo para efetivar as mudanças desejadas.
B60: Anos Finais | C60: 6º | D60: 3º | F60: 3 | G60: Autoconhecimento | H60: Assumir e valorizar quem somos é o primeiro passo para nos tornar quem desejamos ser. | I60: Eu em grupo: meus papéis A aula propõe um percurso de autoobservação em tarefas cooperativas para ajustar papéis no projeto. Para mobilizar a atividade AC.6.3, os estudantes analisam como suas características aparecem nas relações e testam papéis (comunicação, argumentação, organização) que melhor ajudem a cumprir as metas da A2. Esta aula retoma as metas e prepara a A4 (critérios para lidar com influências ao pesquisar/defender ideias). | J60: Como eu sou quando estou com outras pessoas? | K60: Responsabilidade Relacional | L60: Refletir | M60: AC.6.3 Analisar o efeito das características pessoais que estão mais presentes nas próprias relações sociais.
B61: Anos Finais | C61: 6º | D61: 3º | F61: 4 | G61: Tomada de decisão | H61: Testar possibilidades de decisão em diferentes cenários e com a participação de diferentes atores. | I61: Quem me influencia? A aula propõe um percurso de mapeamento de influências (pares, família, mídias, contexto) e critérios para acolher/recusar argumentos. Para mobilizar a atividade TD.6.3, os estudantes reconhecem pessoas envolvidas e como impactam decisões ligadas ao tema do debate, evitando ‘efeito manada’. Esta aula retoma os papéis/grupo (A3) e prepara a construção de argumentos (A5). | J61: Como as pessoas influenciam as decisões uma das outras? | K61: Consciência da influência | L61: Reconhecer | M61: TD.6.3 Analisar a influência das pessoas envolvidas em uma situação para a tomada de decisão.
B62: Anos Finais | C62: 6º | D62: 3º | F62: 5 | G62: Convivência | H62: Aprender a se expressar com respeito, sem abrir mão da autenticidade, construindo relações de confiança com os demais. | I62: Laboratório de argumentos A aula propõe um percurso de construção de argumentos sólidos (tese–razão–exemplo) sobre temas de pertencimento escolar, aplicando critérios da A4. Para mobilizar a atividade C.6.3, os estudantes elaboram argumentos alinhados aos papéis definidos (A3) e às metas (A2). | J62: Como posso me preparar para situações de debate? | K62: Responsabilidade argumentativa | L62: Nomear | M62: C.6.3 Usar argumentos sólidos e condizentes com suas ideias em situações de debate.
B63: Anos Finais | C63: 6º | D63: 3º | F63: 6 | G63: Convivência | H63: Aprender a se expressar com respeito, sem abrir mão da autenticidade, construindo relações de confiança com os demais. | I63: Sessão de Debates Justos + revisão de metas A aula propõe um percurso de apresentação pública dos debates da turma e de síntese do aprendizado. Para mobilizar a atividade C.6.3, os estudantes participam da sessão, aplicam a rubrica, realizam autoavaliação e revisam o Plano de Metas (A2) à luz do desempenho e dos feedbacks. Esta aula consolida o projeto (A1–A6). ENTREGA: Dossiê do Debate (rubrica + autoavaliação) + revisão do Plano de Metas. | J63: Como posso me preparar para situações de debate? | K63: Responsabilidade argumentativa | L63: Nomear | M63: C.6.3 Usar argumentos sólidos e condizentes com suas ideias em situações de debate.
B64: Anos Finais | C64: 7º | D64: 3º | E64: Decidir com emoção e inclusão: Baralho “E se…?” Às vezes o que separa a boa intenção de uma boa decisão é ouvir: o que sentimos, o que o outro sente, o que a situação pede. Depois de avançar na fala respeitosa e no cuidado com o convívio, este bimestre convida a turma a construir, refinar e utilizar um recurso de decisão criado por eles: o Baralho “E se…?” — um conjunto de cartas-dilema, cartas-emoção e cartas-apoio (roteiros curtos de fala/escuta) para pensar antes de agir em situações reais da escola e das redes. O fio condutor é progressivo: interesse que me move → linguagem que inclui → dilema com emoções → revisão com vozes diversas → protocolo simples de uso → sessão piloto → baralho final com guia. O projeto começa no que faz sentido para cada estudante. Eles escolhem 1–2 interesses saudáveis que querem praticar e, a partir deles, identificam situações-semente que darão origem às cartas-dilema. Em seguida, a turma lapida a linguagem das cartas e cria cartas-apoio com princípios de Comunicação Não Violenta, garantindo clareza e respeito. Ao prototipar e testar as cartas, os estudantes analisam causas, opções e consequências, trazendo explicitamente as emoções envolvidas nas escolhas. Depois definem como o baralho será usado em sala real (duração, papéis, regras de escuta, quando chamar um adulto, como registrar decisões) e organizam uma sessão piloto simples. Então, conduzem a sessão piloto, coletam evidências mínimas (um insight, um acordo, um encaminhamento) e refinam o baralho e o protocolo para uso pela comunidade. o Material Impresso funciona como caderno consumível do processo (situações-semente, versões das cartas, checklist de linguagem, matriz de decisão com emoções, protocolo, relato da sessão piloto). Produto: Baralho “E se…?” (versão 3) + Guia de uso (1 página) — recurso autoral e simples para pensar junto antes de agir, disponível para a turma e para outros estudantes da escola, como legado concreto de comunicação respeitosa, decisão consciente e cooperação. A3: Mini-deck v1 A5: Relato da sessão piloto + ajustes A6: Baralho v3 + Guia de uso (1 pág.) (conquista do bimestre) | F64: 1 | G64: Autoconhecimento | H64: Escolher o que nos interessa é também escolher quem estamos nos tornando. | I64: Do meu interesse ao dilema — investigando o que importa No retorno do bimestre, a aula propõe um percurso de retomada e exploração de interesses éticos e saudáveis para identificar contextos reais de decisão relacionados a eles (grupo de estudos, redes, amizade, uso de tempo). Para mobilizar AC.7.3, os estudantes escolhem 1–2 interesses para praticar no bimestre e, a partir deles, descrevem situações‑semente que poderão virar cartas‑dilema do Baralho ‘E se…?’. A mediação destaca relação entre valores, escolhas e emoções envolvidas (curiosidade, medo, empolgação). | J64: Eu me interesso por coisas que fazem a minha vida ser melhor? | K64: Responsabilidade pessoal | L64: Decidir | M64: AC.7.3 Se aprofundar e/ou praticar novos interesses éticos e saudáveis.
B65: Anos Finais | C65: 7º | D65: 3º | F65: 2 | G65: Convivência | H65: Utilizar os princípios da comunicação não violenta para expressar-se com respeito, empatia e assertividade. | I65: Linguagem que inclui — escrevendo sem ferir A aula propõe um percurso de lapidação da linguagem para redigir cartas do baralho de modo claro, respeitoso e inclusivo (diversidade cultural e de gênero), evitando estereótipos e microagressões. Para mobilizar C.7.3, a turma elabora ‘roteiros de fala/escuta’ curtos (eu‑mensagem, pedidos, reparação) que serão usados nas cartas‑apoio (cartas‑resposta). | J65: A forma como eu falo com os outros me ajuda ou me atrapalha? | K65: Auto‑observação | L65: Refletir | M65: C.7.3 Conhecer e usar os princípios da comunicação não violenta na escola.
B66: Anos Finais | C66: 7º | D66: 3º | F66: 3 | G66: Tomada de decisão | H66: Tomar decisões baseadas na análise das causas e consequências das situações. | I66: Prototipando o baralho — cartas‑dilema e cartas‑emoção (v1) A aula propõe transformar as situações‑semente em cartas‑dilema objetivas (‘E se…?’) e criar cartas‑emoção que ajudem a explicitar como me sinto/como os outros se sentirão. Para mobilizar TD.7.3, as equipes associam a cada dilema: causas, opções possíveis e primeiras hipóteses de consequências (curto/médio prazo). Ao final, organizam um primeiro mini‑deck para teste interno. Neste momento do projeto, será importante apresentar o modelo do baralho "E se...", a fim de que os estudantes compreendem para qual tipo de projeto deverão escrever as cartas. | J66: Que tipo de consequências uma decisão pode ter? | K66: Responsabilidade | L66: Decidir | M66: TD.7.3 Tomar decisões pessoais e históricas baseadas na análise de causas e consequências.
B67: Anos Finais | C67: 7º | D67: 3º | F67: 4 | G67: Planejamento | H67: Definir objetivos de curto e médio prazo em diferentes áreas da vida, utilizando estratégias e ferramentas para alcançá-los. | I67: Como vamos usar? — protocolo simples para sala real A aula propõe definir "como" o baralho será usado em contexto real (duração, papéis, regras de escuta, quando chamar adulto, como registrar decisões). Para mobilizar P.7.3, a turma define um objetivo de curto prazo (testar em 1 turma/coletivo), planeja a sessão piloto e combina evidências mínimas (ex.: 1 insight; 1 mudança de fala; 1 ação acordada). | J67: Como posso me organizar para realizar de fato meus objetivos? | K67: Organização e perseverança | L67: Realizar | M67: P.7.3 Realizar objetivos para experimentar a autoeficácia.
B68: Anos Finais | C68: 7º | D68: 3º | F68: 5 | G68: Engajamento | H68: Estar atento e comprometido com as necessidades e demandas da escola, da comunidade e das pessoas com quem convive. | I68: Sessão piloto — usar para decidir juntos (v2) A aula propõe realizar uma "sessão piloto" com o baralho (em outra turma da série, no grêmio ou no próprio grupo), seguindo o protocolo v1. Para mobilizar E.7.3, os estudantes assumem papéis, conduzem a discussão e registram evidências mínimas (o que perceberam, 1 acordo, 1 pedido de ajuda quando necessário). Ao final, coletam 1 feedback do grupo atendido para ajustar o baralho/protocolo. | J68: Como posso ajudar as pessoas da minha escola e família? | K68: Colaboração | L68: Organizar-se | M68: E.7.3 Organizar-se com outras pessoas para atender necessidades e demandas do seu entorno.
B69: Anos Finais | C69: 7º | D69: 3º | F69: 6 | G69: Síntese (integra dimensões) | H69: - Utilizar os princípios da comunicação não violenta para expressar-se com respeito, empatia e assertividade. - Tomar decisões baseadas na análise das causas e consequências das situações. - Utilizar os princípios da comunicação não violenta para expressar-se com respeito, empatia e assertividade. - Definir objetivos de curto e médio prazo em diferentes áreas da vida, utilizando estratégias e ferramentas para alcançá-los. - Estar atento e comprometido com as necessidades e demandas da escola, da comunidade e das pessoas com quem convive. | I69: Baralho “E se…?” pronto para a escola — guia de uso e compromissos A aula propõe consolidar o "Baralho ‘E se…?’" (mini‑deck v3) e um "guia de uso de 1 página" com protocolo final (quando usar, papéis, cuidados, como chamar adulto, como registrar decisões). A síntese valoriza o percurso: interesse → linguagem inclusiva → dilema com emoções → teste → protocolo → uso piloto. Os estudantes pactuam como o baralho poderá ser solicitado/emprestado na escola. | J69: - Que tipo de consequências uma decisão pode ter? - A forma como eu falo com os outros me ajuda ou me atrapalha? - Como posso me organizar para realizar de fato meus objetivos? - Como posso ajudar as pessoas da minha escola e família? | K69: - Responsabilidade - Auto‑observação - Organização e perseverança - Colaboração | L69: - Decidir - Refletir - Realizar - Organizar-se | M69: TD.7.3 C.7.3 P.7.3 E.7.3
B70: Anos Finais | C70: 8º | D70: 3º | E70: Mutirão Relâmpago + Carta de Continuidade A escola é território: tem dores, desejos, potências. Este projeto desloca o “eu posso” para o “nós fazemos”, com passos curtos e efeitos concretos. O início é autocultivo: cada estudante escolhe uma habilidade a desenvolver (mediação, organização, fala pública…) e define formas simples de prática e evidência (AC.8.3 Desenvolver novas habilidades). De posse de um “músculo em treino”, saímos a escutar: entrevistas breves com colegas, funcionários e famílias levantam demandas reais (C.8.3 Agir com empatia em diferentes situações). Para decidir o que fazer agora, a turma define critérios claros (impacto, viabilidade, equidade), compara alternativas e formaliza a escolha em ata pública (TD.8.3 Experimentar diferentes critérios para tomar decisões). Planejamos a intervenção com planos B/C — imprevistos são regra, não exceção (P.8.3 Usar ferramentas de planejamento para lidar com possíveis imprevistos e frustrações) — e distribuímos papéis valorizando talentos diversos (E.8.3 Reconhecer que todas as pessoas têm algo para oferecer à sociedade). Vem então o Mutirão Relâmpago (30–40 min): ação enxuta, registrada com evidências e devolutivas (C.8.3 / E.8.1 Criticar e elogiar características da sociedade, incluindo percepções familiares e comunitárias). Nada termina aqui: a turma avalia, decide continuidade com base em valores éticos (TD.8.4 Usar valores éticos como critérios para tomar decisões para o futuro) e escreve uma Carta de Continuidade comprometendo-se com próximos passos para melhorar o que foi iniciado (E.8.4 Compreender o que pode fazer para contribuir com melhorias na sociedade). Fio condutor: Estruturar um arco só: habilidade-alvo → escuta → decisão com critérios (ata) → plano com B/C → papéis → mutirão → carta. O Material Impresso organiza escutas, matrizes, canvas, mapas de papéis e evidências; o produto final é a ação + compromisso. Produto: Mutirão Relâmpago (execução piloto) + Carta de Continuidade (próximos passos pactuados). Roadmap do bimestre A1 — Habilidade-alvo (AC.8.3): plano micro de prática e indicadores. A2 — Escuta do território (C.8.3): entrevistas curtas; 3 prioridades da turma. A3 — Decidir com critérios (TD.8.3): matriz e Ata de decisão. (entrega intermediária) A4 — Plano com B/C (P.8.3): passos, prazos, riscos e alternativas. A5 — Mutirão Relâmpago (C.8.3/E.8.1): execução e evidências. A6 — Avaliar e seguir (TD.8.4/E.8.4): Carta de Continuidade. (entrega final) | F70: 1 | G70: Autoconhecimento | H70: Cultivar habilidades que conectem quem somos hoje com quem desejamos ser no futuro. | I70: Minha habilidade‑alvo para agir no território A aula propõe escolher 1 habilidade a desenvolver (ex.: mediação, organização, fala pública) e planejar micro‑treinos semanais. Para mobilizar AC.8.3, os estudantes definem indicadores simples de prática conectados à ação comunitária. | J70: Quais habilidades eu gostaria de ter, mas ainda não desenvolvi? | K70: Persistência com propósito | L70: Transformar | M70: AC.8.3 Desenvolver novas habilidades.
B71: Anos Finais | C71: 8º | D71: 3º | F71: 2 | G71: Convivência | H71: Agir com empatia, sendo capaz de compreender as perspectivas e os sentimentos dos outros. | I71: Escutar para agir — mapeando demandas do território A aula propõe entrevistas curtas com colegas/funcionários/comunidade para levantar dores, desejos e propostas. Para mobilizar C.8.3, a turma sintetiza uma nuvem de demandas e destaca 3 prioridades. | J71: Como posso considerar o que os outros pensam e sentem em minhas ações? | K71: Consideração | L71: Cuidar | M71: C.8.3 Agir com empatia em diferentes situações.
B72: Anos Finais | C72: 8º | D72: 3º | F72: 3 | G72: Tomada de decisão | H72: Usar valores éticos como critérios para a tomada de decisão. | I72: Escolha com critérios — qual ação faz mais sentido agora? A aula propõe definir e ponderar critérios (impacto, viabilidade, equidade) e decidir a intervenção do mutirão. Para mobilizar TD.8.3, os estudantes justificam a escolha com base nos critérios e redigem uma ata curta. | J72: O que faz com que eu decida por uma coisa em relação a outra? | K72: Abertura | L72: Decidir | M72: TD.8.3 Experimentar diferentes critérios para tomar decisões.
B73: Anos Finais | C73: 8º | D73: 3º | F73: 4 | G73: Planejamento | H73: Elaborar planos alternativos para lidar com imprevistos e frustrações sem perder de vista seus objetivos. | I73: Plano de ação com planos B/C — do papel ao pátio A aula propõe detalhar tarefas, cronograma e recursos, prevendo riscos e alternativas. Para mobilizar P.8.3, a turma produz um canvas da ação com planos B/C. | J73: O que posso fazer para lidar melhor com imprevistos e frustrações? | K73: Adaptação estratégica | L73: Decidir | M73: P.8.3 Usar ferramentas de planejamento para lidar com possíveis imprevistos e frustrações.
B74: Anos Finais | C74: 8º | D74: 3º | F74: 5 | G74: Convivência + Engajamento | H74: - Agir com empatia, sendo capaz de compreender as perspectivas e os sentimentos dos outros. - Compreender seu papel na sociedade e as formas pelas quais pode contribuir para sua melhoria. | I74: Mutirão Relâmpago — mãos à obra e evidências A aula propõe executar a intervenção planejada em 30–40 minutos, registrar evidências e coletar percepções das pessoas envolvidas. Para mobilizar C.8.3/E.8.1, registram o que funcionou e o que precisa melhorar. | J74: - Como posso considerar o que os outros pensam e sentem em minhas ações? - O que há de bom e de ruim na sociedade? | K74: - Consideração - Senso crítico | L74: - Cuidar - Argumentar | M74: C.8.3 Agir com empatia em diferentes situações. E.8.1 Criticar e elogiar características da sociedade, incluindo percepções familiares e comunitárias.
B75: Anos Finais | C75: 8º | D75: 3º | F75: 6 | G75: Tomada de decisão + Engajamento (síntese) | H75: - Usar valores éticos como critérios para a tomada de decisão. - Compreender seu papel na sociedade e as formas pelas quais pode contribuir para sua melhoria. | I75: Avaliar e seguir — carta de continuidade A aula propõe revisar a ação com vozes diversas, discutir efeitos e decidir continuidade/ajustes coletivamente. Para mobilizar TD.8.4/E.8.4, produzem uma carta de continuidade com próximos passos. | J75: - Como a ética pode estar presente nas decisões para o meu futuro? - O que posso fazer para tornar a sociedade melhor? | K75: - Coerência - Senso de responsabilidade social | L75: - Refletir - Transformar | M75: TD.8.4 Usar valores éticos como critérios para tomar decisões para o futuro. E.8.4 Compreender o que pode fazer para contribuir com melhorias na sociedade.
B76: Anos Finais | C76: 9º | D76: 3º | E76: Transição segura: escolhas on/offline e metas para o Ensino Médio Transição é verbo: decidir, proteger, planejar e agir. O projeto organiza essas ações em “rotas” visíveis, que a turma monta num Painel Interativo. Começamos revisitando o que ainda pesa e como superar (AC.9.3). Em seguida, construímos protocolos de segurança on/offline (C.9.3) e ensaiamos respostas sob pressão (TD.9.3). Com o terreno mais estável, definimos metas para o EM (P.9.3), realizamos uma micro-ação de melhoria na escola (E.9.3) e, por fim, simulamos cenários com rotas de apoio (TD.9.4/P.9.4). As “rotas” se colam no painel e viram referência para a chegada ao novo ciclo. Fio do projeto: do superar (eu comigo) → para o proteger (eu e os outros) → para o resistir (eu entre pares) → para o definir metas (eu e meu futuro) → para o agir na escola (eu e o espaço comum) → para o preparar contingências (eu e a rede) → para o pactuar (eu, família e turma). Produto: Painel Interativo “Rotas de Transição Segura” + registro da micro-ação na escola. Roadmap: A1 plano de superação (AC.9.3, v1) A2 protocolo de proteção (C.9.3) A3 checklist antipressão (TD.9.3) A4 metas EM (P.9.3, v1) · A5 micro-ação na escola (E.9.3) A6 montagem e apresentação do Painel (pactos 30 dias). | F76: 1 | G76: Autoconhecimento | H76: Compreender as fragilidades como parte da identidade, buscando formas saudáveis de lidar com elas e caminhos possíveis de superação. | I76: Superar para seguir — plano de superação (v1) A aula propõe revisar fragilidades e desenhar estratégias de superação alinhadas à transição. Para mobilizar AC.9.3, os estudantes produzem um plano de superação (v1) que alimentará as ‘rotas’ do painel. | J76: Como posso superar minha fragilidades? | K76: Esperança | L76: Transformar | M76: AC.9.3 Analisar como as fragilidades pessoais podem ser superadas.
B77: Anos Finais | C77: 9º | D77: 3º | F77: 2 | G77: Convivência | H77: Agir com responsabilidade, considerando o impacto das próprias decisões no bem-estar físico e psicológico dos outros. | I77: Segurança on/offline — protocolos práticos A aula propõe um percurso que liga as fragilidades mapeadas na A1 (gatilhos pessoais, medos, pontos sensíveis) aos riscos de desinformação (fake news) e de exposição on/offline. Para mobilizar C.9.3, os estudantes analisam como boatos, montagens e conteúdo fora de contexto podem atingir pontos de fragilidade individual e coletiva, e elaboram um protocolo prático de proteção com duas frentes: “STOP antes de compartilhar” (parar–verificar–considerar impacto–decidir), e “Se acontecer…” (o que fazer ao sofrer ou presenciar dano: passos, canais, pessoas de confiança). Esse protocolo será colado na rota “Proteção” do Painel Interativo. | J77: O que pode ferir o bem-estar dos outros? | K77: Coragem ética | L77: Reparar | M77: C.9.3 Proteger a si mesmo e aos outros de riscos e perigos para o bem-estar físico e psicológico.
B78: Anos Finais | C78: 9º | D78: 3º | F78: 3 | G78: Tomada de decisão | H78: Compreender o papel que outras pessoas podem ter no processo de tomada de decisão dos estudantes. | I78: Antipressão na prática — respostas e aliados A aula propõe ensaiar respostas sob pressão de pares e mapear aliados. Para mobilizar TD.9.3, cada estudante compõe um checklist pessoal anti-pressão que integrará o Painel. | J78: Como posso resistir à influência negativa de amigos e colegas? | K78: Posicionamento | L78: Decidir | M78: TD.9.3 Resistir à pressão negativa entre pares, evitando que eles influenciem a tomada de decisões irresponsáveis.
B79: Anos Finais | C79: 9º | D79: 3º | F79: 4 | G79: Planejamento | H79: Planejar a transição para o Ensino Médio com base em quem desejam ser e no que desejam conquistar nessa nova etapa. | I79: Metas para o EM — primeiros passos (v1) A aula propõe definir objetivos acadêmicos e pessoais e destrinchá‑los em passos de curto prazo. Para mobilizar P.9.3, as metas (v1) comporão a parte ‘Rumo ao EM’ do Painel. | J79: O que eu quero conquistar durante o Ensino Médio? | K79: Autodeterminação | L79: Decidir | M79: P.9.3 Estabelecer objetivos para o Ensino Médio.
B80: Anos Finais | C80: 9º | D80: 3º | F80: 5 | G80: Engajamento | H80: Comprometer-se com ações éticas e conscientes no presente, que contribuam para a construção de futuros melhores para si e para os outros. | I80: Micro-ação na escola — melhorar para aprender melhor A aula propõe escolher e executar uma micro-ação de melhoria na escola (limpeza de espaço, sinalização de coleta, cantinho de leitura etc.). Para mobilizar E.9.3, registram efeito e lições para a transição. | J80: Como posso melhorar a vida na minha escola? | K80: Comprometimento com o bem comum | L80: Transformar | M80: E.9.3 Realizar melhorias na vida escolar.
B81: Anos Finais | C81: 9º | D81: 3º | F81: 6 | G81: Tomada de decisão + Planejamento | H81: Compreender o papel que outras pessoas podem ter no processo de tomada de decisão dos estudantes. / Planejar a transição para o Ensino Médio com base em quem desejam ser e no que desejam conquistar nessa nova etapa. | I81: Cenários e rotas de apoio — meu plano de contingência (v1) A aula propõe simular cenários de risco e traçar planos de contingência com pessoas de confiança. Para mobilizar TD.9.4 e P.9.4, os estudantes geram ‘rotas de apoio’ que serão coladas no Painel. | J81: Quem eu quero ser no Ensino Médio? | K81: Engajamento com o futuro | L81: Refletir | M81: TD.9.4 Decidir o perfil de adolescente que deseja ser no Ensino Médio. / P.9.4 Usar ferramentas para planejar a conquista de seus objetivos no Ensino Médio.
B82: Anos Finais | C82: 6º | D82: 4º | E82: Rotas para o Futuro Próximo: intenção, autenticidade e constância Encerrando o 6º ano, este projeto convida os estudantes a escolher intencionalmente características que desejam cultivar, a praticar autenticidade com respeito e limites no cotidiano, a testar decisões em cenários reais ouvindo vozes diversas, a monitorar o próprio progresso e a sustentar a motivação ao longo do tempo. O percurso avança em etapas conectadas: inicia com a seleção de características desejáveis (AC.6.4), aprofunda como se expressar com autenticidade nas relações (C.6.4), desenha e revisa decisões para o futuro próximo com base em cenários e consultas (TD.6.4), cria indicadores simples de evolução acadêmica (P.6.4) e organiza um kit de persistência para atravessar 30–60–90 dias (E.6.4). As aulas se encadeiam explicitando o elo entre elas: o que é escolhido como valor (A1) aparece na fala com respeito (A2), orienta as decisões construídas em diálogo (A3–A4), é acompanhado por indicadores claros (A5) e sustentado por estratégias de constância (A6–A7). Produto: Mostra “Rotas 30–60–90” (mural coletivo simples) + Roteiro 30–60–90 (individual). Entregas formais: A4 — Mapa de Decisão v2; A5 — Painel de monitoramento (semáforo + indicadores); A7 — Roteiro 30–60–90 consolidado. Material Impresso: usado como caderno de trabalho (listas, roteiros, mapas, indicadores); não é o produto final. Roadmap A1 – Lista 3–2–1 de características (AC.6.4): semente do projeto (MI). A2 – Roteiros de fala autêntica (C.6.4): ensaio para limites e pedidos (MI). A3 – Mapa de Decisão v1 (TD.6.4): cenários, vozes e opções (MI). A4 – Mapa de Decisão v2 (TD.6.4): ENTREGA #1 (versão revisada após escuta). A5 – Painel de monitoramento (P.6.4): ENTREGA #2 (indicadores + semáforo). A6 – Roteiro 30–60–90 consolidado + Mostra pública: ENTREGA #3 (síntese final). Produto do bimestre: Mostra ‘Rotas 30–60–90’ (mural coletivo) + Roteiro 30–60–90 (individual). | F82: 1 | G82: Autoconhecimento | H82: Assumir e valorizar quem somos é o primeiro passo para nos tornar quem desejamos ser. | I82: Quem quero cultivar em mim A aula propõe um percurso de nomeação de qualidades a desenvolver no próximo trimestre, explicando autenticidade em termos concretos (coerência entre valores, pensamentos, sentimentos, palavras e ações, com respeito e limites). Para mobilizar a atividade AC.6.4, os estudantes serão convidados a criar uma lista priorizada (3–2–1) de características desejáveis, ligando cada uma a pequenos gestos diários que possam ser observados. Este encontro deverá ser dedicado à produção da Lista 3–2–1 e do primeiro rascunho de gestos diários que serão acompanhados no bimestre. Produto em construção: Lista 3–2–1 + gestos (MI). (sem entrega formal) | J82: Quais características eu gostaria de ter para me tornar a pessoa que desejo ser no futuro? | K82: Intencionalidade | L82: Decidir | M82: AC.6.4 Criar uma lista de caracteríticas desejáveis de serem desenvolvidas.
B83: Anos Finais | C83: 6º | D83: 4º | F83: 2 | G83: Convivência | H83: Aprender a se expressar com respeito, sem abrir mão da autenticidade, construindo relações de confiança com os demais. | I83: Autenticidade no cotidiano: falar com respeito, preservar limites A aula propõe um percurso de treino de fala autêntica em situações do dia a dia (pedir ajuda; recusar convite arriscado; combinar limites; pedir desculpas). Para mobilizar a atividade C.6.4, os estudantes serão convidados a usar eu‑mensagem, paráfrase e pedidos claros, discernindo o que compartilhar e quando, sempre com foco em respeito e segurança. Este encontro deverá ser dedicado à produção dos roteiros de fala e do checklist de limites que serão revisitados quando formos decidir cenários pessoais (A3–A4). Produto em construção: Roteiros + checklist (MI). (sem entrega formal) | J83: O futuro pode ser melhor se eu for autêntico em minhas relações? | K83: Autenticidade | L83: Revelar-se | M83: C.6.4 Analisar a importância da autenticidade na relação com os outros para construir um projeto de vida.
B84: Anos Finais | C84: 6º | D84: 4º | F84: 3 | G84: Tomada de decisão | H84: Testar possibilidades de decisão em diferentes cenários e com a participação de diferentes atores. | I84: Cenários & vozes: desenhando escolhas (v1) A aula propõe um percurso de análise de cenários próximos (escola, amigos, tempo livre) e de identificação de atores/vozes relevantes. Para mobilizar a atividade TD.6.4, os estudantes serão convidados a mapear opções, efeitos prováveis e pessoas a escutar, elaborando a Versão 1 do Mapa de Decisão. Este encontro deverá ser dedicado à produção dos rascunhos de mapas que serão base para a revisão dialogada na A4. Produto em construção: Mapa de Decisão v1 (MI) → revisão na A4. (sem entrega formal) | J84: Como posso analisar cenários e o papel das pessoas em minha vida para tomar decisões para o futuro? | K84: Ponderação | L84: Escutar | M84: TD.6.4 Testar decisões para o futuro com base em diferentes cenários, promovendo diálogos e construindo soluções coletivas.
B85: Anos Finais | C85: 6º | D85: 4º | F85: 4 | G85: Tomada de decisão | H85: Testar possibilidades de decisão em diferentes cenários e com a participação de diferentes atores. | I85: Revisando decisões com vozes diversas (v2) A aula propõe um percurso de devolutiva e revisão das escolhas após escuta ativa. Para mobilizar a atividade TD.6.4, os estudantes serão convidados a incorporar contribuições, ajustar critérios e apresentar a Versão 2 do Mapa de Decisão, explicitando o que mudou e por quê. Este encontro deverá ser dedicado à revisão e apresentação breve dos mapas com registro de mudanças. Produto em construção: Mapa de Decisão v2 (MI). (ENTREGA formal: Mapa de Decisão v2) | J85: Como posso analisar cenários e o papel das pessoas em minha vida para tomar decisões para o futuro? | K85: Ponderação | L85: Escutar | M85: TD.6.4 Testar decisões para o futuro com base em diferentes cenários, promovendo diálogos e construindo soluções coletivas.
B86: Anos Finais | C86: 6º | D86: 4º | F86: 5 | G86: Planejamento | H86: Estabelecer objetivos de curto prazo para organizar os estudos e conquistar metas pessoais na escola. | I86: Como saberei que estou evoluindo? A aula propõe um percurso de definição de indicadores simples de progresso e de montagem de um painel de monitoramento. Para mobilizar a atividade P.6.4, os estudantes serão convidados a escolher evidências observáveis (frequência, duração, qualidade) e a configurar um semáforo semanal de acompanhamento. Este encontro deverá ser dedicado à construção do Painel de monitoramento (semáforo + indicadores) e à marcação do primeiro checkpoint. Produto em construção: Painel de monitoramento (MI + mural). (ENTREGA formal: Painel/semáforo) | J86: Como eu sei se estou evoluindo academicamente? | K86: Responsabilidade | L86: Refletir | M86: P.6.4 Utilizar uma estratégia de monitoramento para verificar se as mudanças estão sendo efetivadas.
B87: Anos Finais | C87: 6º | D87: 4º | F87: 6 | G87: Planejamento & Engajamento | H87: - Estabelecer objetivos de curto prazo para organizar os estudos e conquistar metas pessoais na escola. - Manter a motivação necessária para realizar e concluir tarefas com autonomia e empenho pessoal. | I87: Mostra ‘Rotas 30–60–90’ + síntese do percurso A aula propõe um percurso de consolidação e socialização do projeto. Os estudantes integram indicadores (A5) e kit de persistência (A6) ao Mapa de Decisão (A4) e às práticas de autenticidade (A2), compondo o Roteiro 30–60–90. A turma realiza uma Mostra simples com os painéis e faz uma autoavaliação final do bimestre. Este encontro deverá ser dedicado à apresentação pública (mural simples) e à síntese escrita “o que aprendi/como sigo”. Produto em construção: Roteiro 30–60–90 consolidado (MI) + Mostra. (ENTREGA formal: Roteiro consolidado + autoavaliação) | J87: - Como eu sei se estou evoluindo academicamente? - Como me mantenho motivado ao longo do tempo? | K87: - Responsabilidade - Persistência | L87: - Refletir - Decidir | M87: P.6.4 Utilizar uma estratégia de monitoramento para verificar se as mudanças estão sendo efetivadas. E.6.4 Usar estratégias para se manter motivado para realizar suas tarefas com empenho
B88: Anos Finais | C88: 7º | D88: 4º | E88: Voz pública no território: Áudio-guia da Escola Quando a escola fala com a própria voz, o território escuta. Neste projeto, os estudantes convertem aprendizagens do ano em mensagens públicas curtas, claras e respeitosas, orientadas à ação. O caminho começa com projeções de interesses para a etapa seguinte, mapeia como os princípios da comunicação constroem futuros melhores, decide prioridades para o futuro próximo, aprende com planejamentos anteriores para ajustar o presente e avalia o próprio engajamento ao assumir papéis reais na produção e manutenção do Áudio-guia. O fio condutor é: escuta de quem seremos → pauta pública → decisão para agora → lições aprendidas → produção em serviço. Cada etapa retoma o que foi feito (entrevistas, pautas, matriz de decisão, rubrica de eficácia) e prepara a seguinte (canvas de produção, papéis, indicadores, testes com usuários), para que o lançamento seja também um plano de continuidade. A imagem poética é a de uma escola-farol: mensagens curtas que iluminam caminhos possíveis no cotidiano — convivência, segurança nas redes, cuidado com espaços e pessoas. Produto: Áudio-guia do Território — série de áudios de 30–60s (com QR/links, quando possível) instalados em pontos-chave da escola (entrada, biblioteca, pátio, quadra, corredores), com mensagens públicas que unem respeito, clareza e orientação prática (o que fazer agora). Inclui plano de monitoramento (quem repõe, quando mede, como ajusta). Roadmap do bimestre: A1 — Voz que quero levar ao mundo (AC.7.4): entrevistas/escutas e projeções de interesse para a próxima etapa. A2 — Comunicação que cria futuro (C.7.4): pautas públicas ligadas à convivência/segurança digital/uso de espaços. A3 — Priorizar para o futuro próximo (TD.7.4): matriz de decisão para selecionar mensagens prioritárias. A4 — Produção em pauta (E.7.4): papéis, cronograma, pontos de instalação e indicadores de eficácia. A5 — Pilotos e testes (C.7.4 + E.7.4): roteirizar, gravar, testar com usuários, iterar. (Entrega: protótipos + roteiro final) A6 — No ar! (C.7.4 / P.7.4 / E.7.4): instalação, lançamento e plano de monitoramento com responsáveis e checagens. (Entrega final) O Material Impresso (MI) acompanha todo o ciclo: entrevistas e sínteses (A1), pautas e atitudes/acordos (A2), matriz de decisão (A3), rubrica de eficácia (A4), canvas de produção/indicadores (A5), roteiros e checklists de teste (A6) e registro do plano de monitoramento (A7). | F88: 1 | G88: Autoconhecimento | H88: Escolher o que nos interessa é também escolher quem estamos nos tornando. | I88: Voz que quero levar ao mundo — entrevistas e projeções A aula propõe um percurso de investigação de futuros próximos: estudantes definem temas que importam para si e para o território e realizam entrevistas breves com estudantes do Ensino Médio, buscando pistas sobre interesses, escolhas e mensagens públicas que ajudam a comunidade. Para mobilizar AC.7.4, projetam quais interesses desejam manter/desenvolver na próxima etapa e como isso pode orientar mensagens do áudio‑guia. | J88: Eu me interesso por coisas que fazem a minha vida ser melhor? | K88: Intencionalidade | L88: Decidir | M88: AC.7.4 Projetar seus interesses para o futuro, com base na sua rede de apoio.
B89: Anos Finais | C89: 7º | D89: 4º | F89: 2 | G89: Convivência | H89: Utilizar os princípios da comunicação não violenta para expressar-se com respeito, empatia e assertividade. | I89: Princípios da comunicação que criam futuros melhores A aula propõe a sistematização das entrevistas realizadas e acrescenta o mapeamento de mensagens públicas necessárias no território escolar (convivência, segurança digital, uso dos espaços, cuidado com patrimônio). Será importante explicitar como os princípios da comunicação ajudam a construir futuros melhores para todos. Para mobilizar C.7.4, as equipes rascunham pautas do áudio‑guia e as conectam a atitudes e acordos concretos. | J89: A forma como eu falo com os outros me ajuda ou me atrapalha? | K89: Auto‑observação | L89: Refletir | M89: C.7.4 Analisar como os princípios da comunicação pode ajudar a construir futuros melhores para todos.
B90: Anos Finais | C90: 7º | D90: 4º | F90: 3 | G90: Tomada de decisão | H90: Tomar decisões baseadas na análise das causas e consequências das situações. | I90: Escolhas para o futuro próximo — priorizando mensagens do áudio‑guia A aula propõe avaliar causas/impactos das pautas levantadas (curto prazo, públicos, riscos/benefícios) e priorizar as mensagens do áudio‑guia. Para mobilizar TD.7.4, as equipes usam uma matriz de decisão para o futuro próximo, explicitando por que escolheram cada mensagem e qual impacto esperam. | J90: Que tipo de consequências uma decisão pode ter? | K90: Ponderação | L90: Decidir | M90: TD.7.4 Tomar decisões para o futuro próximo, analisando suas causas e consequências.
B91: Anos Finais | C91: 7º | D91: 4º | F91: 4 | G91: Engajamento | H91: Estar atento e comprometido com as necessidades e demandas da escola, da comunidade e das pessoas com quem convive. | I91: Produção em pauta — papéis, cronograma e indicadores A aula propõe organizar a produção do áudio‑guia: papéis (roteirista, locutor, técnico, revisão de linguagem), cronograma, pontos de instalação (QR) e indicadores de eficácia (escuta, compreensão, mudança de atitude). Para mobilizar E.7.4, os estudantes avaliam o próprio engajamento e pactuam responsabilidades. | J91: Como posso ajudar as pessoas da minha escola e família? | K91: Responsabilidade | L91: Cuidar | M91: E.7.4 Avaliar o próprio engajamento com as necessidades e demandas do seu entorno.
B92: Anos Finais | C92: 7º | D92: 4º | F92: 5 | G92: Convivência + Engajamento | H92: - Utilizar os princípios da comunicação não violenta para expressar-se com respeito, empatia e assertividade. - Estar atento e comprometido com as necessidades e demandas da escola, da comunidade e das pessoas com quem convive. | I92: Gravar, testar, melhorar — áudio‑guia em versão piloto A aula propõe roteirizar e gravar áudios de 30–60s (linguagem clara, respeitosa, orientada à ação), realizar testes rápidos de escuta com 3 usuários por ponto e iterar. Para mobilizar C.7.4 e E.7.4, as equipes revisam mensagens e ajustam pontos de instalação. | J92: - A forma como eu falo com os outros me ajuda ou me atrapalha? - Como posso ajudar as pessoas da minha escola e família? | K92: - Auto‑observação - Colaboração | L92: - Refletir - Cuidar | M92: C.7.4 Analisar como os princípios da comunicação pode ajudar a construir futuros melhores para todos. E.7.4 Avaliar o próprio engajamento com as necessidades e demandas do seu entorno.
B93: Anos Finais | C93: 7º | D93: 4º | F93: 6 | G93: Convivência Planejamento | H93: - Utilizar os princípios da comunicação não violenta para expressar-se com respeito, empatia e assertividade. - Definir objetivos de curto e médio prazo em diferentes áreas da vida, utilizando estratégias e ferramentas para alcançá-los. | I93: Áudio‑guia no ar — instalação, lançamento e plano de acompanhamento A aula propõe instalar QRs/plaquetas (ou divulgar links), apresentar o áudio‑guia à comunidade escolar e pactuar o monitoramento (quem repõe, quem mede, quando revisa). Para mobilizar C.7.4, P.7.4 e E.7.4, os estudantes conduzem o lançamento e registram próximos passos com base em indicadores. | J93: - A forma como eu falo com os outros me ajuda ou me atrapalha? - Como posso me organizar para realizar de fato meus objetivos? | K93: - Responsabilidade - Organização e perseverança | L93: - Decidir - Refletir - Cuidar | M93: C.7.4 Analisar como os princípios da comunicação pode ajudar a construir futuros melhores para todos. P.7.4 Avaliar a eficácia do planejamento realizado anteriormente.
B94: Anos Finais | C94: 8º | D94: 4º | E94: Jogo de Piso “Caminhos do Futuro” Encerrar o ano é ensaiar o próximo passo. Em vez de um roteiro silencioso, criamos um jogo vivo, jogável por outras turmas, que integra o que aprendemos ao longo do ciclo. Partimos do que será preciso cultivar para a transição: mapeamos lacunas e priorizamos habilidades necessárias para se tornarem quem desejam ser no Ensino Médio (AC.8.4 Analisar quais serão as habilidades necessárias para se tornarem quem desejam ser no Ensino Médio). Dessas escolhas nascem cartas-desafio do tabuleiro. Na segunda dobra, escrevemos microcenários de empatia “antes/depois”, imaginando como acordos sensíveis mudam trajetórias (C.8.4 Compreender como a empatia pode ajudar a construir futuros melhores para todos). A terceira dobra convoca decisões éticas de médio prazo (estudo, tempo, redes), convertidas em cartas-decisão (TD.8.4 Usar valores éticos como critérios para tomar decisões para o futuro). Na quarta, desenhamos casas-imprevisto com planos B/C — porque o jogo da vida inclui desvios (P.8.4 Analisar possibilidades de imprevistos e frustrações no futuro). Por fim, criamos casas-contribuição, registrando ações factíveis de bem comum (E.8.4 Compreender o que pode fazer para contribuir com melhorias na sociedade). Com as cartas prontas, prototipamos um tabuleiro no chão (fitas, folhas, giz), testamos regras simples (papéis, tempo, quando pedir ajuda a um adulto) e ajustamos jogabilidade, clareza e segurança. O fechamento é instalação e sessão pública: o jogo vira legado físico da turma para a escola — um convite para continuar decidindo com ética, planejando com resiliência e contribuindo com empatia. Fio condutor: Manter o arco cartas em versão (v1 → teste → final), garantindo que cada aula gera material para o jogo. O Material Impresso guarda esboços e checklists; o produto final é o jogo instalado e jogado. Produto: Jogo de Piso “Caminhos do Futuro” instalado + sessão pública de jogo (registro fotográfico/relato curto). Roadmap do bimestre A1 — Painel-alvo (AC.8.4): habilidades prioritárias → cartas-desafio (v1). A2 — Microcenários de empatia (C.8.4): cartas-empatia (v1). A3 — Decidir com ética (TD.8.4): cartas-decisão (v1). A4 — Imprevistos e B/C (P.8.4): cartas-imprevisto (v1). A5 — Contribuição social (E.8.4): cartas-contribuição (v1). A6 — Instalar e jogar: Jogo de Piso + pactos de uso. (entrega final) | F94: 1 | G94: Autoconhecimento | H94: Cultivar habilidades que conectem quem somos hoje com quem desejamos ser no futuro. | I94: Habilidades para o próximo ciclo — meu painel‑alvo (cartas do jogo) A aula propõe mapear lacunas e selecionar habilidades estratégicas para o próximo ciclo. Para mobilizar AC.8.4, os estudantes constroem o painel‑alvo (v1) e esboçam "cartas‑desafio" do jogo ligadas a essas habilidades. Para tanto, será indispensável que essa aula apresente o projeto do bimestre. | J94: Quais habilidades ajudarão a me tornar o estudante de Ensino Médio que desejo ser? | K94: Visão de futuro | L94: Decidir | M94: AC.8.4 Analisar quais serão as habilidades necessárias para se tornarem quem desejam ser no Ensino Médio.
B95: Anos Finais | C95: 8º | D95: 4º | F95: 2 | G95: Convivência | H95: Agir com empatia, sendo capaz de compreender as perspectivas e os sentimentos dos outros. | I95: Empatia que projeta — microcenários ‘antes/depois’ (cartas) A aula propõe estudar situações em que empatia gerou mudanças e criar "cartas‑empatia" com microcenários antes/depois. Para mobilizar C.8.4, a turma imagina como acordos empáticos moldam o cotidiano e o tabuleiro. | J95: O que aconteceria no mundo se as pessoas fossem mais empáticas? | K95: Compromisso com o bem comum | L95: Transformar | M95: C.8.4 Compreender como a empatia pode ajudar a construir futuros melhores para todos.
B96: Anos Finais | C96: 8º | D96: 4º | F96: 3 | G96: Tomada de decisão | H96: Usar valores éticos como critérios para a tomada de decisão. | I96: Decidir com ética — casas‑decisão do tabuleiro (v1) A aula propõe aplicar uma régua ética a decisões de médio prazo (estudo, tempo, redes) e escrever "cartas‑decisão" para o jogo. Para mobilizar TD.8.4, registram escolhas e justificativas curtas (v1). | J96: Como a ética pode estar presente nas decisões para o meu futuro? | K96: Coerência | L96: Refletir | M96: TD.8.4 Usar valores éticos como critérios para tomar decisões para o futuro.
B97: Anos Finais | C97: 8º | D97: 4º | F97: 4 | G97: Planejamento | H97: Elaborar planos alternativos para lidar com imprevistos e frustrações sem perder de vista seus objetivos. | I97: Planos B/C — casas‑imprevisto do tabuleiro (v1) A aula propõe identificar riscos e combinar respostas com pares, escrevendo "cartas‑imprevisto" com planos B/C. Para mobilizar P.8.4, produzem cartas com passo a passo enxuto. | J97: O que pode acontecer de imprevisível e me frustrar no futuro? | K97: Previdência | L97: Refletir | M97: P.8.4 Analisar possibilidades de imprevistos e frustrações no futuro.
B98: Anos Finais | C98: 8º | D98: 4º | F98: 5 | G98: Engajamento | H98: Compreender seu papel na sociedade e as formas pelas quais pode contribuir para sua melhoria. | I98: Minha contribuição social — casas‑contribuição (v1) A aula propõe escrever "cartas‑contribuição" com ações factíveis de bem comum. Para mobilizar E.8.4, registram propostas ligadas à escola/comunidade. | J98: O que posso fazer para tornar a sociedade melhor? | K98: Senso de responsabilidade social | L98: Transformar | M98: E.8.4 Compreender o que pode fazer para contribuir com melhorias na sociedade.
B99: Anos Finais | C99: 8º | D99: 4º | F99: 6 | G99: Engajamento | H99: - Agir com empatia, sendo capaz de compreender as perspectivas e os sentimentos dos outros. - Usar valores éticos como critérios para a tomada de decisão. - Elaborar planos alternativos para lidar com imprevistos e frustrações sem perder de vista seus objetivos. - Compreender seu papel na sociedade e as formas pelas quais pode contribuir para sua melhoria. | I99: Caminhos do Futuro — instalar e jogar! A aula propõe instalar o "Jogo de Piso ‘Caminhos do Futuro’" no pátio/corredor, apresentar regras simples e promover uma sessão de jogo com outra turma/convidados. Registra pactos e próximos usos. | J99: - O que aconteceria no mundo se as pessoas fossem mais empáticas? - Como a ética pode estar presente nas decisões para o meu futuro? - O que pode acontecer de imprevisível e me frustrar no futuro? - O que posso fazer para tornar a sociedade melhor? | K99: - Compromisso com o bem comum - Coerência - Previdência - Senso de responsabilidade social | L99: - Decidir - Transformar - Refletir | M99: AC.8.4 Analisar quais serão as habilidades necessárias para se tornarem quem desejam ser no Ensino Médio. C.8.4 Compreender como a empatia pode ajudar a construir futuros melhores para todos. TD.8.4 Usar valores éticos como critérios para tomar decisões para o futuro. E.8.4 Compreender o que pode fazer para contribuir com melhorias na sociedade.
B100: EFAF | C100: 9º | D100: 4º | E100: Quem quero ser no Ensino Médio: perfil, plano e território Fechar o ciclo é deixar um rastro que ajude quem vem — inclusive nós mesmos — a seguir em frente. O projeto final combina prevenção, consideração, identidade, execução e contribuição. Mapeamos fatores que podem fragilizar a vida no EM (AC.9.4) e projetamos como considerar o bem-estar dos outros em nossas decisões (C.9.4). Nomeamos o perfil de adolescente que desejamos ser (TD.9.4) e desenhamos ferramentas de execução (P.9.4). O engajamento ganha corpo em ação no território (E.9.4) e se amplia em melhorias nas quatro frentes: pessoal, familiar, escolar e comunitária (E.9.1/E.9.2/E.9.3/E.9.4). O resultado é público e pactuado. Fio do projeto: do risco e cuidado (prevenir) → para o impacto nas decisões (considerar) → para o manifesto de perfil (assumir) → para as rotinas e monitoramento (executar) → para o Projeto Legado (contribuir) → para as quatro frentes (ampliar) → para a Carta e a mostra final (pactuar). Produto: Projeto Legado da Turma (intervenção no território) + Carta de Perfil e Compromisso com o Território (apresentação pública). Roadmap: A1 mapa de riscos (AC.9.4, v1) A2 matriz decisão→impactos (C.9.4, v1) A3 manifesto de perfil (TD.9.4, v1) A4 plano de execução (P.9.4, v1) · A5 melhorias em quatro frentes (E.9.1/E.9.2/E.9.3/E.9.4) A6 Carta + mostra final (pactos). | F100: 1 | G100: Autoconhecimento | H100: Compreender as fragilidades como parte da identidade, buscando formas saudáveis de lidar com elas e caminhos possíveis de superação. | I100: Olhar preventivo para o EM — mapa de riscos e respostas (v1) A aula propõe mapear fatores de risco pessoais/contextuais e planejar respostas saudáveis. Para mobilizar AC.9.4, a turma produz mapas que alimentarão o ‘Projeto Legado’ e a Carta. | J100: O que pode me fragilizar em um futuro próximo? | K100: Consciência preventiva | L100: Observar-se | M100: AC.9.4 Analisar fatores que podem fragilizar a vida durante o Ensino Médio.
...

Sheet Redação e Leitura
A1: Ano/Série | B1: Bimestre | C1: Semana | D1: Título GPS Semanal | E1: Aula | F1: Prática de linguagem | G1: Proposta | H1: Gênero textual | I1: Eixo Temático | J1: Sugestão 1 | K1: Sugestão 2 | L1: Sugestão 3 | M1: Práticas pedagógicas | N1: Plataforma | O1: Objetivos de aprendizagem | P1: Objetos de conhecimento | Q1: Habilidade - Código | R1: Habilidade - Texto
A2: 6º | B2: 1º | C2: 1 | D2: Práticas de Leitura e Escrita do Bimestre | Elaboração do Projeto de Texto 1 | E2: 1 | F2: Leitura | G2: P1 | H2: Notícia | I2: Histórias que a Escola Conta | J2: Harry Potter e a Pedra Filosofal | K2: Diário de um Banana: Rodrick é o Cara | L2: O Menino Maluquinho | M2: - Apresentação do eixo temático e da obra selecionada para o bimestre - Predição guiada - Leitura - Seleção de trechos relevantes (grifos na plataforma de leitura) | N2: Leia SP | O2: - Relacionar o tema bimestral à obra literária selecionada para o bimestre. - Formular hipóteses sobre o enredo da obra literária utilizando a estratégia de predição guiada. | P2: - Reconstrução das condições de produção, circulação e recepção - Adesão às práticas de leitura | Q2: - EF69LP46 - EF69LP49 | R2: - Participar de práticas de compartilhamento de leitura/recepção de obras literárias/manifestações artísticas, tecendo, quando possível, comentários de ordem estética e afetiva. - Mostrar-se interessado e envolvido pela leitura de livros de literatura e por outras produções culturais do campo e receptivo a textos que rompam com seu universo de expectativas, que representem um desafio em relação às suas possibilidades atuais e suas experiências anteriores de leitura, apoiando-se nas marcas linguísticas, em seu conhecimento sobre os gêneros e a temática e nas orientações dadas pelo professor.
A3: 6º | B3: 1º | C3: 1 | D3: Práticas de Leitura e Escrita do Bimestre | Elaboração do Projeto de Texto 1 | E3: 2 | F3: Produção de textos | G3: P1 | H3: Notícia | I3: Histórias que a Escola Conta | J3: Harry Potter e a Pedra Filosofal | K3: Diário de um Banana: Rodrick é o Cara | L3: O Menino Maluquinho | M3: - Definir 5W1H com base nas anotações de leitura - Rascunhar pauta e possíveis manchetes - Listar trechos da obra escolhida que servirão como “fontes”/aspas | N3: Leia SP | O3: - Planejar notícia com título e informações essenciais (5W1H); - Relacionar elementos da leitura da obra ao planejamento da produção. | P3: Estratégias de produção: planejamento de textos informativos | Q3: EF67LP09 | R3: Planejar notícia impressa e para circulação em outras mídias (rádio ou TV/vídeo), tendo em vista as condições de produção, do texto – objetivo, leitores/espectadores, veículos e mídia de circulação etc. –, a partir da escolha do fato a ser noticiado, do levantamento de dados e informações sobre o fato.
A4: 6º | B4: 1º | C4: 2 | D4: Práticas de Leitura | Elaboração do rascunho | E4: 3 | F4: Leitura | G4: P1 | H4: Notícia | I4: Histórias que a Escola Conta | J4: Harry Potter e a Pedra Filosofal | K4: Diário de um Banana: Rodrick é o Cara | L4: O Menino Maluquinho | M4: - Leitura individual e compartilhada. - Marcação de quem, onde e quando no texto | N4: Leia SP | O4: - Diferenciar um fato de uma opinião sobre ele. - Reconhecer a forma composicional do gênero notícia, considerando o contexto de produção e o suporte. | P4: - Reconstrução do contexto de produção, circulação e recepção de textos - Caracterização do campo jornalístico e relação entre os gêneros em circulação, mídias e práticas da cultura digital | Q4: - EF06LP01 - EF06LP01B - EF06LP02 | R4: - Identificar diferentes graus de (im)parcialidade advindos de escolhas linguístico-discursiva feitas pelo autor. - Desenvolver atitude crítica frente aos textos jornalísticos. - Conhecer as características dos diferentes gêneros jornalísticos (escritos, orais e multimodiais) e a relação com a situação comunicativa, o estilo e a finalidade dos gêneros em uso.
A5: 6º | B5: 1º | C5: 2 | D5: Práticas de Leitura | Elaboração do rascunho | E5: 4 | F5: Produção de textos | G5: P1 | H5: Notícia | I5: Histórias que a Escola Conta | J5: Harry Potter e a Pedra Filosofal | K5: Diário de um Banana: Rodrick é o Cara | L5: O Menino Maluquinho | M5: - Escrita orientada do lide a partir do quem, onde e quando retirado da leitura - Redigir o rascunho da redação | N5: Leia SP | O5: - Levantar dados relevantes, considerando as condições de produção que envolvem a circulação de textos. - Planejar o texto, considerando a produção de roteiros e sínteses de informações. | P5: - Relação do texto com o contexto de produção e experimentação de papéis sociais - Construção composicional - Estilo | Q5: - EF69LP06 - EF69LP16B - EF69LP17 | R5: - Produzir notícias, fotodenúncias, fotorreportagens, reportagens, infográficos, podcasts noticiosos, entrevistas, cartas de leitor, comentários, artigos de opinião de interesse local ou global, textos de apresentação e apreciação de produção cultural (resenhas e outros gêneros textuais próprios das formas de expressão das culturas juvenis, em várias mídias). - Utilizar as formas de composição dos gêneros textuais do campo jornalístico. - Identificar recursos estilísticos e semióticos presentes em textos jornalísticos e publicitários.
A6: 6º | B6: 1º | C6: 3 | D6: Práticas de Leitura | Versão final do Texto 1 | E6: 5 | F6: Leitura | G6: P1 | H6: Notícia | I6: Histórias que a Escola Conta | J6: Harry Potter e a Pedra Filosofal | K6: Diário de um Banana: Rodrick é o Cara | L6: O Menino Maluquinho | M6: - Evocação de conhecimentos prévios - Leitura compartilhada - Leitura individual - Marcação de verbos que indicam tempo e ação | N6: Leia SP | O6: - Identificar verbos que indicam pretérito e presente na narrativa lida. - Compreender como os acontecimentos da história são organizados temporalmente. | P6: - Construção composicional - Reconstrução da textualidade e compreensão dos efeitos de sentidos provocados pelos usos de recursos linguísticos e multissemióticos | Q6: - EF69LP16A - EF69LP47 | R6: - Analisar as formas de composição dos gêneros textuais do campo jornalístico. - Analisar, em textos narrativos ficcionais, as diferentes formas de composição próprias de cada gênero, os recursos coesivos que constroem a passagem do tempo e articulam suas partes, a escolha lexical típica de cada gênero para a caracterização dos cenários e dos personagens e os efeitos de sentido decorrentes dos tempos verbais, dos tipos de discurso, dos verbos de enunciação e das variedades linguísticas empregados. expressões conotativas e processos figurativos e do uso de recursos linguísticogramaticais próprios a cada gênero narrativo.
A7: 6º | B7: 1º | C7: 3 | D7: Práticas de Leitura | Versão final do Texto 1 | E7: 6 | F7: Produção de textos | G7: P1 | H7: Notícia | I7: Histórias que a Escola Conta | J7: Harry Potter e a Pedra Filosofal | K7: Diário de um Banana: Rodrick é o Cara | L7: O Menino Maluquinho | M7: - Revisão da versão final do texto - Submissão da redação na plataforma | N7: Redação Paulista | O7: - Revisar o texto produzido, considerando os critérios de clareza, coesão e adequação ao gênero notícia. - Editar a versão final com base nas características do gênero e nas condições de produção. - Finalizar e publicar o texto na plataforma, respeitando os aspectos formais e editoriais da proposta. | P7: - Revisão/edição de texto informativo e opinativo - Textualização, tendo em vista suas condições de produção, as características do gênero em questão, o estabelecimento de coesão, adequação à norma-padrão e o uso adequado de ferramentas de edição | Q7: - EF69LP08 - EF67LP10A | R7: - Revisar/editar o texto produzido, tendo em vista sua adequação ao contexto de produção, a mídia em questão, características do gênero, aspectos relativos à textualidade, a relação entre as diferentes semioses, a formatação e uso adequado das ferramentas de edição (de texto, foto, áudio e vídeo, dependendo do caso) e adequação à norma culta. - Produzir notícia impressa e para TV, rádio e internet tendo em vista características do gênero, o estabelecimento adequado de coesão, os recursos de mídias disponíveis.
A8: 6º | B8: 1º | C8: 4 | D8: Fluência Leitora | Devolutiva do Texto 1 | E8: 7 | F8: Leitura | G8: P1 | H8: Notícia | I8: Histórias que a Escola Conta | J8: Harry Potter e a Pedra Filosofal | K8: Diário de um Banana: Rodrick é o Cara | L8: O Menino Maluquinho | M8: - Realização do Teste de Fluência Leitora - Leitura individual | N8: Leia SP | O8: - Ler em voz alta textos literários com fluência, entonação e ritmo adequados. - Participar de práticas de leitura que favoreçam o desenvolvimento da autonomia leitora. | P8: Oralização | Q8: EF69LP53 | R8: Ler em voz alta textos literários diversos, bem como leituras orais capituladas (compartilhadas ou não com o professor) de livros, contar/recontar histórias tanto da tradição oral, quanto da tradição literária escrita, expressando a compreensão e interpretação do texto por meio de uma leitura ou fala expressiva e fluente, gravando essa leitura ou esse conto/reconto, seja para análise posterior.
A9: 6º | B9: 1º | C9: 4 | D9: Fluência Leitora | Devolutiva do Texto 1 | E9: 8 | F9: Produção de textos | G9: P1 | H9: Notícia | I9: Histórias que a Escola Conta | J9: Harry Potter e a Pedra Filosofal | K9: Diário de um Banana: Rodrick é o Cara | L9: O Menino Maluquinho | M9: - Análise da devolutiva da correção - Construção de quadro "O que está bom; O que preciso melhorar; O que vou fazer para melhorar." | N9: Redação Paulista | O9: - Compreender os critérios utilizados na correção da produção textual. - Refletir sobre os aspectos positivos e os pontos de melhoria do texto produzido. - Elaborar estratégias para aprimorar a escrita em futuras produções. | P9: Revisão/edição de texto informativo e opinativo | Q9: EF69LP08 | R9: Revisar/editar o texto produzido, tendo em vista sua adequação ao contexto de produção, a mídia em questão, características do gênero, aspectos relativos à textualidade, a relação entre as diferentes semioses, a formatação e uso adequado das ferramentas de edição (de texto, foto, áudio e vídeo, dependendo do caso) e adequação à norma culta.
A10: 6º | B10: 1º | C10: 5 | D10: Práticas de Leitura | Elaboração do Projeto de Texto 2 | E10: 9 | F10: Leitura | G10: P2 | H10: Conto | I10: Histórias que a Escola Conta | J10: Harry Potter e a Pedra Filosofal | K10: Diário de um Banana: Rodrick é o Cara | L10: O Menino Maluquinho | M10: - Resumo e discussão da leitura até agora - Leitura individual - Leitura compartilhada | N10: Leia SP | O10: - Retomar e sintetizar a leitura do bimestre, reconstruindo a sequência de acontecimentos e identificando informações essenciais para a compreensão global da narrativa. - Identificar e registrar recursos narrativos que intensificam os efeitos de sentido na leitura.. | P10: - Reconstrução das condições de produção, circulação e recepção - Adesão às práticas de leitura | Q10: - EF69LP46 - EF69LP49 | R10: - Participar de práticas de compartilhamento de leitura/recepção de obras literárias/manifestações artísticas, tecendo, quando possível, comentários de ordem estética e afetiva. - Mostrar-se interessado e envolvido pela leitura de livros de literatura e por outras produções culturais do campo e receptivo a textos que rompam com seu universo de expectativas, que representem um desafio em relação às suas possibilidades atuais e suas experiências anteriores de leitura, apoiando-se nas marcas linguísticas, em seu conhecimento sobre os gêneros e a temática e nas orientações dadas pelo professor.
A11: 6º | B11: 1º | C11: 5 | D11: Práticas de Leitura | Elaboração do Projeto de Texto 2 | E11: 10 | F11: Produção de textos | G11: P2 | H11: Conto | I11: Histórias que a Escola Conta | J11: Harry Potter e a Pedra Filosofal | K11: Diário de um Banana: Rodrick é o Cara | L11: O Menino Maluquinho | M11: Ficha de planejamento de personagem: nome, idade, um traço forte, objetivo e motivação | N11: N/A | O11: - Planejar narrativa considerando os elementos estruturais do gênero conto. - Organizar ideias para construção de personagem, conflito e desfecho. | P11: - Consideração das condições de produção - Estratégias de produção: planejamento, textualização e revisão/edição - Construção da textualidade | Q11: - EF69LP51 - EF67LP30 | R11: - Engajar-se ativamente nos processos de planejamento, textualização, revisão/ edição e reescrita, tendo em vista as restrições temáticas, composicionais e estilísticas dos textos pretendidos e as configurações da situação de produção – o leitor pretendido, o suporte, o contexto de circulação do texto, as finalidades etc. – e considerando a imaginação, a estesia e a verossimilhança próprias ao texto literário. - Criar narrativas ficcionais, tais como contos populares, contos de suspense, mistério, terror, humor, narrativas de enigma, crônicas, histórias em quadrinhos, dentre outros, que utilizem cenários e personagens realistas ou de fantasia, observando os elementos da estrutura narrativa próprios ao gênero pretendido, tais como enredo, personagens, tempo, espaço e narrador, utilizando tempos verbais adequados à narração de fatos passados, empregando conhecimentos sobre diferentes modos de se iniciar uma história e de inserir os discursos direto e indireto.
A12: 6º | B12: 1º | C12: 6 | D12: Fluência Leitora | Elaboração do rascunho | E12: 11 | F12: Leitura | G12: P2 | H12: Conto | I12: Histórias que a Escola Conta | J12: Harry Potter e a Pedra Filosofal | K12: Diário de um Banana: Rodrick é o Cara | L12: O Menino Maluquinho | M12: - Ações pedagógicas com o resultado do teste de Fluência Leitora - Leitura compartilhada - Leitura individual | N12: Leia SP | O12: Utilizar estratégias de leitura para aprofundar a compreensão da obra. | P12: - Reconstrução das condições de produção, circulação e recepção - Apreciação e réplica - Estratégias de leitura | Q12: - EF69LP46 - EF67LP28 | R12: - Participar de práticas de compartilhamento de leitura/recepção de obras literárias/manifestações artísticas, tecendo, quando possível, comentários de ordem estética e afetiva. - Ler e compreender – selecionando procedimentos e estratégias de leitura adequados a diferentes objetivos e levando em conta características dos gêneros e suportes –, romances infantojuvenis, contos populares, contos de terror, lendas brasileiras, indígenas e africanas, poemas, entre outros, expressando avaliação sobre o texto lido e estabelecendo preferências por gêneros, temas, autores.
A13: 6º | B13: 1º | C13: 6 | D13: Fluência Leitora | Elaboração do rascunho | E13: 12 | F13: Produção de textos | G13: P2 | H13: Conto | I13: Histórias que a Escola Conta | J13: Harry Potter e a Pedra Filosofal | K13: Diário de um Banana: Rodrick é o Cara | L13: O Menino Maluquinho | M13: - Esqueleto do enredo em 5 passos: situação inicial/gancho, complicação, percurso, clímax, desfecho - Redigir o rascunho de forma manuscrita a partir do esqueleto do enredo | N13: N/A | O13: - Produzir o rascunho de um conto com coerência narrativa e progressão textual. - Aplicar os elementos estruturais do gênero conto na construção do texto. - Manter o ponto de vista do protagonista ao longo da narrativa. | P13: - Consideração das condições de produção - Estratégias de produção: planejamento, textualização e revisão/edição - Construção da textualidade | Q13: - EF69LP51 - EF67LP30 | R13: - Engajar-se ativamente nos processos de planejamento, textualização, revisão/ edição e reescrita, tendo em vista as restrições temáticas, composicionais e estilísticas dos textos pretendidos e as configurações da situação de produção – o leitor pretendido, o suporte, o contexto de circulação do texto, as finalidades etc. – e considerando a imaginação, a estesia e a verossimilhança próprias ao texto literário. - Criar narrativas ficcionais, tais como contos populares, contos de suspense, mistério, terror, humor, narrativas de enigma, crônicas, histórias em quadrinhos, dentre outros, que utilizem cenários e personagens realistas ou de fantasia, observando os elementos da estrutura narrativa próprios ao gênero pretendido, tais como enredo, personagens, tempo, espaço e narrador, utilizando tempos verbais adequados à narração de fatos passados, empregando conhecimentos sobre diferentes modos de se iniciar uma história e de inserir os discursos direto e indireto.
... A257: 9º | B257: 4º | C257: 8 | D257: Práticas de Leitura | Devolutiva do Texto 2 | E257: 16 | F257: Leitura | G257: P8 | H257: Dissertação Argumentativa ENEM | I257: Conexões e Aprendizados | J257: A Culpa é das Estrelas | K257: Os Meninos da Rua Paulo | L257: Fazendo meu filme | M257: Discussão em sala sobre o componente durante o ano: livro mais querido, o que mais marcou, o que menos marcou, como os estudantes percebem a evolução textual deles | N257: N/A | O257: - Refletir sobre o percurso de leitura e escrita ao longo do ano. - Reconhecer avanços individuais na produção textual. - Compartilhar percepções sobre as obras lidas, os gêneros trabalhados e os textos produzidos. | P257: - Reconstrução das condições de produção, circulação e recepção - Apreciação e réplica | Q257: - EF69LP44 - EF69LP46 | R257: - Inferir a presença de valores sociais, culturais e humanos e de diferentes visões de mundo, em textos literários, reconhecendo nesses textos formas de estabelecer múltiplos olhares sobre as identidades, sociedades e culturas e considerando a autoria e o contexto social e histórico de sua produção. - Participar de práticas de compartilhamento de leitura/recepção de obras literárias/manifestações artísticas, tecendo, quando possível, comentários de ordem estética e afetiva.

Sheet Robótica - PEI 9h
A1: CICLO | B1: ANO | C1: BIMESTRE | D1: Semana | E1: AULAS | F1: HABILIDADES BNCC - COMPUTAÇÃO | G1: HABILIDADE BNCC | H1: OBJETO DE CONHECIMENTO | I1: TÍTULO DA AULA | J1: CONTEÚDO | K1: OBJETIVOS
A2: Anos Finais | B2: 6º | C2: 1º | D2: 1 | E2: 1 e 2 | F2: - EF05CO05 | G2: - Identificar os componentes principais de um computador (dispositivos de entrada/saída, processadores e armazenamento). | H2: - Definição de robótica. - Componentes do computador. | I2: Computadores e robôs: uma introdução | J2: - Périfericos / entradas e saídas. | K2: - Reconhecer os principais perifericos de um computador. - Relacionar com entradas e saídas.
A3: Anos Finais | B3: 6º | C3: 1º | D3: 2 | E3: 3 e 4 | F3: - EF05CO011 | G3: - Identificar a adequação de diferentes tecnologias computacionais na resolução de problemas. | H3: - Conceitos de robótica na cultura e no cotidiano. | I3: Entendendo a robótica | J3: - Conceitos de robótica. - Robôs e suas aplicações. - História da robótica. | K3: - Compreender o conceito de robótica, por meio de suas diferentes representações em produções audiovisuais e usos na sociedade contemporânea. - Reconhecer o impacto e a relevância da robótica no cotidiano.
A4: Anos Finais | B4: 6º | C4: 1º | D4: 3 | E4: 5 e 6 | F4: - EF06CO02 | G4: - Elaborar algoritmos que envolvam instruções sequenciais, de repetição e de seleção, usando uma linguagem de programação. | H4: - Algoritmos e programação em blocos. | I4: Aprendendo a linguagem dos robôs | J4: - Linguagem de programação em blocos na robótica. - Linguagem natural x linguagem formal. - Algoritmo e instruções. | K4: - Compreender que existem diferentes formas de se construir algoritmos. - Reconhecer a programação em blocos como uma forma acessível de se comunicar com os robôs.
A5: Anos Finais | B5: 6º | C5: 1º | D5: 4 | E5: 7 e 8 | F5: - EF06CO02 | G5: - Elaborar algoritmos que envolvam instruções sequenciais, de repetição e de seleção, usando uma linguagem de programação. | H5: - Micro:bit: estrutura da plataforma MakeCode. | I5: Mistérios do micro:bit | J5: -Ambiente de programação do MakeCode. - Menu de ferramentas do MakeCode. - estrutura dos blocos. | K5: - Explorar o ambiente de programação MakeCode do micro:bit. - Identificar as principais ferramentas e funcionalidades de programação.
A6: Anos Finais | B6: 6º | C6: 1º | D6: 5 | E6: 9 e 10 | F6: - EF06CO05 | G6: - Identificar os recursos ou insumos necessários (entradas) para a resolução de problemas, bem como os resultados esperados (saídas), determinar os respectivos tipos de dados, e estabelecer a definição de problema como uma relação entre entrada e saída. | H6: - Plataforma MakeCode: Blocos básicos. - Códigos de programação. | I6: Emoções com o micro:bit: botões | J6: - Comunicação digital com o uso de emojis. - blocos de entrada- botões. - blocos básicos- icones. | K6: - Identificar os blocos de botões e blocos basicos da plataforma Makecode. - Explorar a comunicação no ambiente digital.
A7: Anos Finais | B7: 6º | C7: 1º | D7: 6 | E7: 11 e 12 | F7: - EF06CO05 | G7: - Identificar os recursos ou insumos necessários (entradas) para a resolução de problemas, bem como os resultados esperados (saídas), determinar os respectivos tipos de dados, e estabelecer a definição de problema como uma relação entre entrada e saída. | H7: - Inteligência emocional: ícones que representam as emoções utilizando o recurso acelerõmetro do micro:bit. | I7: Emoções com o micro:bit: acelerômetro | J7: - Representação de emoções no robô. - Sensor acelerômetro no micro:bit. - Bloco agitar no menu de entrada. | K7: - Identificar o sensor acelerômetro na placa micro:bit e suas funcionalidades. - Construir um programa utilizando o sensor acelerômetro.
A8: Anos Finais | B8: 6º | C8: 1º | D8: 7 | E8: 13 e 14 | F8: - EF06CO02 | G8: - Elaborar algoritmos que envolvam instruções sequenciais, de repetição e de seleção, usando uma linguagem de programação. | H8: - Protótipo de robô desplugado com o tema saúde. | I8: Meu amigo robô | J8: - Apresentação do problema. - Desenvolvimento da proposta. - Construção de um protótipo de robô desplugado com tema saúde. | K8: - Construir um robô com materiais não estruturados, utilizando uma proposta de tema transversal.
A9: Anos Finais | B9: 6º | C9: 2º | D9: 1 | E9: 1 e 2 | F9: - EF06CO02 | G9: - Elaborar algoritmos que envolvam instruções sequenciais, de repetição e de seleção, usando uma linguagem de programação. | H9: - Os pilares do pensamento computacional: a sua aplicabilidade no contexto da sociedade. | I9: Pensamento computacional | J9: - Pilares do pensamento computacional. - Decomposição. - Reconhecimento de padrões. - Abstração. - Algoritmos. | K9: - Identificar os pilares do pensamento computacional no contexto da robótica e na relação com problemas do cotidiano.
A10: Anos Finais | B10: 6º | C10: 2º | D10: 2 | E10: 3 e 4 | F10: - EF06CO04 | G10: - Construir soluções de problemas, usando a técnica de decomposição, e automatizar tais soluções usando uma linguagem de programação. | H10: - Fauna brasileira: animações utilizando blocos básicos do menu de ferramentas da plataforma MakeCode. | I10: [Competição de Robótica] Animais animados - Programando a matriz de LEDs | J10: - Fauna brasileira. - Blocos básico (Pausa). - Programação: animações no painel de LEDS do micro:bit. - Competição de Robótica | K10: - Explorar o menu de blocos básico do MakeCode na criação de animações na matriz de LEDs utilizando como tema a fauna brasileira.
A11: Anos Finais | B11: 6º | C11: 2º | D11: 3 | E11: 5 e 6 | F11: - EF06CO04 | G11: - Construir soluções de problemas, usando a técnica de decomposição, e automatizar tais soluções usando uma linguagem de programação. | H11: - Engrenagens: construção de um protótipo utilizando engrenagens que simule um cenário em movimento dos animais em extinção da fauna brasileira. - Competição de projetos | I11: [Competição de Robótica] Animais animados - Conhecendo o projeto | J11: - O que são engrenagens. - Os diferentes tipos de engrenagem e sua aplicação na sociedade. - Atividade sobre o tema. - Apresentação do protótipo "animais em movimento". - Competição de projetos | K11: - Explorar o que são engrenagens e sua aplicabilidade na sociedade. - Conhecer o projeto "animais em movimento" e como ele deve funcionar na prática. - Conhecer a proposta de competição e as etapas de desenvolvimento do projeto
A12: Anos Finais | B12: 6º | C12: 2º | D12: 4 | E12: 7 e 8 | F12: - EF06CO05 | G12: - Identificar os recursos ou insumos necessários (entradas) para a resolução de problemas, bem como os resultados esperados (saídas), determinar os respectivos tipos de dados, e estabelecer a definição de problema como uma relação entre entrada e saída. | H12: - Engrenagens: construção de um protótipo utilizando engrenagens que simule um cenário em movimento dos animais em extinção da fauna brasileira. | I12: [Competição de Robótica] Animais animados - Montando as engrenagens | J12: - Construção do protótipo. - Posicionamento das engrenagens: o encaixe das engrenagens para proporcionar o movimento da plataforma. | K12: - Entender o que são engrenagens e qual a sua função no mundo das máquinas e para a sociedade. - Iniciar a construção do protótipo utilizando engrenagens com o tema "animais em extinção".
A13: Anos Finais | B13: 6º | C13: 2º | D13: 5 | E13: 9 e 10 | F13: - EF06CO05 | G13: - Identificar os recursos ou insumos necessários (entradas) para a resolução de problemas, bem como os resultados esperados (saídas), determinar os respectivos tipos de dados, e estabelecer a definição de problema como uma relação entre entrada e saída. | H13: - Protótipo: construção do cenário com o tema animais em extinção da fauna brasileira. - Instalando a placa micro:bit com o programa aniamis animados. | I13: [Competição de Robótica] Animais animados - Incorporando a placa ao protótipo | J13: - Código de programação. - Finalizar a construção do protótipo com a montagem das engrenagens e o cenário com os animais. | K13: - Construir e finalizar cenario do protótipo animais em movimento. - Aplicar o programa na placa micro:bit. em seguida agregar a placa ao protótipo.
... A64: Anos Finais | B64: 6º | C64: 3º | D64: 7 | E64: 13 e 14 | F64: EF06CO02 | G64: Elaborar algoritmos que envolvam instruções sequenciais, de repetição e de seleção usando uma linguagem de programação. | H64: Desenvolvimento de um programa de jogo, aplicando os conhecimentos de variáveis e condicionais | I64: Micropet - Animais de estimação | J64: Programação do jogo micropet Blocos de variáveis. Blocos de condicionais | K64: Aplicar os conhecimentos de variáveis e condicionais na construção do programa micropet.
A65: Anos Finais | B65: 6º | C65: 4º | D65: 1 | E65: 1 e 2 | H65: A comunicação via rádio, O recurso de rádio no micro:bit. | I65: Teleporte pato 1 | J65: O rádio como veículo de comunicação. Como funciona a transmissão via rádio Conhecendo o sensor de rádio no micro:bit. | K65: Conhecer como a transmissão de informação ocorre via rádio Explorar a função rádio no micro:bit
A66: Anos Finais | B66: 6º | C66: 4º | D66: 2 | E66: 3 e 4 | H66: Rádio: programação utilizando blocos de rádio e variáveis | I66: Teleporte pato 2 | J66: Protótipo de comunicador. Programação utilizando o recurso rádio do micro:bit | K66: Construir a programação do teleporte pato e testar o seu funcionamento no micro:bit
A67: Anos Finais | B67: 6º | C67: 4º | D67: 3 | E67: 5 e 6 | H67: Computação desplugada: output e input, perifericos do computador, números binários e codificação. | I67: Desvendando o código | J67: . Periféricos . Output e input . Diferença entre dados e informação . Números binários e codificação. | K67: Entender os números binários como parte da linguagem computacional utilizada nas máquinas.
A68: Anos Finais | B68: 6º | C68: 4º | D68: 4 | E68: 7 e 8 | H68: Computação desplugada: linguagem de máquina, pixel | I68: Pixel | J68: . Desenhos e pixels . Linguagem de computador | K68: Identificar como os computadores constroem imagens utilizando números
A69: Anos Finais | B69: 6º | C69: 4º | D69: 5 | E69: 9 e 10 | H69: Circuito elétrico: circuitos abertos e fechados, condutores, os pinos de entrada e saída n micro:bit | I69: Vamos ligar os pinos. | J69: Conceito de tensão e corrente elétrica. O que são condutores e onde são utilizados. Circuitos abertos e fechados. | K69: Entender os conceitos de tensão, corrente elétrica e noções básicas de circuitos elétricos .
A70: Anos Finais | B70: 6º | C70: 4º | D70: 6 | E70: 11 e 12 | H70: Circuito elétrico: programação, teste de conectividade utilizando o micro:bit | I70: Vamos ligar os pinos II | J70: Circuito elétrico Cabos de conectividade. Programação | K70: Identificar os pinos do micro:bit. e sua aplicação para a robótica. Aplicar os conceitos de condutividade na prática utilizando a placa micro:bit.
A71: Anos Finais | B71: 6º | C71: 4º | D71: 7 | E71: 13 e 14 | H71: Condutividade de materiais: teste de condutividade com materiais condutores e não condutores utilizando a placa micro:bit e cabos. | I71: Teste de condutividade | J71: Teste de condutividade com materiais condutores e não condutores utilizando o micro:bit | K71: Identificar bons e maus condutores de eletricidade por meio de teste de conectividade.
A72: Anos Finais | B72: 7º | C72: 3º | D72: 1 | E72: 1 e 2 | F72: EF07CO03 | G72: - Construir soluções computacionais de problemas de diferentes áreas do conhecimento, de forma individual e colaborativa, selecionando as estruturas de dados e técnicas adequadas, aperfeiçoando e articulando saberes escolares. | H72: Micro:bit: coordenadas cartesiano, coodenadas na matriz de LEDs . | I72: Coordenadas - Parte 1 | J72: Coordenadas cartesianas As coordenadas na matriz de LEDs | K72: Reconhecer as coordenadas cartesiano e sua aplicação na matriz de LEDS .
A73: Anos Finais | B73: 7º | C73: 3º | D73: 2 | E73: 3 e 4 | F73: EF07CO03 | G73: - Construir soluções computacionais de problemas de diferentes áreas do conhecimento, de forma individual e colaborativa, selecionando as estruturas de dados e técnicas adequadas, aperfeiçoando e articulando saberes escolares. | H73: Micro:bit: função - LEDs do menu de ferramentas MakeCode. Programação. | I73: Coordenadas - Parte 2 | J73: Programação utilizando a função LED do menu de ferramentas do MakeCode. | K73: Identificar a função LED no menu de ferramentas do MakeCode e como aplicá-lo na programação para controlar o funcionamento dos LEDS na matriz.
A74: Anos Finais | B74: 7º | C74: 3º | D74: 3 | E74: 5 e 6 | F74: EF15CO01 | G74: Identificar as principais formas de organizar e representar a informação de maneira estruturada (matrizes, registros, listas e grafos) ou não estruturada (números, palavras, valores verdade). | H74: Micro:bit: função matriz do menu de ferramentas do Makecode. | I74: Jogo de palavras | J74: Bloco matriz no micro:bit – jogo de palavras | K74: Identificar o bloco matriz no menu de ferramentas do MakeCode e explorar a sua aplicação na programação.
A75: Anos Finais | B75: 7º | C75: 3º | D75: 4 | E75: 7 e 8 | F75: EF07CO03 | G75: - Construir soluções computacionais de problemas de diferentes áreas do conhecimento, de forma individual e colaborativa, selecionando as estruturas de dados e técnicas adequadas, aperfeiçoando e articulando saberes escolares. | H75: Plataforma MakeCode: Extensões, extensão robotbit. | I75: Conhecendo as extensões do Makecode | J75: Conhecendo extensões do Makecode. Instalando a extensão robotbit para projetos executaveis utilizando a shield. | K75: Identificar o item extensões no menu de ferramentas do MakeCode. Explorar os tipos de extensão que podem ser utilizados na construção de um projeto.
A76: Anos Finais | B76: 7º | C76: 3º | D76: 5 | E76: 9 e 10 | F76: EF05CO11 | G76: - Identificar a adequação de diferentes tecnologias computacionais na resolução de problemas. | H76: Micro:bit: Placa de extensão Shield. | I76: Conhecendo a shield | J76: Placa de extensão shield para o micro:bit: Conhecendo os Pinos de conexão, Leds, conectores, bateria, interruptor. | K76: Entender os recursos e aplicabilidades da Shield como extensão do micro;bit no desenvolvimento de projetos
A77: Anos Finais | B77: 7º | C77: 3º | D77: 6 | E77: 11 e 12 | F77: EF69CO05 | G77: Identificar os recursos ou insumos necessários (entradas) para a resolução de problemas, bem como os resultados esperados (saídas), determinando os respectivos tipos de dados, e estabelecendo a definição de problema como uma relação entre entrada e saída. | H77: Micro:bit: Placa de extensão Shield. | I77: Controlando os LEDs. | J77: -LEDs da shield. - Programação | K77: Construir um programa para controlar o funcionamento dos LEDs na shield
A78: Anos Finais | B78: 7º | C78: 3º | D78: 7 | E78: 13 e 14 | F78: EF69CO04 | G78: Construir soluções de problemas usando a técnica de decomposição e automatizar tais soluções usando uma linguagem de programação. | H78: Eletromecânica e programação | I78: Comemorando o gol | J78: Protótipo - circuito elétrico, utilizando a schield | K78: Reconhecer o conceito de circuito elétrico aberto e fechado. Para isso, será construido um protótipo simulando um placar de gol utilizando, a placa micro:bit e a extensão shield.
A79: Anos Finais | B79: 7º | C79: 4º | D79: 1 | E79: 1 e 2 | H79: Eletromecânica e programação | I79: Ligando os motores. | J79: Conhecendo os motores DC do kit de robótica: O funcionamento e como podemos utilizá-los em projetos de robótica. Aprendendo a ligar os motores na Shield. Construção de um programa simples para o funcionamento dos motores. | K79: Identificar os motores DC do Kit de robótica e como realizar a ligação na Shield. Construir a programação para o seu funcionamento.
A80: Anos Finais | B80: 7º | C80: 4º | D80: 2 | E80: 3 e 4 | H80: Eletromecânica e programação | I80: Servo motor | K80: Entender o que é um servo motor, funcionalidade e aplicação na robótica.
A81: Anos Finais | B81: 7º | C81: 4º | D81: 3 | E81: 5 e 6 | H81: Eletromecânica e programação | I81: Trabalhando ângulos com servo motor | J81: Relembrando ângulos Utilizando os ângulos no controle do servo motor | K81: Aplicar o conceito de ângulos no funcionamento do servo motor utilizando a programação .
A82: Anos Finais | B82: 7º | C82: 4º | D82: 4 | E82: 7 e 8 | H82: Eletromecânica e programação | I82: Conhecendo o potenciômetro | J82: Potenciômetro – Conceito. | K82: Identificar o potenciômetro como dispositivo de regulagem manual que pode ser usado no ajuste de volume, movimento e no controle de iluminação
A83: Anos Finais | B83: 7º | C83: 4º | D83: 5 | E83: 9 e 10 | H83: Eletromecânica e programação | I83: Controlando o servo motor com o potenciõmetro | J83: Potenciômetro – trabalhando com o servo motor | K83: Explorar o funcionamento do potenciômetro no controle de movimento do servo motor
A84: Anos Finais | B84: 7º | C84: 4º | D84: 6 | E84: 11 e 12 | H84: Eletromecânica e programação | I84: Girassol – Parte 1 | J84: Relembrando o sensor de luminosidade. Programação utilizando sensor e servo motor. | K84: Explorar o uso do servo motor e do sensor de luminosidade na construção de um protótipo que simule por meio da programação o movimento do girassol
A85: Anos Finais | B85: 7º | C85: 4º | D85: 7 | E85: 13 e 14 | H85: Eletromecânica e programação | I85: Girassol – Parte 2 | J85: Protótipo: Construindo um protótipo representando o girassol controlado pelo sensor de luminosidade utilizando servo motor | K85: Retomando a construção do protótipo que simule por meio da programação o movimento do girassol
A86: Anos Finais | B86: 8º | C86: 3º | D86: 1 | E86: 1 e 2 | F86: EF69CO06 | G86: Comparar diferentes casos particulares (instâncias) de um mesmo problema, identificando as semelhanças e diferenças entre eles, e criar um algoritmo para resolver todos, fazendo uso de variáveis (parâmetros) para permitir o tratamento de todos os casos de forma genérica. | H86: Atuadores: servo-motor e aplicações biomiméticas em robótica | I86: Servo no grau! - Explorando o servo-motor e sensor ultrassônico para criar movimentos precisos e automáticos. | J86: Funcionamento do servo-motor Controle e testes com shield Aplicações robóticas do servo Biomimética e robótica Soluções inspiradas em seres vivos | K86: Compreender o funcionamento e o controle do servo-motor, integrando-o à shield em testes práticos. Identificar aplicações do servo-motor em projetos robóticos e refletir sobre sua inspiração na movimentação de seres vivos. Propor soluções criativas com base na biomimética para sistemas robóticos eficientes.
A87: Anos Finais | B87: 8º | C87: 3º | D87: 2 | E87: 3 e 4 | F87: EF69CO05 | G87: Identificar os recursos ou insumos necessários (entradas) para a resolução de problemas, bem como os resultados esperados (saídas), determinando os respectivos tipos de dados, e estabelecendo a definição de problema como uma relação entre entrada e saída. | H87: Sensores ambientais: uso, leitura de dados e interpretação | I87: Vish! Molhou?! - Monitorando o ambiente com sensores que detectam água! | J87: Sensor de umidade: usos e funcionamento Coleta e análise de dados Avaliação de eficácia em diferentes contextos | K87: Explorar usos do sensor de umidade em diferentes contextos ambientais e tecnológicos. Coletar e analisar dados obtidos com o sensor, interpretando sua eficácia em diversas condições.
A88: Anos Finais | B88: 8º | C88: 3º | D88: 3 | E88: 5 e 6 | F88: EF69CO08 | G88: Compreender e utilizar diferentes formas de armazenar, manipular, compactar e recuperar arquivos, documentos e metadados. | H88: Comunicação entre dispositivos e representação visual de dados em interfaces gráficas | I88: Na Tela, Sem Mistério | J88: Comunicação I2C: conceito e aplicação com o display Integração de sensores para exibir dados em tempo real | K88: Compreender como funciona a comunicação I2C e conectar corretamente o display Programar a exibição de textos e dados de sensores no display usando o MakeCode.
A89: Anos Finais | B89: 8º | C89: 3º | D89: 4 | E89: 7 e 8 | F89: EF69CO04 | G89: Construir soluções de problemas usando a técnica de decomposição e automatizar tais soluções usando uma linguagem de programação. | H89: Tecnologia e automação aplicadas à agricultura sustentável | I89: IrrigaBot - Parte I - Do Arado ao Algoritimo | J89: Automação no campo Programação para agricultura inteligente Tecnologia e sustentabilidade Gestão de recursos naturais | K89: Compreender como a tecnologia e a automação otimizam processos agrícolas Introduzir conceitos de programação aplicados à automação. Refletir criticamente sobre o uso da tecnologia na gestão de recursos naturais e no cultivo sustentável.
A90: Anos Finais | B90: 8º | C90: 3º | D90: 5 | E90: 9 e 10 | F90: EF69CO02 | G90: Elaborar algoritmos que envolvam instruções sequenciais, de repetição e de seleção usando uma linguagem de programação. | H90: Automação com servo-motor para irrigação sustentável | I90: IrrigaBot - Parte II - Integrando o atuador ao protótipo | J90: Aplicações do servo na irrigação Programação de atuadores Sustentabilidade hídrica Construção de sistemas automatizados | K90: Entender o funcionamento e as aplicações do servo-motor na automação. Programar o servo-motor para construir um irrigador automático funcional. Refletir sobre o uso consciente da água e a importância da irrigação sustentável.
A91: Anos Finais | B91: 8º | C91: 3º | D91: 6 | E91: 11 e 12 | F91: EF69CO03 | G91: Descrever com precisão a solução de um problema, construindo o programa que implementa a solução descrita. | H91: Interação sensor–atuador: coleta, resposta e análise de dados | I91: IrrigaBot - Parte III - Integrando os sensores ao protótipo | J91: Revisão do sensor de umidade Programação reativa com micro:bit Interpretação de dados e gráficos Ajustes de sistemas automatizados | K91: Retomar conceitos do sensor de umidade e aplicá-los em um projeto prático de robótica. Programar o micro:bit para responder aos dados do sensor com ações automatizadas. Trabalhar com dados e gráficos para entender e ajustar o comportamento do sistema.
A92: Anos Finais | B92: 8º | C92: 3º | D92: 7 | E92: 13 e 14 | F92: EF69CO06 | G92: Comparar diferentes casos particulares (instâncias) de um mesmo problema, identificando as semelhanças e diferenças entre eles, e criar um algoritmo para resolver todos, fazendo uso de variáveis (parâmetros) para permitir o tratamento de todos os casos de forma genérica. | H92: Sistemas automatizados: lógica, integração e inovação | I92: IrrigaBot - Parte IV - Integrando um display ao protótipo. | J92: Lógica da automação baseada em sensores Integração sensor + atuador Prototipagem funcional Pensamento inovador e miniaturização | K92: Compreender a lógica da automação ao acionar mecanismos com base em dados de sensores. Integrar sensor, atuador, e display em uma programação funcional para um protótipo robótico. Representar soluções reais por meio da miniaturização e do pensamento inovador.
A93: Anos Finais | B93: 8º | C93: 4º | D93: 1 | E93: 1 e 2 | F93: EF09CO02 | H93: Pensamento Computacional: Resolução de problemas. | I93: Competição de Robótica I | J93: Introdução ao projeto e visão geral. | K93: Compreender a proposta do projeto e o objetivo final;
A94: Anos Finais | B94: 8º | C94: 4º | D94: 2 | E94: 3 e 4 | F94: EF09CO03 | H94: Cultura Digital: Ética e cooperação. | I94: Competição de Robótica III | J94: Regulamento, Ética e Critérios de Avaliação. | K94: Compreender as normas e a importância da postura ética no jogo.
A95: Anos Finais | B95: 8º | C95: 4º | D95: 3 | E95: 5 e 6 | F95: EF09CO04 | H95: Cultura Digital: Hardware e Periféricos. | I95: Competição de Robótica III | J95: Prototipagem de chassi e Instalação de Atuadores. | K95: Prototipar a estrutura do carrinho e instalar os motores (atuadores) do kit.
A96: Anos Finais | B96: 8º | C96: 4º | D96: 4 | E96: 7 e 8 | F96: EF09CO05 | H96: Pensamento Computacional: Algoritmos e Programação. | I96: Competição de Robótica VI | J96: Lógica de programação e rádio micro:bit. | K96: Desenvolver o algoritmo de controle remoto com estruturas condicionais.
A97: Anos Finais | B97: 8º | C97: 4º | D97: 5 | E97: 9 e 10 | F97: EF09CO06 | H97: Pensamento Computacional: Depuração e Testes. | I97: Competição de Robótica V | J97: Testes na arena de percurso e combate. | K97: Identificar falhas de hardware ou software através da experimentação.
A98: Anos Finais | B98: 8º | C98: 4º | D98: 6 | E98: 11 e 12 | F98: EF09CO07 | H98: Pensamento Computacional: Decomposição de Problemas. | I98: Competição de Robótica VI | J98: Ajustes mecânicos e refinamento lógico. | K98: Resolver problemas complexos de manobra e funcionamento. Ajustes mecânicos.
A99: Anos Finais | B99: 8º | C99: 4º | D99: 7 | E99: 13 e 14 | F99: EF09CO08 | H99: Cultura Digital: Integração Hardware/Software. | I99: Competição de Robótica VII | J99: Estética e Pitch (Explicação Técnica). | K99: Finalizar o design e consolidar o entendimento da interação hardware-software.
A100: Anos Finais | B100: 9º | C100: 3º | D100: 1 | E100: 1 e 2 | F100: EF69CO05 | G100: Identificar os recursos ou insumos necessários (entradas) para a resolução de problemas, bem como os resultados esperados (saídas), determinando os respectivos tipos de dados, e estabelecendo a definição de problema como uma relação entre entrada e saída. | H100: Sensores ambientais e coleta de dados | I100: Estação Meteorológica - Diagnóstico Inicial | J100: Instalação de sensores DHT11 e de luminosidade; coleta de dados ambientais via entrada analógica; estruturação e interpretação de variáveis físicas. | K100: Coletar dados ambientais com sensores embarcados, compreendendo os fenômenos físicos envolvidos e sua importância para o monitoramento climático.
A101: Anos Finais | B101: 9º | C101: 3º | D101: 2 | E101: 3 e 4 | F101: EF69CO07 | G101: Entender o processo de transmissão de dados, como a informação é quebrada em pedaços, transmitida em pacotes através de múltiplos equipamentos, e reconstruída no destino. | H101: Comunicação ambiental entre dispositivos | I101: Código da Missão - Rede de Comunicação Climática | J101: Comunicação via rádio entre micro:bits; envio de alertas ambientais remotos; monitoramento à distância em redes de sensores. | K101: Criar sistemas de monitoramento ambiental remoto com comunicação sem fio, simulando tecnologias de cidades inteligentes.
A102: Anos Finais | B102: 9º | C102: 3º | D102: 3 | E102: 5 e 6 | F102: EF69CO03 | G102: Descrever com precisão a solução de um problema, construindo o programa que implementa a solução descrita. | H102: Resposta automatizada sustentável | I102: A Vida Se Adapta! – Ações automatizadas verdes | J102: Automatização de respostas ambientais; acionamento de LEDs, ventoinhas ou lâmpadas com base em sensores; criação de lógica reativa. | K102: Criar sistemas autônomos que respondem a dados do ambiente para promover conforto e economia de energia.
A103: Anos Finais | B103: 9º | C103: 3º | D103: 4 | E103: 7 e 8 | F103: EF69CO12 | G103: Analisar o consumo de tecnologia na sociedade, compreendendo criticamente o caminho da produção dos recursos bem como aspectos ligados à obsolescência e à sustentabilidade. | H103: Eficiência energética e sensores | I103: Luz Inteligente ON – Energia sob Controle | J103: Programação de iluminação adaptativa com base na luminosidade; controle de LED com lógica condicional; simulação de eficiência energética. | K103: Programar sistemas de iluminação inteligente com base na luz ambiente, promovendo economia e eficiência energética.
A104: Anos Finais | B104: 9º | C104: 3º | D104: 5 | E104: 9 e 10 | F104: EF69CO01 | G104: Classificar informações, agrupando-as em coleções (conjuntos) e associando cada coleção a um ‘tipo de dado’. | H104: Representação e visualização ambiental | I104: Painel Climático - Exibição Ambiental em Tempo Real | J104: Exibição de dados ambientais em display I2C; leitura simultânea de múltiplos sensores; atualização dinâmica de variáveis no visor. | K104: Criar uma interface visual clara e funcional para leitura de variáveis ambientais, como temperatura e luz, por meio do display.
A105: Anos Finais | B105: 9º | C105: 3º | D105: 6 | E105: 11 e 12 | F105: EF69CO08 | G105: Compreender e utilizar diferentes formas de armazenar, manipular, compactar e recuperar arquivos, documentos e metadados. | H105: Integração de sensores e análise de dados | I105: Gráfico do Tempo – Datalogger do Clima | J105: Registro de dados; análise de gráficos climáticos; identificação de padrões ambientais e tendências. | K105: Utilizar o I2C para visualizar dados ambientais e interpretar padrões que ajudem na tomada de decisão ecológica.
A106: Anos Finais | B106: 9º | C106: 3º | D106: 7 | E106: 13 e 14 | F106: EF69CO04 | G106: Construir soluções de problemas usando a técnica de decomposição e automatizar tais soluções usando uma linguagem de programação. | H106: Projeto final: Simulação de Campo da ARCA 42 | I106: Missão Final: Miniestação ARCA 42 | J106: Integração de sensores, atuadores, display e rádio; construção de estação funcional com reação autônoma a variáveis ambientais. | K106: Integrar sensores, display, atuadores e comunicação para desenvolver um sistema que monitore e reaja às condições ambientais de forma sustentável.
A107: Anos Finais | B107: 9º | C107: 4º | D107: 1 | E107: 1 e 2 | F107: EF09CO02 | H107: Pensamento Computacional: Resolução de problemas. | I107: Competição de Robótica I | J107: Introdução ao projeto e visão geral. | K107: Apresentar o projeto, formar as equipes e entender as regras.
A108: Anos Finais | B108: 9º | C108: 4º | D108: 2 | E108: 3 e 4 | F108: EF09CO03 | H108: Cultura Digital: Ética e cooperação. | I108: Competição de Robótica II | J108: Regulamento, Ética e Critérios de Avaliação. | K108: Compreender as normas e a importância da postura ética no jogo.
A109: Anos Finais | B109: 9º | C109: 4º | D109: 3 | E109: 5 e 6 | F109: EF09CO04 | H109: Cultura Digital: Hardware e Periféricos. | I109: Competição de Robótica III | J109: Prototipagem de chassi e Instalação de Atuadores. | K109: Prototipar a estrutura do carrinho e instalar os motores (atuadores) do kit.
A110: Anos Finais | B110: 9º | C110: 4º | D110: 4 | E110: 7 e 8 | F110: EF09CO05 | H110: Pensamento Computacional: Algoritmos e Programação. | I110: Competição de Robótica VI | J110: Lógica de programação e rádio micro:bit. | K110: Desenvolver o algoritmo de controle remoto com estruturas condicionais.
A111: Anos Finais | B111: 9º | C111: 4º | D111: 5 | E111: 9 e 10 | F111: EF09CO06 | H111: Pensamento Computacional: Depuração e Testes. | I111: Competição de Robótica V | J111: Testes na arena de percurso e combate. | K111: Identificar falhas de hardware ou software através da experimentação.
A112: Anos Finais | B112: 9º | C112: 4º | D112: 6 | E112: 11 e 12 | F112: EF09CO07 | H112: Pensamento Computacional: Decomposição de Problemas. | I112: Competição de Robótica VI | J112: Ajustes mecânicos e refinamento lógico. | K112: Resolver problemas complexos de manobra e funcionamento. Ajustes mecânicos.
A113: Anos Finais | B113: 9º | C113: 4º | D113: 7 | E113: 13 e 14 | F113: EF09CO08 | H113: Cultura Digital: Integração Hardware/Software. | I113: Competição de Robótica VII | J113: Estética e Pitch (Explicação Técnica). | K113: Finalizar o design e consolidar o entendimento da interação hardware-software.

Sheet Tecnologia e Inovação
A1: Ciclo | B1: ANO/SÉRIE | C1: Bimestre | D1: Semana | E1: Data | F1: Unidade | G1: Aula Unidade | H1: Aula Sala | I1: Título | J1: Formato de Aula | K1: Objetivo | L1: Conteúdos | M1: Entrega de projeto | N1: Habilidade - BNCC Computação - código | O1: Habilidade - BNCC Computação - texto | P1: Habilidades - BNCC - código | Q1: Habilidades - BNCC - texto
A2: Anos Finais | B2: 6º ano | C2: 1º | D2: 1 | E2: 02 a 06/02 | F2: Introdução à computação: iniciando meus estudos | G2: 1 | H2: 1 | I2: Primeiros passos na tecnologia | J2: Material digital | K2: Identificar os três eixos principais que estruturam o ensino de tecnologia: pensamento computacional, mundo digital e cultura digital. Explicar com suas próprias palavras o que é pensamento computacional e quais são seus quatro pilares fundamentais: decomposição, padrões, abstração e algoritmo. Descrever os conceitos iniciais de pensamento computacional na idealização de um projeto tecnológico pessoal, como jogos, filmes ou aplicativos. | L2: Eixos estruturantes da tecnologia: pensamento computacional, mundo digital e cultura digital. Pilares do pensamento computacional: decomposição, reconhecimento de padrões, abstração e algoritmo. Planejamento inicial de projetos criativos em tecnologia com base em interesses pessoais e nas habilidades desejadas. | M2: n/a | N2: (EF03CO06) (EF05CO05) | O2: (EF03CO06) Reconhecer que, para um computador realizar tarefas, ele se comunica com o mundo exterior com o uso de interfaces físicas (dispositivos de entrada e saída). (EF05CO05) Identificar os componentes principais de um computador (dispositivos de entrada / saída, processadores e armazenamento). | P2: n/a | Q2: n/a
A3: Anos Finais | G3: 2 | H3: 2 | I3: Entrada e saída no computador | J3: Material digital | K3: Listar os principais dispositivos tecnológicos presentes no ambiente escolar, como computadores, teclados, monitores, projetores, microfones, entre outros. Explicar as diferenças entre dispositivos de entrada e dispositivos de saída, identificando suas funções no uso do computador. Classificar corretamente os dispositivos tecnológicos do ambiente escolar em dispositivos de entrada e dispositivos de saída. | L3: Identificação dos dispositivos tecnológicos na escola Dispositivos de entrada e suas funções (mouse, teclado, microfone, câmera) Dispositivos de saída e suas funções (monitor, impressora, projetor, caixa de som) | M3: n/a | N3: (EF03CO06) (EF05CO05) | O3: (EF03CO06) Reconhecer que, para um computador realizar tarefas, ele se comunica com o mundo exterior com o uso de interfaces físicas (dispositivos de entrada e saída). (EF05CO05) Identificar os componentes principais de um computador (dispositivos de entrada / saída, processadores e armazenamento). | P3: n/a | Q3: n/a
A4: Anos Finais | B4: 6º ano | C4: 1º | D4: 2 | E4: 09 a 13/02 | G4: 3 | H4: 3 | I4: Explorando o mouse | J4: Material digital | K4: Identificar as partes e funcionalidades básicas do mouse (botões esquerdo, direito e scroll) em um ambiente de programação visual. Explicar como utilizar o mouse para realizar ações como clicar, arrastar e soltar blocos no ambiente de programação Start Lab. Aplicar as funcionalidades do mouse na criação de programas simples com blocos, explorando a interação com o personagem e as ferramentas criativas do ambiente. | L4: Dispositivo de entrada: o mouse e suas funcionalidades (botão esquerdo, botão direito, scroll). Interação com blocos de programação no ambiente Start Lab (clicar, arrastar, soltar e deletar). Utilização das ferramentas criativas no Start Lab com o mouse (personalização do personagem e exploração dos blocos). | M4: n/a | N4: (EF03CO06) (EF05CO05) | O4: (EF03CO06) Reconhecer que, para um computador realizar tarefas, ele se comunica com o mundo exterior com o uso de interfaces físicas (dispositivos de entrada e saída). (EF05CO05) Identificar os componentes principais de um computador (dispositivos de entrada / saída, processadores e armazenamento). | P4: n/a | Q4: n/a
A5: Anos Finais | G5: 4 | H5: 4 | I5: Criando com Teclado | J5: Material digital | K5: Identificar os principais comandos do teclado na programação utilizando o Start Lab. Reconhecer a função do bloco diga para construir códigos criativos no Start Lab. Aplicar comandos do teclado e do mouse para elaborar mensagens interativas no ambiente de programação. | L5: Exploração do teclado (teclas especiais e caracteres). Uso da bandeira verde e blocos de Eventos (início do algoritmo). Personalização de mensagens com blocos da categoria Aparência. | M5: Sim | N5: (EF03CO06) (EF05CO05) | O5: (EF03CO06) Reconhecer que, para um computador realizar tarefas, ele se comunica com o mundo exterior com o uso de interfaces físicas (dispositivos de entrada e saída). (EF05CO05) Identificar os componentes principais de um computador (dispositivos de entrada / saída, processadores e armazenamento). | P5: n/a | Q5: n/a
A6: Anos Finais | B6: 6º ano | C6: 1º | D6: 3 | E6: 16 a 20/02 | F6: Semana Carvanal (Feriados e Planejamento/Replanejamento)
A7: Anos Finais | B7: 6º ano | C7: 1º | D7: 4 | E7: 23 a 27/02 | F7: Cultura Digital: uma aventura no fórum com Cody | G7: 1 | H7: 5 | I7: Explorando a cultura digital | J7: Material digital | K7: Identificar comportamentos respeitosos e inadequados nas interações digitais. Aplicar princípios de respeito e ética nas interações digitais. Analisar como as emoções digitais afetam as interações online. | L7: Reflexão sobre emoções nas interações digitais. Importância do comportamento respeitoso nos ambientes digitais. Regras de convivência pessoais. | M7: n/a | N7: (EF06CO09) (EF06CO10) | O7: (EF06CO09) - Apresentar conduta e linguagem apropriadas ao se comunicar em ambiente digital, considerando a ética e o respeito. (Nesta habilidade é importante que os alunos possam vivenciar, discutir e refletir sobre o comportamento ao se comunicar em ambiente digital, principalmente na internet, mas não limitada a ela (por exemplo também em aplicativos de conversa) (EF06CO10) Analisar o consumo de tecnologia na sociedade, compreendendo criticamente o caminho da produção dos recursos bem como aspectos ligados à obsolescência e a sustentabilidade. ​ | P7: n/a | Q7: n/a
G8: 2 | H8: 6 | I8: O poder das respostas | J8: Material digital | K8: Aplicar estratégias para responder de maneira respeitosa em interações digitais. Diferenciar respostas respeitosas de impulsivas em situações de comunicação digital. Avaliar o impacto das emoções nas respostas digitais. | L8: Conceito de pirâmide das emoções. Identificação de respostas impulsivas e reflexivas. Impacto das emoções nas interações digitais. | M8: n/a | N8: (EF06CO09) (EF06CO10) | O8: (EF06CO09) - Apresentar conduta e linguagem apropriadas ao se comunicar em ambiente digital, considerando a ética e o respeito. (Nesta habilidade é importante que os alunos possam vivenciar, discutir e refletir sobre o comportamento ao se comunicar em ambiente digital, principalmente na internet, mas não limitada a ela (por exemplo também em aplicativos de conversa) (EF06CO10) Analisar o consumo de tecnologia na sociedade, compreendendo criticamente o caminho da produção dos recursos bem como aspectos ligados à obsolescência e a sustentabilidade. ​ | P8: n/a | Q8: n/a
A9: Anos Finais | B9: 6º ano | C9: 1º | D9: 5 | E9: 02 a 06/03 | G9: 3 | H9: 7 | I9: Tirando dúvidas corretamente | J9: Material digital | K9: Aplicar estratégias para fazer perguntas claras no fórum. Analisar exemplos de perguntas inadequadas e suas melhorias. Criar perguntas objetivas e respeitosas no fórum. | L9: Como fazer perguntas claras e objetivas. Estratégias de criação de boas perguntas. Análise de perguntas inadequadas. | M9: n/a | N9: (EF06CO09) (EF06CO10) | O9: (EF06CO09) - Apresentar conduta e linguagem apropriadas ao se comunicar em ambiente digital, considerando a ética e o respeito. (Nesta habilidade é importante que os alunos possam vivenciar, discutir e refletir sobre o comportamento ao se comunicar em ambiente digital, principalmente na internet, mas não limitada a ela (por exemplo também em aplicativos de conversa) (EF06CO10) Analisar o consumo de tecnologia na sociedade, compreendendo criticamente o caminho da produção dos recursos bem como aspectos ligados à obsolescência e a sustentabilidade. ​ | P9: n/a | Q9: n/a
A10: Anos Finais | G10: 4 | H10: 8 | I10: Desvendando a Obsolescência Programada | J10: Material digital | K10: Compreender o conceito de obsolescência programada e seus impactos. Analisar as consequências ambientais do consumo excessivo de tecnologia. Propor soluções para reduzir o desperdício de aparelhos tecnológicos. | L10: Conceito de obsolescência programada. Impactos ambientais do lixo eletrônico. Soluções para consumo sustentável de tecnologia. | M10: n/a | N10: (EF06CO10) (EF06CO09) | O10: (EF06CO10) Analisar o consumo de tecnologia na sociedade, compreendendo criticamente o caminho da produção dos recursos bem como aspectos ligados à obsolescência e a sustentabilidade. (EF06CO09) - Apresentar conduta e linguagem apropriadas ao se comunicar em ambiente digital, considerando a ética e o respeito. (Nesta habilidade é importante que os alunos possam vivenciar, discutir e refletir sobre o comportamento ao se comunicar em ambiente digital, principalmente na internet, mas não limitada a ela (por exemplo também em aplicativos de conversa) | P10: n/a | Q10: n/a
A11: Anos Finais | B11: 6º ano | C11: 1º | D11: 6 | E11: 09 a 13/03 | G11: x | H11: 9 e 10 | I11: Avaliação da unidade: - Introdução à computação: iniciando meus estudos - Cultura Digital: uma aventura no fórum com Cody | M11: - | N11: - | O11: - | P11: -
A12: Anos Finais | B12: 6º ano | C12: 1º | D12: 7 | E12: 16 a 20/03 | F12: Lógica de programação: exploração criativa pt1 | G12: 1 | H12: 11 | I12: Iniciando a exploração | J12: Vídeo | K12: Selecionar personagens na biblioteca do ambiente de programação. Duplicar e editar personagens para criar novos personagens combinados. Renomear os personagens criados. | L12: Ambientalização no StartLab. Criação e edição de personagens. Composição e personalização de personagens. | M12: n/a | N12: (EF06CO02) | O12: (EF06CO02) Elaborar algoritmos que envolvam instruções sequenciais, de repetição e de seleção usando uma linguagem de programação. | P12: (EF69AR06) | Q12: (EF69AR06) Desenvolver processos de criação em artes visuais, com base em temas ou interesses artísticos, de modo individual, coletivo e colaborativo, fazendo uso de materiais, instrumentos e recursos convencionais, alternativos e digitais.
A13: Anos Finais | G13: 2 | H13: 12 | I13: Ensinando o computador | J13: Vídeo | K13: Conhecer a área de código do startlab. Localizar os blocos de eventos, controle e aparência. Implementar um algoritmo para alterar fantasias. | L13: Revisão e continuação do projeto anterior. Introdução à programação no StartLab. Criação de sequências de animação. | M13: n/a | N13: (EF06CO02) | O13: (EF06CO02) Elaborar algoritmos que envolvam instruções sequenciais, de repetição e de seleção usando uma linguagem de programação. | P13: (EF69AR06) | Q13: (EF69AR06) Desenvolver processos de criação em artes visuais, com base em temas ou interesses artísticos, de modo individual, coletivo e colaborativo, fazendo uso de materiais, instrumentos e recursos convencionais, alternativos e digitais.
A14: Anos Finais | B14: 6º ano | C14: 1º | D14: 8 | E14: 23 a 27/03 | G14: 3 | H14: 13 | I14: Reconhecendo padrões | J14: Vídeo | K14: Reconhecer padrões e automatizar tarefas. Depurar e refinar códigos para eficiência. Adicionar, modificar e nomear os personagens no StartLab. | L14: Introdução à programação no StartLab. Adicionar e modificar fantasias no Start Lab. Otimização de códigos com blocos de controle. | M14: n/a | N14: (EF06CO02) | O14: (EF06CO02) Elaborar algoritmos que envolvam instruções sequenciais, de repetição e de seleção usando uma linguagem de programação. | P14: (EF69AR06) | Q14: (EF69AR06) Desenvolver processos de criação em artes visuais, com base em temas ou interesses artísticos, de modo individual, coletivo e colaborativo, fazendo uso de materiais, instrumentos e recursos convencionais, alternativos e digitais.
A15: Anos Finais | G15: 4 | H15: 14 | I15: Explorando cenários | J15: Vídeo | K15: Diferenciar atores e cenários no StartLab. Modificar cenários no StartLab. Comparar e diferenciar ferramentas de edição de imagens. | L15: Seleção e adição de cenários Copiar e colar elementos visuais Diferenças nas ferramentas de edição | M15: Sim | N15: (EF06CO02) | O15: (EF06CO02) Elaborar algoritmos que envolvam instruções sequenciais, de repetição e de seleção usando uma linguagem de programação. | P15: (EF69AR06) | Q15: (EF69AR06) Desenvolver processos de criação em artes visuais, com base em temas ou interesses artísticos, de modo individual, coletivo e colaborativo, fazendo uso de materiais, instrumentos e recursos convencionais, alternativos e digitais.
A16: Anos Finais | B16: 6º ano | C16: 1º | D16: 9 | E16: 30/03 a 02/04 | G16: x | H16: 15 e 16 | I16: Semana para nivelamento | N16: - | O16: - | P16: - | Q16: -
A17: Anos Finais | B17: 6º ano | C17: 1º | D17: 10 | E17: 06 a 10/04 | G17: x | H17: 17 e 18 | I17: Avaliação das unidades: - Lógica de programação: exploração criativa pt 1 | M17: - | N17: - | O17: - | P17: -
A18: Anos Finais | B18: 6º ano | C18: 1º | D18: 11 | E18: 22 a 24/04 | G18: x | H18: 19 e 20 | I18: Recuperação do bimestre
A19: Anos Finais | B19: 6º ano | C19: 2º | D19: 12 | E19: 22 a 30/04 | F19: Lógica de programação: exploração criativa pt 2 | G19: 1 | H19: 21 | I19: Cenários criativos | J19: Vídeo | K19: Modificar cenários variados Implementar o algoritmo que trocam os cenários Compartilhar o projeto finalizado | L19: Criação de cenários personalizados. Programação da troca de cenários. Salvar e compartilhar o projeto. | M19: n/a | N19: (EF06CO02) | O19: (EF06CO02) Elaborar algoritmos que envolvam instruções sequenciais, de repetição e de seleção usando uma linguagem de programação. | P19: (EF69AR06) | Q19: (EF69AR06) Desenvolver processos de criação em artes visuais, com base em temas ou interesses artísticos, de modo individual, coletivo e colaborativo, fazendo uso de materiais, instrumentos e recursos convencionais, alternativos e digitais.
A20: Anos Finais | G20: 2 | H20: 22 | I20: Cartão animado | J20: Vídeo | K20: Utilizar atores e cenários para um cartão animado. Adicionar e organizar textos e personagens no cenário. Identificar boas práticas de segurança online. | L20: Escolha de temas para o cartão animado. Selecionar os atores do cartão Noções de segurança online, evitando o compartilhamento de informações pessoais. | M20: n/a | N20: (EF06CO02) | O20: (EF06CO02) Elaborar algoritmos que envolvam instruções sequenciais, de repetição e de seleção usando uma linguagem de programação. | P20: (EF69AR06) | Q20: (EF69AR06) Desenvolver processos de criação em artes visuais, com base em temas ou interesses artísticos, de modo individual, coletivo e colaborativo, fazendo uso de materiais, instrumentos e recursos convencionais, alternativos e digitais.
A21: Anos Finais | B21: 6º ano | C21: 2º | D21: 13 | E21: 04 a 08/05 | G21: 3 | H21: 23 | I21: Efeitos divertidos | J21: Vídeo | K21: Compreender como a alteração de efeitos visuais modifica o comportamento do personagem. Aplicar repetição com aumento e retorno de valores para controlar efeitos visuais. Analisar a necessidade de ajustar valores para manter a legibilidade e o funcionamento do algoritmo. | L21: Efeitos visuais em personagens (cor e turbilhão). Lógica de repetição com aumento e diminuição de valores. Controle de efeitos para manter o comportamento esperado do algoritmo. | M21: n/a | N21: (EF06CO02) | O21: (EF06CO02) Elaborar algoritmos que envolvam instruções sequenciais, de repetição e de seleção usando uma linguagem de programação. | P21: (EF69AR06) | Q21: (EF69AR06) Desenvolver processos de criação em artes visuais, com base em temas ou interesses artísticos, de modo individual, coletivo e colaborativo, fazendo uso de materiais, instrumentos e recursos convencionais, alternativos e digitais.
A22: Anos Finais | G22: 4 | H22: 24 | I22: Reutilização de Código | J22: Vídeo | K22: Reutilizar e adaptar códigos desenvolvidos previamente Experimentar diferentes efeitos visuais para os personagens. Utilizar a lógica de repetição com aumento positiva e negativa para criar efeitos dinâmicos. | L22: Algoritmos com repetições positivas e negativas Uso de blocos de aparência para modificar efeitos visuais. Abstração e reutilização de códigos em diferentes atores do projeto. | M22: Sim | N22: (EF06CO02) | O22: (EF06CO02) Elaborar algoritmos que envolvam instruções sequenciais, de repetição e de seleção usando uma linguagem de programação. | P22: (EF69AR06) | Q22: (EF69AR06) Desenvolver processos de criação em artes visuais, com base em temas ou interesses artísticos, de modo individual, coletivo e colaborativo, fazendo uso de materiais, instrumentos e recursos convencionais, alternativos e digitais.
A23: Anos Finais | B23: 6º ano | C23: 2º | D23: 14 | E23: 11 a 15/05 | G23: x | H23: 25 e 26 | I23: Avaliação das unidades: - Lógica de programação: exploração criativa pt 2 | M23: - | N23: - | O23: - | P23: -
A24: Anos Finais | B24: 6º ano | C24: 2º | D24: 15 | E24: 18 a 22/05 | F24: Tipos de dados: criando uma coleção de máquinas | G24: 1 | H24: 27 | I24: Criando um concurso de máquinas | J24: Material digital | K24: Compreender a proposta do projeto "Concurso de Máquinas". Identificar a necessidade de organizar itens em coleções. Planejar a seleção de itens reais e a criação de um item fictício para o concurso. | L24: O que é uma coleção Coleção de elementos Planejamento de Projeto Interativo | M24: n/a | N24: (EF06CO01) | O24: (EF06CO01) Classificar informações, agrupando-as em coleções (conjuntos) e associando cada coleção a um ‘tipo de dados | P24: n/a | Q24: n/a
G25: 2 | H25: 28 | I25: Criando fantasias | J25: Material digital | K25: Utilizar as ferramentas de desenho do Start Lab para criar elementos visuais. Nomear fantasias de atores de forma significativa. Compreender que elementos podem ser representados por números, textos e imagens | L25: Ferramentas de desenho (Start Lab) Representação de Dados (número, texto, imagem) Organização de Fantasias/Atores | M25: n/a | N25: (EF06CO01) | O25: (EF06CO01) Classificar informações, agrupando-as em coleções (conjuntos) e associando cada coleção a um ‘tipo de dados | P25: n/a | Q25: n/a
A26: Anos Finais | B26: 6º ano | C26: 2º | D26: 16 | E26: 25 a 29/05 | G26: 3 | H26: 29 | I26: Sorteando elementos | J26: Vídeo | K26: Aplicar blocos de evento para iniciar a execução do programa. Utilizar o bloco "Mudar fantasia para" para exibir fantasias. Implementar o bloco "número aleatório" para sortear imagens dinamicamente. | L26: Blocos de Eventos (bandeira verde) Blocos de Aparência (Mudar fantasia para) Bloco de operadores (número aleatório) | M26: n/a | N26: (EF06CO05) | O26: (EF06CO05) Identificar os recursos ou insumos necessários (entradas) para a resolução de problemas, bem como os resultados esperados (saídas), determinando os respectivos tipos de dados, e estabelecendo a definição de problema como uma relação entre entrada e saída. | P26: n/a | Q26: n/a
G27: 4 | H27: 30 | I27: Adicionando interação | J27: Vídeo | K27: Criar um botão interativo para iniciar a interação do usuário. Utilizar blocos de "Diga" para exibir mensagens de boas-vindas. Implementar o bloco "Pergunte e Espere" para coletar respostas do usuário. | L27: Criação de Botões Blocos de Aparência (Diga) Sensores (Pergunte e Espere, Resposta) | M27: n/a | N27: (EF06CO05) | O27: (EF06CO05) Identificar os recursos ou insumos necessários (entradas) para a resolução de problemas, bem como os resultados esperados (saídas), determinando os respectivos tipos de dados, e estabelecendo a definição de problema como uma relação entre entrada e saída. | P27: n/a | Q27: n/a
A28: Anos Finais | B28: 6º ano | C28: 2º | D28: 17 | E28: 01 a 03/06 | G28: x | H28: 31 e 32 | I28: Semana para nivelamento | N28: - | O28: - | P28: - | Q28: -
A29: Anos Finais | B29: 6º ano | C29: 2º | D29: 18 | E29: 08 a 12/06 | F29: Tipos de dados: criando uma coleção de máquinas | G29: 5 | H29: 33 | I29: Validando respostas | J29: Vídeo | K29: Aplicar o bloco condicional "Se Então" para verificar condições. Utilizar operadores de comparação (contém) para validar respostas. Compreender o tipo de dado booleano (verdadeiro/falso). | L29: Estruturas condicionais (Se Então) Operadores de comparação (contém) Tipo de dado Booleano | M29: n/a | N29: (EF06CO05) | O29: (EF06C001) Classificar informações, agrupando-as em coleções (conjuntos) e associando cada coleção a um tipo de dados. | P29: n/a | Q29: n/a
G30: 6 | H30: 34 | I30: Comparando respostas | J30: Vídeo | K30: Diferenciar o uso dos operadores "igualdade" e "contém". Utilizar o sensor "nome da fantasia de ator" para validação dinâmica. Ajustar a lógica de validação para considerar variações na entrada do usuário. | L30: Operador de igualdade Sensor "Nome da Fantasia" Validação dinâmica de respostas | M30: n/a | N30: (EF06CO05) (EF06C001) | O30: (EF06C001) Classificar informações, agrupando-as em coleções (conjuntos) e associando cada coleção a um tipo de dados. (EF06C005) Identificar os insumos necessários (entradas) para a resolução de problemas, bem como os resultados esperados (saídas), determinando os respectivos tipos de dados, estabelecendo a definição de problema como uma relação entre entrada e saída. | P30: n/a | Q30: n/a
A31: Anos Finais | B31: 6º ano | C31: 2º | D31: 19 | E31: 15 a 19/06 | G31: 7 | H31: 35 | I31: Melhorando a experiência | J31: Vídeo | K31: Implementar o bloco condicional "Se então senão" para fornecer feedback completo. Criar mensagens personalizadas para acertos e erros do usuário. Desenvolver abordagem respeitosa e incentivadora ao lidar com erros. | L31: Blocos de Controle ("Se então senão") Feedback ao usuário Design de interação (UX) | M31: n/a | N31: (EF06CO05) | O31: (EF06CO05) Identificar os recursos ou insumos necessários (entradas) para a resolução de problemas, bem como os resultados esperados (saídas), determinando os respectivos tipos de dados, e estabelecendo a definição de problema como uma relação entre entrada e saída. | P31: n/a | Q31: n/a
G32: 8 | H32: 36 | I32: Reflexão | J32: Material digital | K32: Refletir sobre a conexão dos novos conhecimentos com saberes prévios. Identificar novas ideias e a ampliação do pensamento proporcionada pela unidade. Formular perguntas e desafios futuros para aprofundar o aprendizado. | L32: Revisão de conceitos (coleções, tipos de dados, condicionais) Processo de aprendizagem e reflexão Identificação de desafios e próximos passos | M32: Sim | N32: (EF06CO05) | O32: (EF06CO05) Identificar os recursos ou insumos necessários (entradas) para a resolução de problemas, bem como os resultados esperados (saídas), determinando os respectivos tipos de dados, e estabelecendo a definição de problema como uma relação entre entrada e saída. | P32: n/a | Q32: n/a
A33: Anos Finais | B33: 6º ano | C33: 2º | D33: 20 | E33: 22 a 26/06 | G33: x | H33: 37 e 38 | I33: Avaliação da unidade: - Tipos de dados: criando uma coleção de máquinas | M33: - | N33: - | O33: - | P33: -
A34: Anos Finais | B34: 6º ano | C34: 2º | D34: 21 | E34: 27 a 31/07 | G34: x | H34: 39 e 40 | I34: Recuperação do bimestre
